Workbook

Sheet 2025
A1: TIPO DE SOLICITUD | B1: NOMBRE | C1: ENTIDAD | D1: ASUNTO | E1: RADICADO | F1: FECHA DE INGRESO DE LA SOLICITUD | G1: HORA | H1: ANEXOS | I1: PROCESO RESPONSABLE | J1: TERMINO | K1: POSIBLES DIAS RESTANTES | L1: FECHA DE VENCIMIENTO | M1: RADICADO POR | N1: ALERTA | O1: ALERTA 2 | P1: CONSECUTIVO | Q1: FECHA DE SALIDA | R1: DIAS QUE LE SOBRARON
A2: OTRO | B2: MAYRA ARTUNDUAGA | C2: ESAC | D2: DESAFILIACIONES | E2: 1 | F2: 46024 | G2: FALSE | H2: FALSE | I2: COMERCIAL | J2: =IF(A2="INFORMACIÓN O DOCUMENTOS", 10, IF(A2="CONSULTA", 30, IF(A2="FACTURACIÓN Y COBROS", 15, IF(A2="VINCULACIÓN Y DESVINCULACIÓN", 15, IF(A2="NO ES DE NUESTRA COMPETENCIA", 5, IF(A2="OTRO", 15, "")))))) -> 15 | K2: =IF(AND(F2<>"", L2<>""), NETWORKDAYS(TODAY(), L2-1, FESTIVOS!A$1:A$55), "") -> -97 | L2: =IF(AND(F2<>"", J2<>""), WORKDAY(F2, J2, FESTIVOS!A$1:A$55), "") -> 46048 | M2: LAURA GIRALDO | N2: 0 | O2: =IF(OR(K2="", J2=""), "", IF(K2<0, "Vencido", IF(K2>(J2/2), "Supere la mitad", "Bajo la mitad"))) -> Vencido | P2: CE-GC-007 | Q2: 46038 | R2: =IF(OR(Q2="", L2=""), "", NETWORKDAYS(L2, Q2, FESTIVOS!A1:A55)) -> -7
A3: OTRO | B3: MAYRA ARTUNDUAGA | C3: ESAC | D3: DESAFILIACIONES | E3: 2 | F3: 46024 | G3: FALSE | H3: FALSE | I3: COMERCIAL | J3: =IF(A3="INFORMACIÓN O DOCUMENTOS", 10, IF(A3="CONSULTA", 30, IF(A3="FACTURACIÓN Y COBROS", 15, IF(A3="VINCULACIÓN Y DESVINCULACIÓN", 15, IF(A3="NO ES DE NUESTRA COMPETENCIA", 5, IF(A3="OTRO", 15, "")))))) -> 15 | K3: =IF(AND(F3<>"", L3<>""), NETWORKDAYS(TODAY(), L3-1, FESTIVOS!A$1:A$55), "") -> -97 | L3: =IF(AND(F3<>"", J3<>""), WORKDAY(F3, J3, FESTIVOS!A$1:A$55), "") -> 46048 | M3: LAURA GIRALDO | N3: =IF(K3="", "", MAX(0, K3 - (TODAY() - TODAY()))) -> 0 | O3: =IF(OR(K3="", J3=""), "", IF(K3<0, "Vencido", IF(K3>(J3/2), "Supere la mitad", "Bajo la mitad"))) -> Vencido | P3: CE-GC-008 | Q3: 46041 | R3: =IF(OR(Q3="", L3=""), "", NETWORKDAYS(L3, Q3, FESTIVOS!A2:A56)) -> -6
A4: OTRO | B4: CARLOS ALMERO VIDEL | C4: USUARIO | D4: COTIZACIÓN | E4: 3 | F4: 46027 | G4: FALSE | H4: FALSE | I4: COMERCIAL | J4: =IF(A4="INFORMACIÓN O DOCUMENTOS", 10, IF(A4="CONSULTA", 30, IF(A4="FACTURACIÓN Y COBROS", 15, IF(A4="VINCULACIÓN Y DESVINCULACIÓN", 15, IF(A4="NO ES DE NUESTRA COMPETENCIA", 5, IF(A4="OTRO", 15, "")))))) -> 15 | K4: =IF(AND(F4<>"", L4<>""), NETWORKDAYS(TODAY(), L4-1, FESTIVOS!A$1:A$55), "") -> -97 | L4: =IF(AND(F4<>"", J4<>""), WORKDAY(F4, J4, FESTIVOS!A$1:A$55), "") -> 46049 | M4: LAURA GIRALDO | N4: =IF(K4="", "", MAX(0, K4 - (TODAY() - TODAY()))) -> 0 | O4: =IF(OR(K4="", J4=""), "", IF(K4<0, "Vencido", IF(K4>(J4/2), "Supere la mitad", "Bajo la mitad"))) -> Vencido | P4: CE-GC-0011 | Q4: 46029 | R4: =IF(OR(Q4="", L4=""), "", NETWORKDAYS(L4, Q4, FESTIVOS!A3:A57)) -> -14 | S4: si salen en engativo sobraron
A5: OTRO | B5: MAYRA ARTUNDUAGA | C5: ESAC | D5: DESAFILIACIONES | E5: 4 | F5: 46027 | G5: FALSE | H5: FALSE | I5: COMERCIAL | J5: =IF(A5="INFORMACIÓN O DOCUMENTOS", 10, IF(A5="CONSULTA", 30, IF(A5="FACTURACIÓN Y COBROS", 15, IF(A5="VINCULACIÓN Y DESVINCULACIÓN", 15, IF(A5="NO ES DE NUESTRA COMPETENCIA", 5, IF(A5="OTRO", 15, "")))))) -> 15 | K5: =IF(AND(F5<>"", L5<>""), NETWORKDAYS(TODAY(), L5-1, FESTIVOS!A$1:A$55), "") -> -97 | L5: =IF(AND(F5<>"", J5<>""), WORKDAY(F5, J5, FESTIVOS!A$1:A$55), "") -> 46049 | M5: LAURA GIRALDO | N5: =IF(K5="", "", MAX(0, K5 - (TODAY() - TODAY()))) -> 0 | O5: =IF(OR(K5="", J5=""), "", IF(K5<0, "Vencido", IF(K5>(J5/2), "Supere la mitad", "Bajo la mitad"))) -> Vencido | P5: CE-GC-0010 | Q5: 46038 | R5: =IF(OR(Q5="", L5=""), "", NETWORKDAYS(L5, Q5, FESTIVOS!A4:A58)) -> -8 | S5: si salen positivos nos pasamos
A6: OTRO | B6: EMITIDO POR LA ALCALDIA | C6: ALCALDIA | D6: TRASLADO POR COMPETENCIA -MARIA MARGARITALOPEZ GOMEZ | E6: 5 | F6: 46028 | G6: FALSE | H6: FALSE | I6: COMERCIAL | J6: =IF(A6="INFORMACIÓN O DOCUMENTOS", 10, IF(A6="CONSULTA", 30, IF(A6="FACTURACIÓN Y COBROS", 15, IF(A6="VINCULACIÓN Y DESVINCULACIÓN", 15, IF(A6="NO ES DE NUESTRA COMPETENCIA", 5, IF(A6="OTRO", 15, "")))))) -> 15 | K6: =IF(AND(F6<>"", L6<>""), NETWORKDAYS(TODAY(), L6-1, FESTIVOS!A$1:A$55), "") -> -96 | L6: =IF(AND(F6<>"", J6<>""), WORKDAY(F6, J6, FESTIVOS!A$1:A$55), "") -> 46050 | M6: LAURA GIRALDO | N6: =IF(K6="", "", MAX(0, K6 - (TODAY() - TODAY()))) -> 0 | O6: =IF(OR(K6="", J6=""), "", IF(K6<0, "Vencido", IF(K6>(J6/2), "Supere la mitad", "Bajo la mitad"))) -> Vencido | P6: CE-GC-0055 | Q6: 46038 | R6: =IF(OR(Q6="", L6=""), "", NETWORKDAYS(L6, Q6, FESTIVOS!A5:A59)) -> -9
A7: OTRO | B7: KARLA JOHANA LISCANO CORREA | C7: ALCALDIA | D7: ACTA DEL COMITÉ DE CONOCIMIENTO DE RIESGO | E7: 6 | F7: 46028 | G7: FALSE | H7: FALSE | I7: COMERCIAL | J7: =IF(A7="INFORMACIÓN O DOCUMENTOS", 10, IF(A7="CONSULTA", 30, IF(A7="FACTURACIÓN Y COBROS", 15, IF(A7="VINCULACIÓN Y DESVINCULACIÓN", 15, IF(A7="NO ES DE NUESTRA COMPETENCIA", 5, IF(A7="OTRO", 15, "")))))) -> 15 | K7: =IF(AND(F7<>"", L7<>""), NETWORKDAYS(TODAY(), L7-1, FESTIVOS!A$1:A$55), "") -> -96 | L7: =IF(AND(F7<>"", J7<>""), WORKDAY(F7, J7, FESTIVOS!A$1:A$55), "") -> 46050 | M7: LAURA GIRALDO | N7: =IF(K7="", "", MAX(0, K7 - (TODAY() - TODAY()))) -> 0 | O7: =IF(OR(K7="", J7=""), "", IF(K7<0, "Vencido", IF(K7>(J7/2), "Supere la mitad", "Bajo la mitad"))) -> Vencido | P7: NO REQUIERE RESPUESTA | Q7: FALSE | R7: =IF(OR(Q7="", L7=""), "", NETWORKDAYS(L7, Q7, FESTIVOS!A6:A60)) -> #VALUE!
A8: OTRO | B8: ESTHER JULIA GOMEZ | C8: USUARIO | D8: DERECHO DE PETICIÓN | E8: 7 | F8: 46028 | G8: FALSE | H8: FALSE | I8: COMERCIAL | J8: =IF(A8="INFORMACIÓN O DOCUMENTOS", 10, IF(A8="CONSULTA", 30, IF(A8="FACTURACIÓN Y COBROS", 15, IF(A8="VINCULACIÓN Y DESVINCULACIÓN", 15, IF(A8="NO ES DE NUESTRA COMPETENCIA", 5, IF(A8="OTRO", 15, "")))))) -> 15 | K8: =IF(AND(F8<>"", L8<>""), NETWORKDAYS(TODAY(), L8-1, FESTIVOS!A$1:A$55), "") -> -96 | L8: =IF(AND(F8<>"", J8<>""), WORKDAY(F8, J8, FESTIVOS!A$1:A$55), "") -> 46050 | M8: LAURA GIRALDO | N8: =IF(K8="", "", MAX(0, K8 - (TODAY() - TODAY()))) -> 0 | O8: =IF(OR(K8="", J8=""), "", IF(K8<0, "Vencido", IF(K8>(J8/2), "Supere la mitad", "Bajo la mitad"))) -> Vencido | P8: CE-GC-0113 | Q8: 46050 | R8: =IF(OR(Q8="", L8=""), "", NETWORKDAYS(L8, Q8, FESTIVOS!A7:A61)) -> 1
A9: OTRO | B9: OMAR JOSE MAESTRE FELIZZOLA | C9: SUPER | D9: REMISIÓN MESA DE TRABAJO | E9: 8 | F9: 46028 | G9: FALSE | H9: FALSE | I9: JURÍDICA | J9: =IF(A9="INFORMACIÓN O DOCUMENTOS", 10, IF(A9="CONSULTA", 30, IF(A9="FACTURACIÓN Y COBROS", 15, IF(A9="VINCULACIÓN Y DESVINCULACIÓN", 15, IF(A9="NO ES DE NUESTRA COMPETENCIA", 5, IF(A9="OTRO", 15, "")))))) -> 15 | K9: =IF(AND(F9<>"", L9<>""), NETWORKDAYS(TODAY(), L9-1, FESTIVOS!A$1:A$55), "") -> -96 | L9: =IF(AND(F9<>"", J9<>""), WORKDAY(F9, J9, FESTIVOS!A$1:A$55), "") -> 46050 | M9: LAURA GIRALDO | N9: =IF(K9="", "", MAX(0, K9 - (TODAY() - TODAY()))) -> 0 | O9: =IF(OR(K9="", J9=""), "", IF(K9<0, "Vencido", IF(K9>(J9/2), "Supere la mitad", "Bajo la mitad"))) -> Vencido | P9: FALSE | Q9: FALSE | R9: =IF(OR(Q9="", L9=""), "", NETWORKDAYS(L9, Q9, FESTIVOS!A8:A62)) -> #VALUE!
A10: OTRO | B10: ADRIANA GUZMÁN BUITRAGO | C10: USUARIO DE SERVINTEGRAL | D10: DERECHO DE PETICIÓN | E10: 9 | F10: 46028 | G10: FALSE | H10: FALSE | I10: COMERCIAL | J10: =IF(A10="INFORMACIÓN O DOCUMENTOS", 10, IF(A10="CONSULTA", 30, IF(A10="FACTURACIÓN Y COBROS", 15, IF(A10="VINCULACIÓN Y DESVINCULACIÓN", 15, IF(A10="NO ES DE NUESTRA COMPETENCIA", 5, IF(A10="OTRO", 15, "")))))) -> 15 | K10: =IF(AND(F10<>"", L10<>""), NETWORKDAYS(TODAY(), L10-1, FESTIVOS!A$1:A$55), "") -> -96 | L10: =IF(AND(F10<>"", J10<>""), WORKDAY(F10, J10, FESTIVOS!A$1:A$55), "") -> 46050 | M10: LAURA GIRALDO | N10: =IF(K10="", "", MAX(0, K10 - (TODAY() - TODAY()))) -> 0 | O10: =IF(OR(K10="", J10=""), "", IF(K10<0, "Vencido", IF(K10>(J10/2), "Supere la mitad", "Bajo la mitad"))) -> Vencido | P10: CE-GC-0065 | Q10: 46041 | R10: =IF(OR(Q10="", L10=""), "", NETWORKDAYS(L10, Q10, FESTIVOS!A9:A63)) -> -8
A11: OTRO | B11: GINA PAOLA RIVERA CHACON | C11: USUARIO DE SERVINTEGRAL | D11: RESPUESTA DE VINCULACIÓN | E11: 10 | F11: 46029 | G11: FALSE | H11: FALSE | I11: COMERCIAL | J11: =IF(A11="INFORMACIÓN O DOCUMENTOS", 10, IF(A11="CONSULTA", 30, IF(A11="FACTURACIÓN Y COBROS", 15, IF(A11="VINCULACIÓN Y DESVINCULACIÓN", 15, IF(A11="NO ES DE NUESTRA COMPETENCIA", 5, IF(A11="OTRO", 15, "")))))) -> 15 | K11: =IF(AND(F11<>"", L11<>""), NETWORKDAYS(TODAY(), L11-1, FESTIVOS!A$1:A$55), "") -> -95 | L11: =IF(AND(F11<>"", J11<>""), WORKDAY(F11, J11, FESTIVOS!A$1:A$55), "") -> 46051 | M11: LAURA GIRALDO | N11: =IF(K11="", "", MAX(0, K11 - (TODAY() - TODAY()))) -> 0 | O11: =IF(OR(K11="", J11=""), "", IF(K11<0, "Vencido", IF(K11>(J11/2), "Supere la mitad", "Bajo la mitad"))) -> Vencido | P11: CE-GC-0012 | Q11: 46037 | R11: =IF(OR(Q11="", L11=""), "", NETWORKDAYS(L11, Q11, FESTIVOS!A10:A64)) -> -11
A12: OTRO | B12: EQUIPO DE VERIFICACIÓN | C12: USUARIO DE SERVINTEGRAL | D12: ACTUALIZACIÓN DE INFORMACIÓN | E12: 11 | F12: 46029 | G12: FALSE | H12: FALSE | I12: JURÍDICA | J12: =IF(A12="INFORMACIÓN O DOCUMENTOS", 10, IF(A12="CONSULTA", 30, IF(A12="FACTURACIÓN Y COBROS", 15, IF(A12="VINCULACIÓN Y DESVINCULACIÓN", 15, IF(A12="NO ES DE NUESTRA COMPETENCIA", 5, IF(A12="OTRO", 15, "")))))) -> 15 | K12: =IF(AND(F12<>"", L12<>""), NETWORKDAYS(TODAY(), L12-1, FESTIVOS!A$1:A$55), "") -> -95 | L12: =IF(AND(F12<>"", J12<>""), WORKDAY(F12, J12, FESTIVOS!A$1:A$55), "") -> 46051 | M12: LAURA GIRALDO | N12: =IF(K12="", "", MAX(0, K12 - (TODAY() - TODAY()))) -> 0 | O12: =IF(OR(K12="", J12=""), "", IF(K12<0, "Vencido", IF(K12>(J12/2), "Supere la mitad", "Bajo la mitad"))) -> Vencido | P12: FALSE | Q12: FALSE | R12: =IF(OR(Q12="", L12=""), "", NETWORKDAYS(L12, Q12, FESTIVOS!A11:A65)) -> #VALUE!
A13: OTRO | B13: MARIA GLORIA CUELLAR LOZANO | C13: USUARIO DE SERVINTEGRAL | D13: INMUEBLE DESOCUPADO | E13: 12 | F13: 46030 | G13: FALSE | H13: FALSE | I13: COMERCIAL | J13: =IF(A13="INFORMACIÓN O DOCUMENTOS", 10, IF(A13="CONSULTA", 30, IF(A13="FACTURACIÓN Y COBROS", 15, IF(A13="VINCULACIÓN Y DESVINCULACIÓN", 15, IF(A13="NO ES DE NUESTRA COMPETENCIA", 5, IF(A13="OTRO", 15, "")))))) -> 15 | K13: =IF(AND(F13<>"", L13<>""), NETWORKDAYS(TODAY(), L13-1, FESTIVOS!A$1:A$55), "") -> -94 | L13: =IF(AND(F13<>"", J13<>""), WORKDAY(F13, J13, FESTIVOS!A$1:A$55), "") -> 46052 | M13: LAURA GIRALDO | N13: =IF(K13="", "", MAX(0, K13 - (TODAY() - TODAY()))) -> 0 | O13: =IF(OR(K13="", J13=""), "", IF(K13<0, "Vencido", IF(K13>(J13/2), "Supere la mitad", "Bajo la mitad"))) -> Vencido | P13: CE-GC-0033 | Q13: 46036 | R13: =IF(OR(Q13="", L13=""), "", NETWORKDAYS(L13, Q13, FESTIVOS!A12:A66)) -> -13
A14: OTRO | B14: DIANA MARCELA PERDOMO BELTRÁN | C14: SUPER | D14: Respuesta al radicado de entrada SSPD No. 20255294845332 de fecha 20 de noviembre de 2025 - Respuesta a solicitud con radicado interno 2529 del 4 de noviembre de 2025. “Radicado CE-GT-2420 (Respuesta a Radicado No. 2437 del 20 de octubre de 2025.Requerimiento Ordinario No. 49 - 3458)” | E14: 13 | F14: 46030 | G14: FALSE | H14: FALSE | I14: JURÍDICA | J14: =IF(A14="INFORMACIÓN O DOCUMENTOS", 10, IF(A14="CONSULTA", 30, IF(A14="FACTURACIÓN Y COBROS", 15, IF(A14="VINCULACIÓN Y DESVINCULACIÓN", 15, IF(A14="NO ES DE NUESTRA COMPETENCIA", 5, IF(A14="OTRO", 15, "")))))) -> 15 | K14: =IF(AND(F14<>"", L14<>""), NETWORKDAYS(TODAY(), L14-1, FESTIVOS!A$1:A$55), "") -> -94 | L14: =IF(AND(F14<>"", J14<>""), WORKDAY(F14, J14, FESTIVOS!A$1:A$55), "") -> 46052 | M14: LAURA GIRALDO | N14: =IF(K14="", "", MAX(0, K14 - (TODAY() - TODAY()))) -> 0 | O14: =IF(OR(K14="", J14=""), "", IF(K14<0, "Vencido", IF(K14>(J14/2), "Supere la mitad", "Bajo la mitad"))) -> Vencido | P14: CE-GC-0033 | Q14: 46036 | R14: =IF(OR(Q14="", L14=""), "", NETWORKDAYS(L14, Q14, FESTIVOS!A13:A67)) -> -13
A15: OTRO | B15: ISMAEL SILVA ALVAREZ | C15: GAS CAQUETA | D15: SOLICITUD DE CERTIFICADO | E15: 14 | F15: 46030 | G15: FALSE | H15: FALSE | I15: COMERCIAL | J15: =IF(A15="INFORMACIÓN O DOCUMENTOS", 10, IF(A15="CONSULTA", 30, IF(A15="FACTURACIÓN Y COBROS", 15, IF(A15="VINCULACIÓN Y DESVINCULACIÓN", 15, IF(A15="NO ES DE NUESTRA COMPETENCIA", 5, IF(A15="OTRO", 15, "")))))) -> 15 | K15: =IF(AND(F15<>"", L15<>""), NETWORKDAYS(TODAY(), L15-1, FESTIVOS!A$1:A$55), "") -> -94 | L15: =IF(AND(F15<>"", J15<>""), WORKDAY(F15, J15, FESTIVOS!A$1:A$55), "") -> 46052 | M15: LAURA GIRALDO | N15: =IF(K15="", "", MAX(0, K15 - (TODAY() - TODAY()))) -> 0 | O15: =IF(OR(K15="", J15=""), "", IF(K15<0, "Vencido", IF(K15>(J15/2), "Supere la mitad", "Bajo la mitad"))) -> Vencido | P15: CE-GC-0014 | Q15: 46035 | R15: =IF(OR(Q15="", L15=""), "", NETWORKDAYS(L15, Q15, FESTIVOS!A14:A68)) -> -14
A16: OTRO | B16: LORENA CASTAÑO | C16: SAMAMB | D16: CARACTERIZACIÓN | E16: 15 | F16: 46030 | G16: FALSE | H16: FALSE | I16: RESIDUOS | J16: =IF(A16="INFORMACIÓN O DOCUMENTOS", 10, IF(A16="CONSULTA", 30, IF(A16="FACTURACIÓN Y COBROS", 15, IF(A16="VINCULACIÓN Y DESVINCULACIÓN", 15, IF(A16="NO ES DE NUESTRA COMPETENCIA", 5, IF(A16="OTRO", 15, "")))))) -> 15 | K16: =IF(AND(F16<>"", L16<>""), NETWORKDAYS(TODAY(), L16-1, FESTIVOS!A$1:A$55), "") -> -94 | L16: =IF(AND(F16<>"", J16<>""), WORKDAY(F16, J16, FESTIVOS!A$1:A$55), "") -> 46052 | M16: LAURA GIRALDO | N16: =IF(K16="", "", MAX(0, K16 - (TODAY() - TODAY()))) -> 0 | O16: =IF(OR(K16="", J16=""), "", IF(K16<0, "Vencido", IF(K16>(J16/2), "Supere la mitad", "Bajo la mitad"))) -> Vencido | P16: NO REQUIERE RESPUESTA | Q16: FALSE | R16: =IF(OR(Q16="", L16=""), "", NETWORKDAYS(L16, Q16, FESTIVOS!A15:A69)) -> #VALUE!
A17: OTRO | B17: LORENA CASTAÑO | C17: SAMAMB | D17: PROPUESTA | E17: 16 | F17: 46030 | G17: FALSE | H17: FALSE | I17: COMERCIAL | J17: =IF(A17="INFORMACIÓN O DOCUMENTOS", 10, IF(A17="CONSULTA", 30, IF(A17="FACTURACIÓN Y COBROS", 15, IF(A17="VINCULACIÓN Y DESVINCULACIÓN", 15, IF(A17="NO ES DE NUESTRA COMPETENCIA", 5, IF(A17="OTRO", 15, "")))))) -> 15 | K17: =IF(AND(F17<>"", L17<>""), NETWORKDAYS(TODAY(), L17-1, FESTIVOS!A$1:A$55), "") -> -94 | L17: =IF(AND(F17<>"", J17<>""), WORKDAY(F17, J17, FESTIVOS!A$1:A$55), "") -> 46052 | M17: LAURA GIRALDO | N17: =IF(K17="", "", MAX(0, K17 - (TODAY() - TODAY()))) -> 0 | O17: =IF(OR(K17="", J17=""), "", IF(K17<0, "Vencido", IF(K17>(J17/2), "Supere la mitad", "Bajo la mitad"))) -> Vencido | P17: NO REQUIERE RESPUESTA | Q17: FALSE | R17: =IF(OR(Q17="", L17=""), "", NETWORKDAYS(L17, Q17, FESTIVOS!A16:A70)) -> #VALUE!
A18: OTRO | B18: FREDY HERNAN TEJADA | C18: ELECTROCAQUETA | D18: Respuesta a oficio CE-GC-0002 del 05-01-2026 con Rad interno No 2026-1-1-75 del 06-01-2026 | E18: 17 | F18: 46030 | G18: FALSE | H18: FALSE | I18: COMERCIAL | J18: =IF(A18="INFORMACIÓN O DOCUMENTOS", 10, IF(A18="CONSULTA", 30, IF(A18="FACTURACIÓN Y COBROS", 15, IF(A18="VINCULACIÓN Y DESVINCULACIÓN", 15, IF(A18="NO ES DE NUESTRA COMPETENCIA", 5, IF(A18="OTRO", 15, "")))))) -> 15 | K18: =IF(AND(F18<>"", L18<>""), NETWORKDAYS(TODAY(), L18-1, FESTIVOS!A$1:A$55), "") -> -94 | L18: =IF(AND(F18<>"", J18<>""), WORKDAY(F18, J18, FESTIVOS!A$1:A$55), "") -> 46052 | M18: LAURA GIRALDO | N18: =IF(K18="", "", MAX(0, K18 - (TODAY() - TODAY()))) -> 0 | O18: =IF(OR(K18="", J18=""), "", IF(K18<0, "Vencido", IF(K18>(J18/2), "Supere la mitad", "Bajo la mitad"))) -> Vencido | P18: NO REQUIERE RESPUESTA | Q18: FALSE | R18: =IF(OR(Q18="", L18=""), "", NETWORKDAYS(L18, Q18, FESTIVOS!A17:A71)) -> #VALUE!
A19: OTRO | B19: FREDY HERNAN TEJADA | C19: ELECTROCAQUETA | D19: Respuesta a oficio CE-GC-0001 del 05-1-2026 con Rad interno No 2026-1-1-74 del 06-01-2026 | E19: 18 | F19: 46031 | G19: FALSE | H19: FALSE | I19: COMERCIAL | J19: =IF(A19="INFORMACIÓN O DOCUMENTOS", 10, IF(A19="CONSULTA", 30, IF(A19="FACTURACIÓN Y COBROS", 15, IF(A19="VINCULACIÓN Y DESVINCULACIÓN", 15, IF(A19="NO ES DE NUESTRA COMPETENCIA", 5, IF(A19="OTRO", 15, "")))))) -> 15 | K19: =IF(AND(F19<>"", L19<>""), NETWORKDAYS(TODAY(), L19-1, FESTIVOS!A$1:A$55), "") -> -92 | L19: =IF(AND(F19<>"", J19<>""), WORKDAY(F19, J19, FESTIVOS!A$1:A$55), "") -> 46055 | M19: LAURA GIRALDO | N19: =IF(K19="", "", MAX(0, K19 - (TODAY() - TODAY()))) -> 0 | O19: =IF(OR(K19="", J19=""), "", IF(K19<0, "Vencido", IF(K19>(J19/2), "Supere la mitad", "Bajo la mitad"))) -> Vencido | P19: NO REQUIERE RESPUESTA | Q19: FALSE | R19: =IF(OR(Q19="", L19=""), "", NETWORKDAYS(L19, Q19, FESTIVOS!A18:A72)) -> #VALUE!
A20: OTRO | B20: LUZ ELIANA TOBON MUÑOZ | C20: USUARIO DE SERVINTEGRAL | D20: SOLICITD DE ESCOMBROS | E20: 19 | F20: 46031 | G20: FALSE | H20: FALSE | I20: COMERCIAL | J20: =IF(A20="INFORMACIÓN O DOCUMENTOS", 10, IF(A20="CONSULTA", 30, IF(A20="FACTURACIÓN Y COBROS", 15, IF(A20="VINCULACIÓN Y DESVINCULACIÓN", 15, IF(A20="NO ES DE NUESTRA COMPETENCIA", 5, IF(A20="OTRO", 15, "")))))) -> 15 | K20: =IF(AND(F20<>"", L20<>""), NETWORKDAYS(TODAY(), L20-1, FESTIVOS!A$1:A$55), "") -> -92 | L20: =IF(AND(F20<>"", J20<>""), WORKDAY(F20, J20, FESTIVOS!A$1:A$55), "") -> 46055 | M20: LAURA GIRALDO | N20: =IF(K20="", "", MAX(0, K20 - (TODAY() - TODAY()))) -> 0 | O20: =IF(OR(K20="", J20=""), "", IF(K20<0, "Vencido", IF(K20>(J20/2), "Supere la mitad", "Bajo la mitad"))) -> Vencido | P20: CE-GC-0073 | Q20: 46043 | R20: =IF(OR(Q20="", L20=""), "", NETWORKDAYS(L20, Q20, FESTIVOS!A19:A73)) -> -9
A21: OTRO | B21: NANCY BOHORQUEZ | C21: USUARIO DE SERVINTEGRAL | D21: SOLICITD DE DESCUENTO EN LA DEUDA DE ASEO | E21: 20 | F21: 46035 | G21: FALSE | H21: FALSE | I21: COMERCIAL | J21: =IF(A21="INFORMACIÓN O DOCUMENTOS", 10, IF(A21="CONSULTA", 30, IF(A21="FACTURACIÓN Y COBROS", 15, IF(A21="VINCULACIÓN Y DESVINCULACIÓN", 15, IF(A21="NO ES DE NUESTRA COMPETENCIA", 5, IF(A21="OTRO", 15, "")))))) -> 15 | K21: =IF(AND(F21<>"", L21<>""), NETWORKDAYS(TODAY(), L21-1, FESTIVOS!A$1:A$55), "") -> -92 | L21: =IF(AND(F21<>"", J21<>""), WORKDAY(F21, J21, FESTIVOS!A$1:A$55), "") -> 46056 | M21: LAURA GIRALDO | N21: =IF(K21="", "", MAX(0, K21 - (TODAY() - TODAY()))) -> 0 | O21: FALSE | P21: CE-GC-0050 | Q21: 46037 | R21: =IF(OR(Q21="", L21=""), "", NETWORKDAYS(L21, Q21, FESTIVOS!A20:A74)) -> -14
A22: OTRO | B22: EMA | C22: USUARIO DE SERVINTEGRAL | D22: REFERENCIAS PERSONALES | E22: 21 | F22: 46035 | G22: FALSE | H22: FALSE | I22: TALENTO HUMANO | J22: =IF(A22="INFORMACIÓN O DOCUMENTOS", 10, IF(A22="CONSULTA", 30, IF(A22="FACTURACIÓN Y COBROS", 15, IF(A22="VINCULACIÓN Y DESVINCULACIÓN", 15, IF(A22="NO ES DE NUESTRA COMPETENCIA", 5, IF(A22="OTRO", 15, "")))))) -> 15 | K22: =IF(AND(F22<>"", L22<>""), NETWORKDAYS(TODAY(), L22-1, FESTIVOS!A$1:A$55), "") -> -92 | L22: =IF(AND(F22<>"", J22<>""), WORKDAY(F22, J22, FESTIVOS!A$1:A$55), "") -> 46056 | M22: LAURA GIRALDO | N22: =IF(K22="", "", MAX(0, K22 - (TODAY() - TODAY()))) -> 0 | O22: =IF(OR(K22="", J22=""), "", IF(K22<0, "Vencido", IF(K22>(J22/2), "Supere la mitad", "Bajo la mitad"))) -> Vencido | P22: NO REQUIERE RESPUESTA | Q22: FALSE | R22: =IF(OR(Q22="", L22=""), "", NETWORKDAYS(L22, Q22, FESTIVOS!A21:A75)) -> #VALUE!
A23: OTRO | B23: LEONOR RODRIGUEZ CELIS | C23: USUARIO DE SERVINTEGRAL | D23: AGRADECIMIENTO | E23: 22 | F23: 46035 | G23: FALSE | H23: FALSE | I23: RESIDUOS | J23: =IF(A23="INFORMACIÓN O DOCUMENTOS", 10, IF(A23="CONSULTA", 30, IF(A23="FACTURACIÓN Y COBROS", 15, IF(A23="VINCULACIÓN Y DESVINCULACIÓN", 15, IF(A23="NO ES DE NUESTRA COMPETENCIA", 5, IF(A23="OTRO", 15, "")))))) -> 15 | K23: =IF(AND(F23<>"", L23<>""), NETWORKDAYS(TODAY(), L23-1, FESTIVOS!A$1:A$55), "") -> -92 | L23: =IF(AND(F23<>"", J23<>""), WORKDAY(F23, J23, FESTIVOS!A$1:A$55), "") -> 46056 | M23: LAURA GIRALDO | N23: =IF(K23="", "", MAX(0, K23 - (TODAY() - TODAY()))) -> 0 | O23: =IF(OR(K23="", J23=""), "", IF(K23<0, "Vencido", IF(K23>(J23/2), "Supere la mitad", "Bajo la mitad"))) -> Vencido | P23: CE-GC-0033 | Q23: 46036 | R23: =IF(OR(Q23="", L23=""), "", NETWORKDAYS(L23, Q23, FESTIVOS!A22:A76)) -> -15
A24: OTRO | B24: YULIANA ESCOBAR | C24: ESAC | D24: NOTIFICACIÓN PERSONAL | E24: 23 | F24: 46035 | G24: FALSE | H24: FALSE | I24: COMERCIAL | J24: =IF(A24="INFORMACIÓN O DOCUMENTOS", 10, IF(A24="CONSULTA", 30, IF(A24="FACTURACIÓN Y COBROS", 15, IF(A24="VINCULACIÓN Y DESVINCULACIÓN", 15, IF(A24="NO ES DE NUESTRA COMPETENCIA", 5, IF(A24="OTRO", 15, "")))))) -> 15 | K24: =IF(AND(F24<>"", L24<>""), NETWORKDAYS(TODAY(), L24-1, FESTIVOS!A$1:A$55), "") -> -92 | L24: =IF(AND(F24<>"", J24<>""), WORKDAY(F24, J24, FESTIVOS!A$1:A$55), "") -> 46056 | M24: LAURA GIRALDO | N24: =IF(K24="", "", MAX(0, K24 - (TODAY() - TODAY()))) -> 0 | O24: =IF(OR(K24="", J24=""), "", IF(K24<0, "Vencido", IF(K24>(J24/2), "Supere la mitad", "Bajo la mitad"))) -> Vencido | P24: CE-GC-0033 | Q24: 46036 | R24: =IF(OR(Q24="", L24=""), "", NETWORKDAYS(L24, Q24, FESTIVOS!A23:A77)) -> -15
A25: OTRO | B25: YULIANA ESCOBAR | C25: ESAC | D25: NOTIFICACIÓN PERSONAL | E25: 24 | F25: 46035 | G25: FALSE | H25: FALSE | I25: COMERCIAL | J25: =IF(A25="INFORMACIÓN O DOCUMENTOS", 10, IF(A25="CONSULTA", 30, IF(A25="FACTURACIÓN Y COBROS", 15, IF(A25="VINCULACIÓN Y DESVINCULACIÓN", 15, IF(A25="NO ES DE NUESTRA COMPETENCIA", 5, IF(A25="OTRO", 15, "")))))) -> 15 | K25: =IF(AND(F25<>"", L25<>""), NETWORKDAYS(TODAY(), L25-1, FESTIVOS!A$1:A$55), "") -> -92 | L25: =IF(AND(F25<>"", J25<>""), WORKDAY(F25, J25, FESTIVOS!A$1:A$55), "") -> 46056 | M25: LAURA GIRALDO | N25: =IF(K25="", "", MAX(0, K25 - (TODAY() - TODAY()))) -> 0 | O25: =IF(OR(K25="", J25=""), "", IF(K25<0, "Vencido", IF(K25>(J25/2), "Supere la mitad", "Bajo la mitad"))) -> Vencido | P25: CE-GC-0033 | Q25: 46036 | R25: =IF(OR(Q25="", L25=""), "", NETWORKDAYS(L25, Q25, FESTIVOS!A24:A78)) -> -15
A26: OTRO | B26: YULIANA ESCOBAR | C26: ESAC | D26: NOTIFICACIÓN PERSONAL | E26: 25 | F26: 46035 | G26: FALSE | H26: FALSE | I26: COMERCIAL | J26: =IF(A26="INFORMACIÓN O DOCUMENTOS", 10, IF(A26="CONSULTA", 30, IF(A26="FACTURACIÓN Y COBROS", 15, IF(A26="VINCULACIÓN Y DESVINCULACIÓN", 15, IF(A26="NO ES DE NUESTRA COMPETENCIA", 5, IF(A26="OTRO", 15, "")))))) -> 15 | K26: =IF(AND(F26<>"", L26<>""), NETWORKDAYS(TODAY(), L26-1, FESTIVOS!A$1:A$55), "") -> -92 | L26: =IF(AND(F26<>"", J26<>""), WORKDAY(F26, J26, FESTIVOS!A$1:A$55), "") -> 46056 | M26: LAURA GIRALDO | N26: =IF(K26="", "", MAX(0, K26 - (TODAY() - TODAY()))) -> 0 | O26: =IF(OR(K26="", J26=""), "", IF(K26<0, "Vencido", IF(K26>(J26/2), "Supere la mitad", "Bajo la mitad"))) -> Vencido | P26: CE-GC-0033 | Q26: 46036 | R26: =IF(OR(Q26="", L26=""), "", NETWORKDAYS(L26, Q26, FESTIVOS!A25:A79)) -> -15
A27: OTRO | B27: YULIANA ESCOBAR | C27: ESAC | D27: NOTIFICACIÓN PERSONAL | E27: 26 | F27: 46035 | G27: FALSE | H27: FALSE | I27: COMERCIAL | J27: =IF(A27="INFORMACIÓN O DOCUMENTOS", 10, IF(A27="CONSULTA", 30, IF(A27="FACTURACIÓN Y COBROS", 15, IF(A27="VINCULACIÓN Y DESVINCULACIÓN", 15, IF(A27="NO ES DE NUESTRA COMPETENCIA", 5, IF(A27="OTRO", 15, "")))))) -> 15 | K27: =IF(AND(F27<>"", L27<>""), NETWORKDAYS(TODAY(), L27-1, FESTIVOS!A$1:A$55), "") -> -92 | L27: =IF(AND(F27<>"", J27<>""), WORKDAY(F27, J27, FESTIVOS!A$1:A$55), "") -> 46056 | M27: LAURA GIRALDO | N27: =IF(K27="", "", MAX(0, K27 - (TODAY() - TODAY()))) -> 0 | O27: =IF(OR(K27="", J27=""), "", IF(K27<0, "Vencido", IF(K27>(J27/2), "Supere la mitad", "Bajo la mitad"))) -> Vencido | P27: CE-GC-0033 | Q27: 46036 | R27: =IF(OR(Q27="", L27=""), "", NETWORKDAYS(L27, Q27, FESTIVOS!A26:A80)) -> -15
A28: OTRO | B28: YULIANA ESCOBAR | C28: ESAC | D28: NOTIFICACIÓN PERSONAL | E28: 27 | F28: 46035 | G28: FALSE | H28: FALSE | I28: COMERCIAL | J28: =IF(A28="INFORMACIÓN O DOCUMENTOS", 10, IF(A28="CONSULTA", 30, IF(A28="FACTURACIÓN Y COBROS", 15, IF(A28="VINCULACIÓN Y DESVINCULACIÓN", 15, IF(A28="NO ES DE NUESTRA COMPETENCIA", 5, IF(A28="OTRO", 15, "")))))) -> 15 | K28: =IF(AND(F28<>"", L28<>""), NETWORKDAYS(TODAY(), L28-1, FESTIVOS!A$1:A$55), "") -> -92 | L28: =IF(AND(F28<>"", J28<>""), WORKDAY(F28, J28, FESTIVOS!A$1:A$55), "") -> 46056 | M28: LAURA GIRALDO | N28: =IF(K28="", "", MAX(0, K28 - (TODAY() - TODAY()))) -> 0 | O28: =IF(OR(K28="", J28=""), "", IF(K28<0, "Vencido", IF(K28>(J28/2), "Supere la mitad", "Bajo la mitad"))) -> Vencido | P28: CE-GC-0033 | Q28: 46036 | R28: =IF(OR(Q28="", L28=""), "", NETWORKDAYS(L28, Q28, FESTIVOS!A27:A81)) -> -15
A29: OTRO | B29: WILLIAM EDMUNDO PIEDRAHITA MAYA | C29: CORPOAMAZONIA | D29: TRASLADO POR COMPETENCIA | E29: 28 | F29: 46035 | G29: FALSE | H29: FALSE | I29: COMERCIAL | J29: =IF(A29="INFORMACIÓN O DOCUMENTOS", 10, IF(A29="CONSULTA", 30, IF(A29="FACTURACIÓN Y COBROS", 15, IF(A29="VINCULACIÓN Y DESVINCULACIÓN", 15, IF(A29="NO ES DE NUESTRA COMPETENCIA", 5, IF(A29="OTRO", 15, "")))))) -> 15 | K29: =IF(AND(F29<>"", L29<>""), NETWORKDAYS(TODAY(), L29-1, FESTIVOS!A$1:A$55), "") -> -92 | L29: =IF(AND(F29<>"", J29<>""), WORKDAY(F29, J29, FESTIVOS!A$1:A$55), "") -> 46056 | M29: LAURA GIRALDO | N29: =IF(K29="", "", MAX(0, K29 - (TODAY() - TODAY()))) -> 0 | O29: =IF(OR(K29="", J29=""), "", IF(K29<0, "Vencido", IF(K29>(J29/2), "Supere la mitad", "Bajo la mitad"))) -> Vencido | P29: CE-GC-0033 | Q29: 46036 | R29: =IF(OR(Q29="", L29=""), "", NETWORKDAYS(L29, Q29, FESTIVOS!A28:A82)) -> -15
A30: OTRO | B30: LUIS MANUEL ESPINOSA CALDERON | C30: ALCALDIA | D30: SOLICITUD DE INFORMACIÓN PARA LIQUIDAR EL CONCURSO ECONOMICO | E30: 29 | F30: 46036 | G30: FALSE | H30: FALSE | I30: COMERCIAL | J30: =IF(A30="INFORMACIÓN O DOCUMENTOS", 10, IF(A30="CONSULTA", 30, IF(A30="FACTURACIÓN Y COBROS", 15, IF(A30="VINCULACIÓN Y DESVINCULACIÓN", 15, IF(A30="NO ES DE NUESTRA COMPETENCIA", 5, IF(A30="OTRO", 15, "")))))) -> 15 | K30: =IF(AND(F30<>"", L30<>""), NETWORKDAYS(TODAY(), L30-1, FESTIVOS!A$1:A$55), "") -> -91 | L30: =IF(AND(F30<>"", J30<>""), WORKDAY(F30, J30, FESTIVOS!A$1:A$55), "") -> 46057 | M30: LAURA GIRALDO | N30: =IF(K30="", "", MAX(0, K30 - (TODAY() - TODAY()))) -> 0 | O30: =IF(OR(K30="", J30=""), "", IF(K30<0, "Vencido", IF(K30>(J30/2), "Supere la mitad", "Bajo la mitad"))) -> Vencido | P30: CE-GC-0033 | Q30: 46036 | R30: =IF(OR(Q30="", L30=""), "", NETWORKDAYS(L30, Q30, FESTIVOS!A29:A83)) -> -16
A31: OTRO | B31: Javier Hernán Puyo Plazas | C31: MINESTERIO DE TRABAJO | D31: Derecho de Petición fechado el día 23/12/2025 | E31: 30 | F31: 46036 | G31: FALSE | H31: FALSE | I31: TALENTO HUMANO | J31: =IF(A31="INFORMACIÓN O DOCUMENTOS", 10, IF(A31="CONSULTA", 30, IF(A31="FACTURACIÓN Y COBROS", 15, IF(A31="VINCULACIÓN Y DESVINCULACIÓN", 15, IF(A31="NO ES DE NUESTRA COMPETENCIA", 5, IF(A31="OTRO", 15, "")))))) -> 15 | K31: =IF(AND(F31<>"", L31<>""), NETWORKDAYS(TODAY(), L31-1, FESTIVOS!A$1:A$55), "") -> -91 | L31: =IF(AND(F31<>"", J31<>""), WORKDAY(F31, J31, FESTIVOS!A$1:A$55), "") -> 46057 | M31: LAURA GIRALDO | N31: =IF(K31="", "", MAX(0, K31 - (TODAY() - TODAY()))) -> 0 | O31: =IF(OR(K31="", J31=""), "", IF(K31<0, "Vencido", IF(K31>(J31/2), "Supere la mitad", "Bajo la mitad"))) -> Vencido | P31: CE-GC-0033 | Q31: 46036 | R31: =IF(OR(Q31="", L31=""), "", NETWORKDAYS(L31, Q31, FESTIVOS!A30:A84)) -> -16
A32: OTRO | B32: LUIS ZAPATA OROZCO | C32: USUARIO DE SERVINTEGRAL | D32: SOLICITUD DE 1 LETRERO | E32: 31 | F32: 46036 | G32: FALSE | H32: FALSE | I32: COMERCIAL | J32: =IF(A32="INFORMACIÓN O DOCUMENTOS", 10, IF(A32="CONSULTA", 30, IF(A32="FACTURACIÓN Y COBROS", 15, IF(A32="VINCULACIÓN Y DESVINCULACIÓN", 15, IF(A32="NO ES DE NUESTRA COMPETENCIA", 5, IF(A32="OTRO", 15, "")))))) -> 15 | K32: =IF(AND(F32<>"", L32<>""), NETWORKDAYS(TODAY(), L32-1, FESTIVOS!A$1:A$55), "") -> -91 | L32: =IF(AND(F32<>"", J32<>""), WORKDAY(F32, J32, FESTIVOS!A$1:A$55), "") -> 46057 | M32: LAURA GIRALDO | N32: =IF(K32="", "", MAX(0, K32 - (TODAY() - TODAY()))) -> 0 | O32: =IF(OR(K32="", J32=""), "", IF(K32<0, "Vencido", IF(K32>(J32/2), "Supere la mitad", "Bajo la mitad"))) -> Vencido | P32: CE-GC-0033 | Q32: 46036 | R32: =IF(OR(Q32="", L32=""), "", NETWORKDAYS(L32, Q32, FESTIVOS!A31:A85)) -> -16
A33: OTRO | B33: CLAUDIA TOVAR | C33: USUARIO DE SERVINTEGRAL | D33: VINCULACIÓN DIRECTA | E33: 32 | F33: 46036 | G33: FALSE | H33: FALSE | I33: COMERCIAL | J33: =IF(A33="INFORMACIÓN O DOCUMENTOS", 10, IF(A33="CONSULTA", 30, IF(A33="FACTURACIÓN Y COBROS", 15, IF(A33="VINCULACIÓN Y DESVINCULACIÓN", 15, IF(A33="NO ES DE NUESTRA COMPETENCIA", 5, IF(A33="OTRO", 15, "")))))) -> 15 | K33: =IF(AND(F33<>"", L33<>""), NETWORKDAYS(TODAY(), L33-1, FESTIVOS!A$1:A$55), "") -> -91 | L33: =IF(AND(F33<>"", J33<>""), WORKDAY(F33, J33, FESTIVOS!A$1:A$55), "") -> 46057 | M33: LAURA GIRALDO | N33: =IF(K33="", "", MAX(0, K33 - (TODAY() - TODAY()))) -> 0 | O33: =IF(OR(K33="", J33=""), "", IF(K33<0, "Vencido", IF(K33>(J33/2), "Supere la mitad", "Bajo la mitad"))) -> Vencido | P33: CE-GC-0033 | Q33: 46036 | R33: =IF(OR(Q33="", L33=""), "", NETWORKDAYS(L33, Q33, FESTIVOS!A32:A86)) -> -16
A34: OTRO | B34: MARIA IRAIDES HERRERA GAITAN | C34: USUARIO DE SERVINTEGRAL | D34: VINCULACIÓN DIRECTA | E34: 33 | F34: 46036 | G34: FALSE | H34: FALSE | I34: COMERCIAL | J34: =IF(A34="INFORMACIÓN O DOCUMENTOS", 10, IF(A34="CONSULTA", 30, IF(A34="FACTURACIÓN Y COBROS", 15, IF(A34="VINCULACIÓN Y DESVINCULACIÓN", 15, IF(A34="NO ES DE NUESTRA COMPETENCIA", 5, IF(A34="OTRO", 15, "")))))) -> 15 | K34: =IF(AND(F34<>"", L34<>""), NETWORKDAYS(TODAY(), L34-1, FESTIVOS!A$1:A$55), "") -> -91 | L34: =IF(AND(F34<>"", J34<>""), WORKDAY(F34, J34, FESTIVOS!A$1:A$55), "") -> 46057 | M34: LAURA GIRALDO | N34: =IF(K34="", "", MAX(0, K34 - (TODAY() - TODAY()))) -> 0 | O34: =IF(OR(K34="", J34=""), "", IF(K34<0, "Vencido", IF(K34>(J34/2), "Supere la mitad", "Bajo la mitad"))) -> Vencido | P34: CE-GC-0033 | Q34: 46036 | R34: =IF(OR(Q34="", L34=""), "", NETWORKDAYS(L34, Q34, FESTIVOS!A33:A87)) -> -16
... A185: OTRO | B185: LIGIA CONSTANZA ROJA MEJIA | C185: USUARIO DE SERVINTEGRAL | D185: Invitación reunión con Pares Académicos – Programa Administración Financiera | E185: 184 | F185: 46062 | G185: FALSE | H185: FALSE | I185: FINANCIERA | J185: =IF(A185="INFORMACIÓN O DOCUMENTOS", 10, IF(A185="CONSULTA", 30, IF(A185="FACTURACIÓN Y COBROS", 15, IF(A185="VINCULACIÓN Y DESVINCULACIÓN", 15, IF(A185="NO ES DE NUESTRA COMPETENCIA", 5, IF(A185="OTRO", 15, "")))))) -> 15 | K185: =IF(AND(F185<>"", L185<>""), NETWORKDAYS(TODAY(), L185-1, FESTIVOS!A$1:A$55), "") -> -72 | L185: =IF(AND(F185<>"", J185<>""), WORKDAY(F185, J185, FESTIVOS!A$1:A$55), "") -> 46083 | M185: LAURA GIRALDO | N185: =IF(K185="", "", MAX(0, K185 - (TODAY() - TODAY()))) -> 0 | O185: =IF(OR(K185="", J185=""), "", IF(K185<0, "Vencido", IF(K185>(J185/2), "Supere la mitad", "Bajo la mitad"))) -> Vencido | P185: CE-GC-0033 | Q185: 46036 | R185: =IF(OR(Q185="", L185=""), "", NETWORKDAYS(L185, Q185, FESTIVOS!A184:A238)) -> -34
A186: OTRO | B186: YEISON JULIAN CELIS | C186: TRABAJADOR DE SERVINTEGRAL | D186: Constancia sobre reunión del 6 de febrero de 2026 – Radicado No. 0125 | E186: 185 | F186: 46062 | G186: FALSE | H186: FALSE | J186: =IF(A186="INFORMACIÓN O DOCUMENTOS", 10, IF(A186="CONSULTA", 30, IF(A186="FACTURACIÓN Y COBROS", 15, IF(A186="VINCULACIÓN Y DESVINCULACIÓN", 15, IF(A186="NO ES DE NUESTRA COMPETENCIA", 5, IF(A186="OTRO", 15, "")))))) -> 15 | K186: =IF(AND(F186<>"", L186<>""), NETWORKDAYS(TODAY(), L186-1, FESTIVOS!A$1:A$55), "") -> -72 | L186: =IF(AND(F186<>"", J186<>""), WORKDAY(F186, J186, FESTIVOS!A$1:A$55), "") -> 46083 | M186: LAURA GIRALDO | N186: =IF(K186="", "", MAX(0, K186 - (TODAY() - TODAY()))) -> 0 | O186: =IF(OR(K186="", J186=""), "", IF(K186<0, "Vencido", IF(K186>(J186/2), "Supere la mitad", "Bajo la mitad"))) -> Vencido | P186: CE-GH-0228 | Q186: 46069 | R186: =IF(OR(Q186="", L186=""), "", NETWORKDAYS(L186, Q186, FESTIVOS!A185:A239)) -> -11
A187: OTRO | B187: OSCAR JAVIER RAMOS | C187: USUARIO DE SERVINTEGRAL | D187: Solicitud de apoyo para jornada de aseo y embellecimiento I.E. ANDES SEDE ALPES | E187: 186 | F187: 46062 | G187: FALSE | H187: FALSE | J187: =IF(A187="INFORMACIÓN O DOCUMENTOS", 10, IF(A187="CONSULTA", 30, IF(A187="FACTURACIÓN Y COBROS", 15, IF(A187="VINCULACIÓN Y DESVINCULACIÓN", 15, IF(A187="NO ES DE NUESTRA COMPETENCIA", 5, IF(A187="OTRO", 15, "")))))) -> 15 | K187: =IF(AND(F187<>"", L187<>""), NETWORKDAYS(TODAY(), L187-1, FESTIVOS!A$1:A$55), "") -> -72 | L187: =IF(AND(F187<>"", J187<>""), WORKDAY(F187, J187, FESTIVOS!A$1:A$55), "") -> 46083 | M187: LAURA GIRALDO | N187: =IF(K187="", "", MAX(0, K187 - (TODAY() - TODAY()))) -> 0 | O187: =IF(OR(K187="", J187=""), "", IF(K187<0, "Vencido", IF(K187>(J187/2), "Supere la mitad", "Bajo la mitad"))) -> Vencido | P187: CE-GC-0033 | Q187: 46036 | R187: =IF(OR(Q187="", L187=""), "", NETWORKDAYS(L187, Q187, FESTIVOS!A186:A240)) -> -34
A188: OTRO | B188: ARISTIDES TOVAR | C188: USUARIO DE SERVINTEGRAL | D188: ENCUENTRO NACIONAL | E188: 187 | F188: 46062 | G188: FALSE | H188: FALSE | J188: =IF(A188="INFORMACIÓN O DOCUMENTOS", 10, IF(A188="CONSULTA", 30, IF(A188="FACTURACIÓN Y COBROS", 15, IF(A188="VINCULACIÓN Y DESVINCULACIÓN", 15, IF(A188="NO ES DE NUESTRA COMPETENCIA", 5, IF(A188="OTRO", 15, "")))))) -> 15 | K188: =IF(AND(F188<>"", L188<>""), NETWORKDAYS(TODAY(), L188-1, FESTIVOS!A$1:A$55), "") -> -72 | L188: =IF(AND(F188<>"", J188<>""), WORKDAY(F188, J188, FESTIVOS!A$1:A$55), "") -> 46083 | M188: LAURA GIRALDO | N188: =IF(K188="", "", MAX(0, K188 - (TODAY() - TODAY()))) -> 0 | O188: =IF(OR(K188="", J188=""), "", IF(K188<0, "Vencido", IF(K188>(J188/2), "Supere la mitad", "Bajo la mitad"))) -> Vencido | P188: CE-GC-0033 | Q188: 46036 | R188: =IF(OR(Q188="", L188=""), "", NETWORKDAYS(L188, Q188, FESTIVOS!A187:A241)) -> -34
A189: OTRO | B189: QUEJA DEL SERVICIO | C189: USUARIO DE SERVINTEGRAL | D189: EVIDALIA LADINO | E189: 188 | F189: 46062 | G189: FALSE | H189: FALSE | J189: =IF(A189="INFORMACIÓN O DOCUMENTOS", 10, IF(A189="CONSULTA", 30, IF(A189="FACTURACIÓN Y COBROS", 15, IF(A189="VINCULACIÓN Y DESVINCULACIÓN", 15, IF(A189="NO ES DE NUESTRA COMPETENCIA", 5, IF(A189="OTRO", 15, "")))))) -> 15 | K189: =IF(AND(F189<>"", L189<>""), NETWORKDAYS(TODAY(), L189-1, FESTIVOS!A$1:A$55), "") -> -72 | L189: =IF(AND(F189<>"", J189<>""), WORKDAY(F189, J189, FESTIVOS!A$1:A$55), "") -> 46083 | M189: LAURA GIRALDO | N189: =IF(K189="", "", MAX(0, K189 - (TODAY() - TODAY()))) -> 0 | O189: =IF(OR(K189="", J189=""), "", IF(K189<0, "Vencido", IF(K189>(J189/2), "Supere la mitad", "Bajo la mitad"))) -> Vencido | P189: CE-GC-0033 | Q189: 46036 | R189: =IF(OR(Q189="", L189=""), "", NETWORKDAYS(L189, Q189, FESTIVOS!A188:A242)) -> -34
A190: OTRO | B190: SIXTO ALFONSO PARAMO | C190: USUARIO DE SERVINTEGRAL | D190: COMUNICACIÓN DE ACTA MEDIANTE LA CUAL SE RESUELVE IMPUGNACIÓN FRENTE AL CASO MARIANO OSWALDO ROJAS ARANGO- C.C 94043507 Y SE REITERA EL DEBER DE ALLEGAR EL SOPORTE DE PAGO DE HONORARIOS A FAVOR DE LA JUNTA NACIONAL PARA EL TRÁMITE CORRESPONDIENTE | E190: 189 | F190: 46062 | G190: FALSE | H190: FALSE | J190: =IF(A190="INFORMACIÓN O DOCUMENTOS", 10, IF(A190="CONSULTA", 30, IF(A190="FACTURACIÓN Y COBROS", 15, IF(A190="VINCULACIÓN Y DESVINCULACIÓN", 15, IF(A190="NO ES DE NUESTRA COMPETENCIA", 5, IF(A190="OTRO", 15, "")))))) -> 15 | K190: =IF(AND(F190<>"", L190<>""), NETWORKDAYS(TODAY(), L190-1, FESTIVOS!A$1:A$55), "") -> -72 | L190: =IF(AND(F190<>"", J190<>""), WORKDAY(F190, J190, FESTIVOS!A$1:A$55), "") -> 46083 | M190: LAURA GIRALDO | N190: =IF(K190="", "", MAX(0, K190 - (TODAY() - TODAY()))) -> 0 | O190: =IF(OR(K190="", J190=""), "", IF(K190<0, "Vencido", IF(K190>(J190/2), "Supere la mitad", "Bajo la mitad"))) -> Vencido | P190: CE-GC-0033 | Q190: 46036 | R190: =IF(OR(Q190="", L190=""), "", NETWORKDAYS(L190, Q190, FESTIVOS!A189:A243)) -> -34
A191: OTRO | B191: CAMILO ENRIQUE DIAZ CARDENAS | C191: USUARIO DE SERVINTEGRAL | D191: ACEPTACIÓN DE LA PROPUESTA | E191: 190 | F191: 46062 | G191: FALSE | H191: FALSE | J191: =IF(A191="INFORMACIÓN O DOCUMENTOS", 10, IF(A191="CONSULTA", 30, IF(A191="FACTURACIÓN Y COBROS", 15, IF(A191="VINCULACIÓN Y DESVINCULACIÓN", 15, IF(A191="NO ES DE NUESTRA COMPETENCIA", 5, IF(A191="OTRO", 15, "")))))) -> 15 | K191: =IF(AND(F191<>"", L191<>""), NETWORKDAYS(TODAY(), L191-1, FESTIVOS!A$1:A$55), "") -> -72 | L191: =IF(AND(F191<>"", J191<>""), WORKDAY(F191, J191, FESTIVOS!A$1:A$55), "") -> 46083 | M191: LAURA GIRALDO | N191: =IF(K191="", "", MAX(0, K191 - (TODAY() - TODAY()))) -> 0 | O191: =IF(OR(K191="", J191=""), "", IF(K191<0, "Vencido", IF(K191>(J191/2), "Supere la mitad", "Bajo la mitad"))) -> Vencido | P191: CE-GC-0033 | Q191: 46036 | R191: =IF(OR(Q191="", L191=""), "", NETWORKDAYS(L191, Q191, FESTIVOS!A190:A244)) -> -34
A192: OTRO | B192: YOLANDA NARVAEZ | C192: USUARIO DE SERVINTEGRAL | D192: SOLIICTUD DE CERTIFICADO | E192: 191 | F192: 46062 | G192: FALSE | H192: FALSE | J192: =IF(A192="INFORMACIÓN O DOCUMENTOS", 10, IF(A192="CONSULTA", 30, IF(A192="FACTURACIÓN Y COBROS", 15, IF(A192="VINCULACIÓN Y DESVINCULACIÓN", 15, IF(A192="NO ES DE NUESTRA COMPETENCIA", 5, IF(A192="OTRO", 15, "")))))) -> 15 | K192: =IF(AND(F192<>"", L192<>""), NETWORKDAYS(TODAY(), L192-1, FESTIVOS!A$1:A$55), "") -> -72 | L192: =IF(AND(F192<>"", J192<>""), WORKDAY(F192, J192, FESTIVOS!A$1:A$55), "") -> 46083 | M192: LAURA GIRALDO | N192: =IF(K192="", "", MAX(0, K192 - (TODAY() - TODAY()))) -> 0 | O192: =IF(OR(K192="", J192=""), "", IF(K192<0, "Vencido", IF(K192>(J192/2), "Supere la mitad", "Bajo la mitad"))) -> Vencido | P192: CE-GC-0033 | Q192: 46036 | R192: =IF(OR(Q192="", L192=""), "", NETWORKDAYS(L192, Q192, FESTIVOS!A191:A245)) -> -34
A193: OTRO | B193: YANETH MOLINA | C193: USUARIO DE SERVINTEGRAL | D193: COTIZACIÓN | E193: 192 | F193: 46062 | G193: FALSE | H193: FALSE | J193: =IF(A193="INFORMACIÓN O DOCUMENTOS", 10, IF(A193="CONSULTA", 30, IF(A193="FACTURACIÓN Y COBROS", 15, IF(A193="VINCULACIÓN Y DESVINCULACIÓN", 15, IF(A193="NO ES DE NUESTRA COMPETENCIA", 5, IF(A193="OTRO", 15, "")))))) -> 15 | K193: =IF(AND(F193<>"", L193<>""), NETWORKDAYS(TODAY(), L193-1, FESTIVOS!A$1:A$55), "") -> -72 | L193: =IF(AND(F193<>"", J193<>""), WORKDAY(F193, J193, FESTIVOS!A$1:A$55), "") -> 46083 | M193: LAURA GIRALDO | N193: =IF(K193="", "", MAX(0, K193 - (TODAY() - TODAY()))) -> 0 | O193: =IF(OR(K193="", J193=""), "", IF(K193<0, "Vencido", IF(K193>(J193/2), "Supere la mitad", "Bajo la mitad"))) -> Vencido | P193: CE-GC-0033 | Q193: 46036 | R193: =IF(OR(Q193="", L193=""), "", NETWORKDAYS(L193, Q193, FESTIVOS!A192:A246)) -> -34
A194: OTRO | B194: ELBA OBANDO | C194: USUARIO DE SERVINTEGRAL | D194: SOLICITUD DE PAZ Y SALVO | E194: 193 | F194: 46062 | G194: FALSE | H194: FALSE | J194: =IF(A194="INFORMACIÓN O DOCUMENTOS", 10, IF(A194="CONSULTA", 30, IF(A194="FACTURACIÓN Y COBROS", 15, IF(A194="VINCULACIÓN Y DESVINCULACIÓN", 15, IF(A194="NO ES DE NUESTRA COMPETENCIA", 5, IF(A194="OTRO", 15, "")))))) -> 15 | K194: =IF(AND(F194<>"", L194<>""), NETWORKDAYS(TODAY(), L194-1, FESTIVOS!A$1:A$55), "") -> -72 | L194: =IF(AND(F194<>"", J194<>""), WORKDAY(F194, J194, FESTIVOS!A$1:A$55), "") -> 46083 | M194: LAURA GIRALDO | N194: =IF(K194="", "", MAX(0, K194 - (TODAY() - TODAY()))) -> 0 | O194: =IF(OR(K194="", J194=""), "", IF(K194<0, "Vencido", IF(K194>(J194/2), "Supere la mitad", "Bajo la mitad"))) -> Vencido | P194: CE-GC-0033 | Q194: 46036 | R194: =IF(OR(Q194="", L194=""), "", NETWORKDAYS(L194, Q194, FESTIVOS!A193:A247)) -> -34
A195: OTRO | B195: LUZ DARY MURILLO GOMEZ | C195: USUARIO DE SERVINTEGRAL | D195: APOYO INSTITUCIONAL | E195: 194 | F195: 46062 | G195: FALSE | H195: FALSE | J195: =IF(A195="INFORMACIÓN O DOCUMENTOS", 10, IF(A195="CONSULTA", 30, IF(A195="FACTURACIÓN Y COBROS", 15, IF(A195="VINCULACIÓN Y DESVINCULACIÓN", 15, IF(A195="NO ES DE NUESTRA COMPETENCIA", 5, IF(A195="OTRO", 15, "")))))) -> 15 | K195: =IF(AND(F195<>"", L195<>""), NETWORKDAYS(TODAY(), L195-1, FESTIVOS!A$1:A$55), "") -> -72 | L195: =IF(AND(F195<>"", J195<>""), WORKDAY(F195, J195, FESTIVOS!A$1:A$55), "") -> 46083 | M195: LAURA GIRALDO | N195: =IF(K195="", "", MAX(0, K195 - (TODAY() - TODAY()))) -> 0 | O195: =IF(OR(K195="", J195=""), "", IF(K195<0, "Vencido", IF(K195>(J195/2), "Supere la mitad", "Bajo la mitad"))) -> Vencido | P195: CE-GC-0033 | Q195: 46036 | R195: =IF(OR(Q195="", L195=""), "", NETWORKDAYS(L195, Q195, FESTIVOS!A194:A248)) -> -34
A196: OTRO | B196: JESÚS ALBERTO ESCOBAR HURTADO | C196: ALCALDIA | D196: REMISIÓN DE CIRCULAR 003 | E196: 195 | F196: 46062 | G196: FALSE | H196: FALSE | J196: =IF(A196="INFORMACIÓN O DOCUMENTOS", 10, IF(A196="CONSULTA", 30, IF(A196="FACTURACIÓN Y COBROS", 15, IF(A196="VINCULACIÓN Y DESVINCULACIÓN", 15, IF(A196="NO ES DE NUESTRA COMPETENCIA", 5, IF(A196="OTRO", 15, "")))))) -> 15 | K196: =IF(AND(F196<>"", L196<>""), NETWORKDAYS(TODAY(), L196-1, FESTIVOS!A$1:A$55), "") -> -72 | L196: =IF(AND(F196<>"", J196<>""), WORKDAY(F196, J196, FESTIVOS!A$1:A$55), "") -> 46083 | M196: LAURA GIRALDO | N196: =IF(K196="", "", MAX(0, K196 - (TODAY() - TODAY()))) -> 0 | O196: =IF(OR(K196="", J196=""), "", IF(K196<0, "Vencido", IF(K196>(J196/2), "Supere la mitad", "Bajo la mitad"))) -> Vencido | P196: CE-GC-0033 | Q196: 46036 | R196: =IF(OR(Q196="", L196=""), "", NETWORKDAYS(L196, Q196, FESTIVOS!A195:A249)) -> -34
A197: OTRO | B197: MARIBEL CAMACHO | C197: USUARIO DE SERVINTEGRAL | D197: capacitaciones a Empresas 100% Subsidiado | E197: 196 | F197: 46062 | G197: FALSE | H197: FALSE | J197: =IF(A197="INFORMACIÓN O DOCUMENTOS", 10, IF(A197="CONSULTA", 30, IF(A197="FACTURACIÓN Y COBROS", 15, IF(A197="VINCULACIÓN Y DESVINCULACIÓN", 15, IF(A197="NO ES DE NUESTRA COMPETENCIA", 5, IF(A197="OTRO", 15, "")))))) -> 15 | K197: =IF(AND(F197<>"", L197<>""), NETWORKDAYS(TODAY(), L197-1, FESTIVOS!A$1:A$55), "") -> -72 | L197: =IF(AND(F197<>"", J197<>""), WORKDAY(F197, J197, FESTIVOS!A$1:A$55), "") -> 46083 | M197: LAURA GIRALDO | N197: =IF(K197="", "", MAX(0, K197 - (TODAY() - TODAY()))) -> 0 | O197: =IF(OR(K197="", J197=""), "", IF(K197<0, "Vencido", IF(K197>(J197/2), "Supere la mitad", "Bajo la mitad"))) -> Vencido | P197: CE-GC-0033 | Q197: 46036 | R197: =IF(OR(Q197="", L197=""), "", NETWORKDAYS(L197, Q197, FESTIVOS!A196:A250)) -> -34
... A263: OTRO | B263: JESSIKA PERDOMO | C263: ALCALDIA | D263: SOLICITUD DE CERTIFICACIÓN | E263: 262 | F263: 46072 | G263: FALSE | H263: FALSE | J263: =IF(A263="INFORMACIÓN O DOCUMENTOS", 10, IF(A263="CONSULTA", 30, IF(A263="FACTURACIÓN Y COBROS", 15, IF(A263="VINCULACIÓN Y DESVINCULACIÓN", 15, IF(A263="NO ES DE NUESTRA COMPETENCIA", 5, IF(A263="OTRO", 15, "")))))) -> 15 | K263: =IF(AND(F263<>"", L263<>""), NETWORKDAYS(TODAY(), L263-1, FESTIVOS!A$1:A$55), "") -> -65 | L263: =IF(AND(F263<>"", J263<>""), WORKDAY(F263, J263, FESTIVOS!A$1:A$55), "") -> 46093 | M263: LAURA GIRALDO | N263: =IF(K263="", "", MAX(0, K263 - (TODAY() - TODAY()))) -> 0 | O263: =IF(OR(K263="", J263=""), "", IF(K263<0, "Vencido", IF(K263>(J263/2), "Supere la mitad", "Bajo la mitad"))) -> Vencido | P263: CE-GC-0283 | Q263: 46085 | R263: =IF(OR(Q263="", L263=""), "", NETWORKDAYS(L263, Q263, FESTIVOS!A262:A316)) -> -7
A264: OTRO | B264: DOMINGA DE JESÚS RAMOS SUÁREZ | C264: JUZGADO | D264: LEVANTAMIENTO DE MEDIDAS CAUTELARES - PROCESO EJECUTIVO DE ALIMENTOS RAD. 2025-00118-00-00 | E264: 263 | F264: 46072 | G264: FALSE | H264: FALSE | J264: =IF(A264="INFORMACIÓN O DOCUMENTOS", 10, IF(A264="CONSULTA", 30, IF(A264="FACTURACIÓN Y COBROS", 15, IF(A264="VINCULACIÓN Y DESVINCULACIÓN", 15, IF(A264="NO ES DE NUESTRA COMPETENCIA", 5, IF(A264="OTRO", 15, "")))))) -> 15 | K264: =IF(AND(F264<>"", L264<>""), NETWORKDAYS(TODAY(), L264-1, FESTIVOS!A$1:A$55), "") -> -65 | L264: =IF(AND(F264<>"", J264<>""), WORKDAY(F264, J264, FESTIVOS!A$1:A$55), "") -> 46093 | M264: LAURA GIRALDO | N264: =IF(K264="", "", MAX(0, K264 - (TODAY() - TODAY()))) -> 0 | O264: =IF(OR(K264="", J264=""), "", IF(K264<0, "Vencido", IF(K264>(J264/2), "Supere la mitad", "Bajo la mitad"))) -> Vencido | P264: NO REQUIERE RESPUESTA | Q264: FALSE | R264: =IF(OR(Q264="", L264=""), "", NETWORKDAYS(L264, Q264, FESTIVOS!A263:A317)) -> #VALUE!
A265: OTRO | B265: Leidi Milena Santamaria Perez | C265: ALCALDIA | D265: Solicitud de Certificación de pago de subsidios año 2025 | E265: 264 | F265: 46072 | G265: FALSE | H265: FALSE | J265: =IF(A265="INFORMACIÓN O DOCUMENTOS", 10, IF(A265="CONSULTA", 30, IF(A265="FACTURACIÓN Y COBROS", 15, IF(A265="VINCULACIÓN Y DESVINCULACIÓN", 15, IF(A265="NO ES DE NUESTRA COMPETENCIA", 5, IF(A265="OTRO", 15, "")))))) -> 15 | K265: =IF(AND(F265<>"", L265<>""), NETWORKDAYS(TODAY(), L265-1, FESTIVOS!A$1:A$55), "") -> -65 | L265: =IF(AND(F265<>"", J265<>""), WORKDAY(F265, J265, FESTIVOS!A$1:A$55), "") -> 46093 | M265: LAURA GIRALDO | N265: =IF(K265="", "", MAX(0, K265 - (TODAY() - TODAY()))) -> 0 | O265: =IF(OR(K265="", J265=""), "", IF(K265<0, "Vencido", IF(K265>(J265/2), "Supere la mitad", "Bajo la mitad"))) -> Vencido | P265: CE-GC-0274 | Q265: 46076 | R265: =IF(OR(Q265="", L265=""), "", NETWORKDAYS(L265, Q265, FESTIVOS!A264:A318)) -> -14
A266: OTRO | B266: ANDRES CAMILO CADAVID | C266: USUARIO DE SERVINTEGRAL | D266: CERTIFICADO DEUDA JASMÍN BELTRÁN MORALES | E266: 265 | F266: 46072 | G266: FALSE | H266: FALSE | J266: =IF(A266="INFORMACIÓN O DOCUMENTOS", 10, IF(A266="CONSULTA", 30, IF(A266="FACTURACIÓN Y COBROS", 15, IF(A266="VINCULACIÓN Y DESVINCULACIÓN", 15, IF(A266="NO ES DE NUESTRA COMPETENCIA", 5, IF(A266="OTRO", 15, "")))))) -> 15 | K266: =IF(AND(F266<>"", L266<>""), NETWORKDAYS(TODAY(), L266-1, FESTIVOS!A$1:A$55), "") -> -65 | L266: =IF(AND(F266<>"", J266<>""), WORKDAY(F266, J266, FESTIVOS!A$1:A$55), "") -> 46093 | M266: LAURA GIRALDO | N266: =IF(K266="", "", MAX(0, K266 - (TODAY() - TODAY()))) -> 0 | O266: =IF(OR(K266="", J266=""), "", IF(K266<0, "Vencido", IF(K266>(J266/2), "Supere la mitad", "Bajo la mitad"))) -> Vencido | P266: CE-GT-0280 | Q266: 46090 | R266: =IF(OR(Q266="", L266=""), "", NETWORKDAYS(L266, Q266, FESTIVOS!A265:A319)) -> -4
A267: OTRO | B267: YENY CAROLINA VILLAMIL | C267: ELECTROCAQUETA | D267: Traslado por competencia del oficio con rad No 2026-1-1-222 del 18-02-2026 | E267: 266 | F267: 46072 | G267: FALSE | H267: FALSE | J267: =IF(A267="INFORMACIÓN O DOCUMENTOS", 10, IF(A267="CONSULTA", 30, IF(A267="FACTURACIÓN Y COBROS", 15, IF(A267="VINCULACIÓN Y DESVINCULACIÓN", 15, IF(A267="NO ES DE NUESTRA COMPETENCIA", 5, IF(A267="OTRO", 15, "")))))) -> 15 | K267: =IF(AND(F267<>"", L267<>""), NETWORKDAYS(TODAY(), L267-1, FESTIVOS!A$1:A$55), "") -> -65 | L267: =IF(AND(F267<>"", J267<>""), WORKDAY(F267, J267, FESTIVOS!A$1:A$55), "") -> 46093 | M267: LAURA GIRALDO | N267: =IF(K267="", "", MAX(0, K267 - (TODAY() - TODAY()))) -> 0 | O267: =IF(OR(K267="", J267=""), "", IF(K267<0, "Vencido", IF(K267>(J267/2), "Supere la mitad", "Bajo la mitad"))) -> Vencido | P267: CE-GC-0363 | Q267: 46093 | R267: =IF(OR(Q267="", L267=""), "", NETWORKDAYS(L267, Q267, FESTIVOS!A266:A320)) -> 1
A268: OTRO | B268: JAIRO ANTONIO MOLINA | C268: USUARIO DE SERVINTEGRAL | D268: SOLICITUD DE CERTIFICADO | E268: 267 | F268: 46072 | G268: FALSE | H268: FALSE | J268: =IF(A268="INFORMACIÓN O DOCUMENTOS", 10, IF(A268="CONSULTA", 30, IF(A268="FACTURACIÓN Y COBROS", 15, IF(A268="VINCULACIÓN Y DESVINCULACIÓN", 15, IF(A268="NO ES DE NUESTRA COMPETENCIA", 5, IF(A268="OTRO", 15, "")))))) -> 15 | K268: =IF(AND(F268<>"", L268<>""), NETWORKDAYS(TODAY(), L268-1, FESTIVOS!A$1:A$55), "") -> -65 | L268: =IF(AND(F268<>"", J268<>""), WORKDAY(F268, J268, FESTIVOS!A$1:A$55), "") -> 46093 | M268: LAURA GIRALDO | N268: =IF(K268="", "", MAX(0, K268 - (TODAY() - TODAY()))) -> 0 | O268: =IF(OR(K268="", J268=""), "", IF(K268<0, "Vencido", IF(K268>(J268/2), "Supere la mitad", "Bajo la mitad"))) -> Vencido | P268: CE-GC-0294 | Q268: 46107 | R268: =IF(OR(Q268="", L268=""), "", NETWORKDAYS(L268, Q268, FESTIVOS!A267:A321)) -> 11
A269: OTRO | B269: RIQUELIO OVIEDO | C269: USUARIO DE SERVINTEGRAL | D269: SOLICITUD DE PODA | E269: 268 | F269: 46073 | G269: FALSE | H269: FALSE | J269: =IF(A269="INFORMACIÓN O DOCUMENTOS", 10, IF(A269="CONSULTA", 30, IF(A269="FACTURACIÓN Y COBROS", 15, IF(A269="VINCULACIÓN Y DESVINCULACIÓN", 15, IF(A269="NO ES DE NUESTRA COMPETENCIA", 5, IF(A269="OTRO", 15, "")))))) -> 15 | K269: =IF(AND(F269<>"", L269<>""), NETWORKDAYS(TODAY(), L269-1, FESTIVOS!A$1:A$55), "") -> -64 | L269: =IF(AND(F269<>"", J269<>""), WORKDAY(F269, J269, FESTIVOS!A$1:A$55), "") -> 46094 | M269: LAURA GIRALDO | N269: =IF(K269="", "", MAX(0, K269 - (TODAY() - TODAY()))) -> 0 | O269: =IF(OR(K269="", J269=""), "", IF(K269<0, "Vencido", IF(K269>(J269/2), "Supere la mitad", "Bajo la mitad"))) -> Vencido | P269: CE-GR-0278 | Q269: 46085 | R269: =IF(OR(Q269="", L269=""), "", NETWORKDAYS(L269, Q269, FESTIVOS!A268:A322)) -> -8
A270: OTRO | B270: CHRISTYAM CAMILO SALAZAR ROJAS | C270: ALCALDIA | D270: SOLICITUD DE COTIZACIÓN | E270: 269 | F270: 46073 | G270: FALSE | H270: FALSE | J270: =IF(A270="INFORMACIÓN O DOCUMENTOS", 10, IF(A270="CONSULTA", 30, IF(A270="FACTURACIÓN Y COBROS", 15, IF(A270="VINCULACIÓN Y DESVINCULACIÓN", 15, IF(A270="NO ES DE NUESTRA COMPETENCIA", 5, IF(A270="OTRO", 15, "")))))) -> 15 | K270: =IF(AND(F270<>"", L270<>""), NETWORKDAYS(TODAY(), L270-1, FESTIVOS!A$1:A$55), "") -> -64 | L270: =IF(AND(F270<>"", J270<>""), WORKDAY(F270, J270, FESTIVOS!A$1:A$55), "") -> 46094 | M270: LAURA GIRALDO | N270: =IF(K270="", "", MAX(0, K270 - (TODAY() - TODAY()))) -> 0 | O270: =IF(OR(K270="", J270=""), "", IF(K270<0, "Vencido", IF(K270>(J270/2), "Supere la mitad", "Bajo la mitad"))) -> Vencido | P270: CE-GC-0308 | Q270: 46085 | R270: =IF(OR(Q270="", L270=""), "", NETWORKDAYS(L270, Q270, FESTIVOS!A269:A323)) -> -8
A271: OTRO | B271: INGESCOR S.A.S. | C271: USUARIO DE SERVINTEGRAL | D271: SOLICITUD INFORMACIÓN DE CAPACITACIÓN EN GESTIÓN DE RESIDUOS Y SOSTENIBILIDAD | E271: 270 | F271: 46073 | G271: FALSE | H271: FALSE | J271: =IF(A271="INFORMACIÓN O DOCUMENTOS", 10, IF(A271="CONSULTA", 30, IF(A271="FACTURACIÓN Y COBROS", 15, IF(A271="VINCULACIÓN Y DESVINCULACIÓN", 15, IF(A271="NO ES DE NUESTRA COMPETENCIA", 5, IF(A271="OTRO", 15, "")))))) -> 15 | K271: =IF(AND(F271<>"", L271<>""), NETWORKDAYS(TODAY(), L271-1, FESTIVOS!A$1:A$55), "") -> -64 | L271: =IF(AND(F271<>"", J271<>""), WORKDAY(F271, J271, FESTIVOS!A$1:A$55), "") -> 46094 | M271: LAURA GIRALDO | N271: =IF(K271="", "", MAX(0, K271 - (TODAY() - TODAY()))) -> 0 | O271: =IF(OR(K271="", J271=""), "", IF(K271<0, "Vencido", IF(K271>(J271/2), "Supere la mitad", "Bajo la mitad"))) -> Vencido | P271: CE-GR-0293 | Q271: 46079 | R271: =IF(OR(Q271="", L271=""), "", NETWORKDAYS(L271, Q271, FESTIVOS!A270:A324)) -> -12
A272: OTRO | B272: MAYRA ARTUNDUAGA | C272: ESAC | D272: DESAFILIACIÓN | E272: 271 | F272: 46073 | G272: FALSE | H272: FALSE | I272: COMERCIAL | J272: =IF(A272="INFORMACIÓN O DOCUMENTOS", 10, IF(A272="CONSULTA", 30, IF(A272="FACTURACIÓN Y COBROS", 15, IF(A272="VINCULACIÓN Y DESVINCULACIÓN", 15, IF(A272="NO ES DE NUESTRA COMPETENCIA", 5, IF(A272="OTRO", 15, "")))))) -> 15 | K272: =IF(AND(F272<>"", L272<>""), NETWORKDAYS(TODAY(), L272-1, FESTIVOS!A$1:A$55), "") -> -64 | L272: =IF(AND(F272<>"", J272<>""), WORKDAY(F272, J272, FESTIVOS!A$1:A$55), "") -> 46094 | M272: LAURA GIRALDO | N272: =IF(K272="", "", MAX(0, K272 - (TODAY() - TODAY()))) -> 0 | O272: =IF(OR(K272="", J272=""), "", IF(K272<0, "Vencido", IF(K272>(J272/2), "Supere la mitad", "Bajo la mitad"))) -> Vencido | P272: CE-GC-0326 | Q272: 46091 | R272: FALSE
A273: OTRO | B273: MAYRA ARTUNDUAGA | C273: ESAC | D273: DESAFILIACIÓN | E273: 272 | F273: 46073 | G273: FALSE | H273: FALSE | I273: COMERCIAL | J273: =IF(A273="INFORMACIÓN O DOCUMENTOS", 10, IF(A273="CONSULTA", 30, IF(A273="FACTURACIÓN Y COBROS", 15, IF(A273="VINCULACIÓN Y DESVINCULACIÓN", 15, IF(A273="NO ES DE NUESTRA COMPETENCIA", 5, IF(A273="OTRO", 15, "")))))) -> 15 | K273: =IF(AND(F273<>"", L273<>""), NETWORKDAYS(TODAY(), L273-1, FESTIVOS!A$1:A$55), "") -> -64 | L273: =IF(AND(F273<>"", J273<>""), WORKDAY(F273, J273, FESTIVOS!A$1:A$55), "") -> 46094 | M273: LAURA GIRALDO | N273: =IF(K273="", "", MAX(0, K273 - (TODAY() - TODAY()))) -> 0 | O273: =IF(OR(K273="", J273=""), "", IF(K273<0, "Vencido", IF(K273>(J273/2), "Supere la mitad", "Bajo la mitad"))) -> Vencido | P273: CE-GC-0327 | Q273: NO FIRMADO | R273: FALSE
A274: OTRO | B274: MAYRA ARTUNDUAGA | C274: ESAC | D274: DESAFILIACIÓN | E274: 273 | F274: 46073 | G274: FALSE | H274: FALSE | I274: COMERCIAL | J274: =IF(A274="INFORMACIÓN O DOCUMENTOS", 10, IF(A274="CONSULTA", 30, IF(A274="FACTURACIÓN Y COBROS", 15, IF(A274="VINCULACIÓN Y DESVINCULACIÓN", 15, IF(A274="NO ES DE NUESTRA COMPETENCIA", 5, IF(A274="OTRO", 15, "")))))) -> 15 | K274: =IF(AND(F274<>"", L274<>""), NETWORKDAYS(TODAY(), L274-1, FESTIVOS!A$1:A$55), "") -> -64 | L274: =IF(AND(F274<>"", J274<>""), WORKDAY(F274, J274, FESTIVOS!A$1:A$55), "") -> 46094 | M274: LAURA GIRALDO | N274: =IF(K274="", "", MAX(0, K274 - (TODAY() - TODAY()))) -> 0 | O274: =IF(OR(K274="", J274=""), "", IF(K274<0, "Vencido", IF(K274>(J274/2), "Supere la mitad", "Bajo la mitad"))) -> Vencido | P274: CE-GC-0328 | Q274: NO FIRMADO | R274: FALSE
A275: OTRO | B275: MAYRA ARTUNDUAGA | C275: ESAC | D275: DESAFILIACIÓN | E275: 274 | F275: 46073 | G275: FALSE | H275: FALSE | I275: COMERCIAL | J275: =IF(A275="INFORMACIÓN O DOCUMENTOS", 10, IF(A275="CONSULTA", 30, IF(A275="FACTURACIÓN Y COBROS", 15, IF(A275="VINCULACIÓN Y DESVINCULACIÓN", 15, IF(A275="NO ES DE NUESTRA COMPETENCIA", 5, IF(A275="OTRO", 15, "")))))) -> 15 | K275: =IF(AND(F275<>"", L275<>""), NETWORKDAYS(TODAY(), L275-1, FESTIVOS!A$1:A$55), "") -> -64 | L275: =IF(AND(F275<>"", J275<>""), WORKDAY(F275, J275, FESTIVOS!A$1:A$55), "") -> 46094 | M275: LAURA GIRALDO | N275: =IF(K275="", "", MAX(0, K275 - (TODAY() - TODAY()))) -> 0 | O275: =IF(OR(K275="", J275=""), "", IF(K275<0, "Vencido", IF(K275>(J275/2), "Supere la mitad", "Bajo la mitad"))) -> Vencido | P275: CE-GC-0329 | Q275: NO FIRMADO | R275: FALSE
A276: OTRO | B276: MAYRA ARTUNDUAGA | C276: ESAC | D276: DESAFILIACIÓN | E276: 275 | F276: 46073 | G276: FALSE | H276: FALSE | I276: COMERCIAL | J276: =IF(A276="INFORMACIÓN O DOCUMENTOS", 10, IF(A276="CONSULTA", 30, IF(A276="FACTURACIÓN Y COBROS", 15, IF(A276="VINCULACIÓN Y DESVINCULACIÓN", 15, IF(A276="NO ES DE NUESTRA COMPETENCIA", 5, IF(A276="OTRO", 15, "")))))) -> 15 | K276: =IF(AND(F276<>"", L276<>""), NETWORKDAYS(TODAY(), L276-1, FESTIVOS!A$1:A$55), "") -> -64 | L276: =IF(AND(F276<>"", J276<>""), WORKDAY(F276, J276, FESTIVOS!A$1:A$55), "") -> 46094 | M276: LAURA GIRALDO | N276: =IF(K276="", "", MAX(0, K276 - (TODAY() - TODAY()))) -> 0 | O276: =IF(OR(K276="", J276=""), "", IF(K276<0, "Vencido", IF(K276>(J276/2), "Supere la mitad", "Bajo la mitad"))) -> Vencido | P276: CE-GC-0330 | Q276: 46095 | R276: FALSE
A277: OTRO | B277: MAYRA ARTUNDUAGA | C277: ESAC | D277: DESAFILIACIÓN | E277: 276 | F277: 46073 | G277: FALSE | H277: FALSE | I277: COMERCIAL | J277: =IF(A277="INFORMACIÓN O DOCUMENTOS", 10, IF(A277="CONSULTA", 30, IF(A277="FACTURACIÓN Y COBROS", 15, IF(A277="VINCULACIÓN Y DESVINCULACIÓN", 15, IF(A277="NO ES DE NUESTRA COMPETENCIA", 5, IF(A277="OTRO", 15, "")))))) -> 15 | K277: =IF(AND(F277<>"", L277<>""), NETWORKDAYS(TODAY(), L277-1, FESTIVOS!A$1:A$55), "") -> -64 | L277: =IF(AND(F277<>"", J277<>""), WORKDAY(F277, J277, FESTIVOS!A$1:A$55), "") -> 46094 | M277: LAURA GIRALDO | N277: =IF(K277="", "", MAX(0, K277 - (TODAY() - TODAY()))) -> 0 | O277: =IF(OR(K277="", J277=""), "", IF(K277<0, "Vencido", IF(K277>(J277/2), "Supere la mitad", "Bajo la mitad"))) -> Vencido | P277: CE-GC-0331 | Q277: 46085 | R277: FALSE
A278: OTRO | B278: MAYRA ARTUNDUAGA | C278: ESAC | D278: DESAFILIACIÓN | E278: 277 | F278: 46073 | G278: FALSE | H278: FALSE | I278: COMERCIAL | J278: =IF(A278="INFORMACIÓN O DOCUMENTOS", 10, IF(A278="CONSULTA", 30, IF(A278="FACTURACIÓN Y COBROS", 15, IF(A278="VINCULACIÓN Y DESVINCULACIÓN", 15, IF(A278="NO ES DE NUESTRA COMPETENCIA", 5, IF(A278="OTRO", 15, "")))))) -> 15 | K278: =IF(AND(F278<>"", L278<>""), NETWORKDAYS(TODAY(), L278-1, FESTIVOS!A$1:A$55), "") -> -64 | L278: =IF(AND(F278<>"", J278<>""), WORKDAY(F278, J278, FESTIVOS!A$1:A$55), "") -> 46094 | M278: LAURA GIRALDO | N278: =IF(K278="", "", MAX(0, K278 - (TODAY() - TODAY()))) -> 0 | O278: =IF(OR(K278="", J278=""), "", IF(K278<0, "Vencido", IF(K278>(J278/2), "Supere la mitad", "Bajo la mitad"))) -> Vencido | P278: CE-GC-0332 | Q278: NO FIRMADO | R278: FALSE
A279: OTRO | B279: Luis Eduardo Guevara Joven | C279: USUARIO DE SERVINTEGRAL | D279: DERECHO DE PETICIÓN | E279: 278 | F279: 46073 | G279: FALSE | H279: FALSE | I279: COMERCIAL | J279: =IF(A279="INFORMACIÓN O DOCUMENTOS", 10, IF(A279="CONSULTA", 30, IF(A279="FACTURACIÓN Y COBROS", 15, IF(A279="VINCULACIÓN Y DESVINCULACIÓN", 15, IF(A279="NO ES DE NUESTRA COMPETENCIA", 5, IF(A279="OTRO", 15, "")))))) -> 15 | K279: =IF(AND(F279<>"", L279<>""), NETWORKDAYS(TODAY(), L279-1, FESTIVOS!A$1:A$55), "") -> -64 | L279: =IF(AND(F279<>"", J279<>""), WORKDAY(F279, J279, FESTIVOS!A$1:A$55), "") -> 46094 | M279: LAURA GIRALDO | N279: =IF(K279="", "", MAX(0, K279 - (TODAY() - TODAY()))) -> 0 | O279: =IF(OR(K279="", J279=""), "", IF(K279<0, "Vencido", IF(K279>(J279/2), "Supere la mitad", "Bajo la mitad"))) -> Vencido | P279: CE-GC-0323 | Q279: 46090 | R279: FALSE
A280: OTRO | B280: MAYRA ARTUNDUAGA | C280: ESAC | D280: DESAFILIACIÓN | E280: 279 | F280: 46073 | G280: FALSE | H280: FALSE | I280: COMERCIAL | J280: =IF(A280="INFORMACIÓN O DOCUMENTOS", 10, IF(A280="CONSULTA", 30, IF(A280="FACTURACIÓN Y COBROS", 15, IF(A280="VINCULACIÓN Y DESVINCULACIÓN", 15, IF(A280="NO ES DE NUESTRA COMPETENCIA", 5, IF(A280="OTRO", 15, "")))))) -> 15 | K280: =IF(AND(F280<>"", L280<>""), NETWORKDAYS(TODAY(), L280-1, FESTIVOS!A$1:A$55), "") -> -64 | L280: =IF(AND(F280<>"", J280<>""), WORKDAY(F280, J280, FESTIVOS!A$1:A$55), "") -> 46094 | M280: LAURA GIRALDO | N280: =IF(K280="", "", MAX(0, K280 - (TODAY() - TODAY()))) -> 0 | O280: =IF(OR(K280="", J280=""), "", IF(K280<0, "Vencido", IF(K280>(J280/2), "Supere la mitad", "Bajo la mitad"))) -> Vencido | P280: CE-GC-0333 | Q280: 46090 | R280: FALSE
A281: OTRO | B281: ZAMORA ARISTIZABAL JHOHN | C281: USUARIO DE SERVINTEGRAL | D281: SOLIICTUD DE APOYO | E281: 280 | F281: 46073 | G281: FALSE | H281: FALSE | I281: COMERCIAL | J281: =IF(A281="INFORMACIÓN O DOCUMENTOS", 10, IF(A281="CONSULTA", 30, IF(A281="FACTURACIÓN Y COBROS", 15, IF(A281="VINCULACIÓN Y DESVINCULACIÓN", 15, IF(A281="NO ES DE NUESTRA COMPETENCIA", 5, IF(A281="OTRO", 15, "")))))) -> 15 | K281: =IF(AND(F281<>"", L281<>""), NETWORKDAYS(TODAY(), L281-1, FESTIVOS!A$1:A$55), "") -> -64 | L281: =IF(AND(F281<>"", J281<>""), WORKDAY(F281, J281, FESTIVOS!A$1:A$55), "") -> 46094 | M281: LAURA GIRALDO | N281: =IF(K281="", "", MAX(0, K281 - (TODAY() - TODAY()))) -> 0 | O281: =IF(OR(K281="", J281=""), "", IF(K281<0, "Vencido", IF(K281>(J281/2), "Supere la mitad", "Bajo la mitad"))) -> Vencido | P281: CE-GC-0400 | Q281: 46094 | R281: FALSE
A282: OTRO | B282: BELISARIO MONTOYA | C282: USUARIO DE SERVINTEGRAL | D282: SOLICITUD DE VISITA | E282: 281 | F282: 46076 | G282: FALSE | H282: FALSE | I282: RESIDUOS | J282: =IF(A282="INFORMACIÓN O DOCUMENTOS", 10, IF(A282="CONSULTA", 30, IF(A282="FACTURACIÓN Y COBROS", 15, IF(A282="VINCULACIÓN Y DESVINCULACIÓN", 15, IF(A282="NO ES DE NUESTRA COMPETENCIA", 5, IF(A282="OTRO", 15, "")))))) -> 15 | K282: =IF(AND(F282<>"", L282<>""), NETWORKDAYS(TODAY(), L282-1, FESTIVOS!A$1:A$55), "") -> -62 | L282: =IF(AND(F282<>"", J282<>""), WORKDAY(F282, J282, FESTIVOS!A$1:A$55), "") -> 46097 | M282: LAURA GIRALDO | N282: =IF(K282="", "", MAX(0, K282 - (TODAY() - TODAY()))) -> 0 | O282: =IF(OR(K282="", J282=""), "", IF(K282<0, "Vencido", IF(K282>(J282/2), "Supere la mitad", "Bajo la mitad"))) -> Vencido | P282: CE-GR-0290 | Q282: 46080 | R282: FALSE
A283: OTRO | B283: CARLOS ESCOBAR | C283: USUARIO DE SERVINTEGRAL | D283: DERECHO DE PETICIÓN | E283: 282 | F283: 46076 | G283: FALSE | H283: FALSE | I283: COMERCIAL | J283: =IF(A283="INFORMACIÓN O DOCUMENTOS", 10, IF(A283="CONSULTA", 30, IF(A283="FACTURACIÓN Y COBROS", 15, IF(A283="VINCULACIÓN Y DESVINCULACIÓN", 15, IF(A283="NO ES DE NUESTRA COMPETENCIA", 5, IF(A283="OTRO", 15, "")))))) -> 15 | K283: =IF(AND(F283<>"", L283<>""), NETWORKDAYS(TODAY(), L283-1, FESTIVOS!A$1:A$55), "") -> -62 | L283: =IF(AND(F283<>"", J283<>""), WORKDAY(F283, J283, FESTIVOS!A$1:A$55), "") -> 46097 | M283: LAURA GIRALDO | N283: =IF(K283="", "", MAX(0, K283 - (TODAY() - TODAY()))) -> 0 | O283: =IF(OR(K283="", J283=""), "", IF(K283<0, "Vencido", IF(K283>(J283/2), "Supere la mitad", "Bajo la mitad"))) -> Vencido | P283: CE-GC-0279 | Q283: 46086 | R283: FALSE
A284: OTRO | B284: ANDRES FELIPE CABRERA | C284: USUARIO DE SERVINTEGRAL | D284: COTIZACIÓN | E284: 283 | F284: 46076 | G284: FALSE | H284: FALSE | I284: COMERCIAL | J284: =IF(A284="INFORMACIÓN O DOCUMENTOS", 10, IF(A284="CONSULTA", 30, IF(A284="FACTURACIÓN Y COBROS", 15, IF(A284="VINCULACIÓN Y DESVINCULACIÓN", 15, IF(A284="NO ES DE NUESTRA COMPETENCIA", 5, IF(A284="OTRO", 15, "")))))) -> 15 | K284: =IF(AND(F284<>"", L284<>""), NETWORKDAYS(TODAY(), L284-1, FESTIVOS!A$1:A$55), "") -> -62 | L284: =IF(AND(F284<>"", J284<>""), WORKDAY(F284, J284, FESTIVOS!A$1:A$55), "") -> 46097 | M284: LAURA GIRALDO | N284: =IF(K284="", "", MAX(0, K284 - (TODAY() - TODAY()))) -> 0 | O284: =IF(OR(K284="", J284=""), "", IF(K284<0, "Vencido", IF(K284>(J284/2), "Supere la mitad", "Bajo la mitad"))) -> Vencido | P284: CE-GC-0291 | Q284: 46079 | R284: =IF(OR(Q284="", L284=""), "", NETWORKDAYS(L284, Q284, FESTIVOS!A283:A337)) -> -13
A285: OTRO | B285: CINDY VANESSA CONTRERAS ZAMBRANO | C285: USUARIO DE SERVINTEGRAL | D285: Invitación a capacitación gratuita “Reglamento Interno de Trabajo” | E285: 284 | F285: 46076 | G285: FALSE | H285: FALSE | I285: TALENTO HUMANO | J285: =IF(A285="INFORMACIÓN O DOCUMENTOS", 10, IF(A285="CONSULTA", 30, IF(A285="FACTURACIÓN Y COBROS", 15, IF(A285="VINCULACIÓN Y DESVINCULACIÓN", 15, IF(A285="NO ES DE NUESTRA COMPETENCIA", 5, IF(A285="OTRO", 15, "")))))) -> 15 | K285: =IF(AND(F285<>"", L285<>""), NETWORKDAYS(TODAY(), L285-1, FESTIVOS!A$1:A$55), "") -> -62 | L285: =IF(AND(F285<>"", J285<>""), WORKDAY(F285, J285, FESTIVOS!A$1:A$55), "") -> 46097 | M285: LAURA GIRALDO | N285: =IF(K285="", "", MAX(0, K285 - (TODAY() - TODAY()))) -> 0 | O285: =IF(OR(K285="", J285=""), "", IF(K285<0, "Vencido", IF(K285>(J285/2), "Supere la mitad", "Bajo la mitad"))) -> Vencido | P285: NO REQUIERE RESPUESTA | Q285: FALSE | R285: =IF(OR(Q285="", L285=""), "", NETWORKDAYS(L285, Q285, FESTIVOS!A284:A338)) -> #VALUE!
A286: OTRO | B286: WILSON BECERRA | C286: USUARIO DE SERVINTEGRAL | D286: SOLICITUD PUERTA A PUERTA | E286: 285 | F286: 46076 | G286: FALSE | H286: FALSE | I286: RESIDUOS | J286: =IF(A286="INFORMACIÓN O DOCUMENTOS", 10, IF(A286="CONSULTA", 30, IF(A286="FACTURACIÓN Y COBROS", 15, IF(A286="VINCULACIÓN Y DESVINCULACIÓN", 15, IF(A286="NO ES DE NUESTRA COMPETENCIA", 5, IF(A286="OTRO", 15, "")))))) -> 15 | K286: =IF(AND(F286<>"", L286<>""), NETWORKDAYS(TODAY(), L286-1, FESTIVOS!A$1:A$55), "") -> -62 | L286: =IF(AND(F286<>"", J286<>""), WORKDAY(F286, J286, FESTIVOS!A$1:A$55), "") -> 46097 | M286: LAURA GIRALDO | N286: =IF(K286="", "", MAX(0, K286 - (TODAY() - TODAY()))) -> 0 | O286: =IF(OR(K286="", J286=""), "", IF(K286<0, "Vencido", IF(K286>(J286/2), "Supere la mitad", "Bajo la mitad"))) -> Vencido | P286: CE-GR-0352 | Q286: 46094 | R286: =IF(OR(Q286="", L286=""), "", NETWORKDAYS(L286, Q286, FESTIVOS!A285:A339)) -> -2
A287: OTRO | B287: Vilma Socorro Luengas | C287: USUARIO DE SERVINTEGRAL | D287: Petición respetuosa | E287: 286 | F287: 46076 | G287: FALSE | H287: FALSE | J287: =IF(A287="INFORMACIÓN O DOCUMENTOS", 10, IF(A287="CONSULTA", 30, IF(A287="FACTURACIÓN Y COBROS", 15, IF(A287="VINCULACIÓN Y DESVINCULACIÓN", 15, IF(A287="NO ES DE NUESTRA COMPETENCIA", 5, IF(A287="OTRO", 15, "")))))) -> 15 | K287: =IF(AND(F287<>"", L287<>""), NETWORKDAYS(TODAY(), L287-1, FESTIVOS!A$1:A$55), "") -> -62 | L287: =IF(AND(F287<>"", J287<>""), WORKDAY(F287, J287, FESTIVOS!A$1:A$55), "") -> 46097 | M287: LAURA GIRALDO | N287: =IF(K287="", "", MAX(0, K287 - (TODAY() - TODAY()))) -> 0 | O287: =IF(OR(K287="", J287=""), "", IF(K287<0, "Vencido", IF(K287>(J287/2), "Supere la mitad", "Bajo la mitad"))) -> Vencido | P287: CE-GR-0295 | Q287: 46079 | R287: =IF(OR(Q287="", L287=""), "", NETWORKDAYS(L287, Q287, FESTIVOS!A286:A340)) -> -13
A288: OTRO | B288: Iván Alexander Ribon Castillo | C288: USUARIO DE SERVINTEGRAL | D288: CITACION A VALORACION # 1 Y TESTIGO 94043507 MARIANO OSWALDO ROJAS ARANGO | E288: 287 | F288: 46076 | G288: FALSE | H288: FALSE | I288: TALENTO HUMANO | J288: =IF(A288="INFORMACIÓN O DOCUMENTOS", 10, IF(A288="CONSULTA", 30, IF(A288="FACTURACIÓN Y COBROS", 15, IF(A288="VINCULACIÓN Y DESVINCULACIÓN", 15, IF(A288="NO ES DE NUESTRA COMPETENCIA", 5, IF(A288="OTRO", 15, "")))))) -> 15 | K288: =IF(AND(F288<>"", L288<>""), NETWORKDAYS(TODAY(), L288-1, FESTIVOS!A$1:A$55), "") -> -62 | L288: =IF(AND(F288<>"", J288<>""), WORKDAY(F288, J288, FESTIVOS!A$1:A$55), "") -> 46097 | M288: LAURA GIRALDO | N288: =IF(K288="", "", MAX(0, K288 - (TODAY() - TODAY()))) -> 0 | O288: FALSE | P288: NO REQUIERE RESPUESTA | Q288: FALSE | R288: =IF(OR(Q288="", L288=""), "", NETWORKDAYS(L288, Q288, FESTIVOS!A287:A341)) -> #VALUE!
A289: OTRO | B289: LUZ DARY MURILLO GOMEZ | C289: ALCALDIA | D289: Solicitud de apoyo institucional - Estrategia grandes voluntarios | E289: 288 | F289: 46076 | G289: FALSE | H289: FALSE | I289: COMERCIAL | J289: =IF(A289="INFORMACIÓN O DOCUMENTOS", 10, IF(A289="CONSULTA", 30, IF(A289="FACTURACIÓN Y COBROS", 15, IF(A289="VINCULACIÓN Y DESVINCULACIÓN", 15, IF(A289="NO ES DE NUESTRA COMPETENCIA", 5, IF(A289="OTRO", 15, "")))))) -> 15 | K289: =IF(AND(F289<>"", L289<>""), NETWORKDAYS(TODAY(), L289-1, FESTIVOS!A$1:A$55), "") -> -62 | L289: =IF(AND(F289<>"", J289<>""), WORKDAY(F289, J289, FESTIVOS!A$1:A$55), "") -> 46097 | M289: LAURA GIRALDO | N289: =IF(K289="", "", MAX(0, K289 - (TODAY() - TODAY()))) -> 0 | O289: =IF(OR(K289="", J289=""), "", IF(K289<0, "Vencido", IF(K289>(J289/2), "Supere la mitad", "Bajo la mitad"))) -> Vencido | P289: CE-GC-0296 | Q289: 46084 | R289: =IF(OR(Q289="", L289=""), "", NETWORKDAYS(L289, Q289, FESTIVOS!A288:A342)) -> -10
A290: OTRO | B290: CHRISTYAM CAMILO SALAZAR ROJAS | C290: ALCALDIA | D290: 200.09.116-106 Solicitud de apoyo institucional para la segunda jornada de limpieza, reforestación y cátedra ambiental en el Humedal El San Luis SERVINTEGRAL | E290: 289 | F290: 46076 | G290: FALSE | H290: FALSE | I290: COMERCIAL | J290: =IF(A290="INFORMACIÓN O DOCUMENTOS", 10, IF(A290="CONSULTA", 30, IF(A290="FACTURACIÓN Y COBROS", 15, IF(A290="VINCULACIÓN Y DESVINCULACIÓN", 15, IF(A290="NO ES DE NUESTRA COMPETENCIA", 5, IF(A290="OTRO", 15, "")))))) -> 15 | K290: =IF(AND(F290<>"", L290<>""), NETWORKDAYS(TODAY(), L290-1, FESTIVOS!A$1:A$55), "") -> -62 | L290: =IF(AND(F290<>"", J290<>""), WORKDAY(F290, J290, FESTIVOS!A$1:A$55), "") -> 46097 | M290: LAURA GIRALDO | N290: =IF(K290="", "", MAX(0, K290 - (TODAY() - TODAY()))) -> 0 | O290: =IF(OR(K290="", J290=""), "", IF(K290<0, "Vencido", IF(K290>(J290/2), "Supere la mitad", "Bajo la mitad"))) -> Vencido | P290: CE-GC-0362 | Q290: 46097 | R290: =IF(OR(Q290="", L290=""), "", NETWORKDAYS(L290, Q290, FESTIVOS!A289:A343)) -> 1
A291: OTRO | B291: SERGIO POLANIA | C291: USUARIO DE SERVINTEGRAL | D291: SOLICITUD DE CERTIFICADO | E291: 290 | F291: 46076 | G291: FALSE | H291: FALSE | I291: COMERCIAL | J291: =IF(A291="INFORMACIÓN O DOCUMENTOS", 10, IF(A291="CONSULTA", 30, IF(A291="FACTURACIÓN Y COBROS", 15, IF(A291="VINCULACIÓN Y DESVINCULACIÓN", 15, IF(A291="NO ES DE NUESTRA COMPETENCIA", 5, IF(A291="OTRO", 15, "")))))) -> 15 | K291: =IF(AND(F291<>"", L291<>""), NETWORKDAYS(TODAY(), L291-1, FESTIVOS!A$1:A$55), "") -> -62 | L291: =IF(AND(F291<>"", J291<>""), WORKDAY(F291, J291, FESTIVOS!A$1:A$55), "") -> 46097 | M291: LAURA GIRALDO | N291: =IF(K291="", "", MAX(0, K291 - (TODAY() - TODAY()))) -> 0 | O291: =IF(OR(K291="", J291=""), "", IF(K291<0, "Vencido", IF(K291>(J291/2), "Supere la mitad", "Bajo la mitad"))) -> Vencido | P291: CE-GC-0316 | Q291: 46085 | R291: =IF(OR(Q291="", L291=""), "", NETWORKDAYS(L291, Q291, FESTIVOS!A290:A344)) -> -9
A292: OTRO | B292: DISTRICARNES EL GRAN NOVILLO | C292: USUARIO DE SERVINTEGRAL | D292: SOLICITUD CERTIFICADO PRESTACION DEL SERVICIO DE ASEO | E292: 291 | F292: 46077 | G292: FALSE | H292: FALSE | I292: COMERCIAL | J292: =IF(A292="INFORMACIÓN O DOCUMENTOS", 10, IF(A292="CONSULTA", 30, IF(A292="FACTURACIÓN Y COBROS", 15, IF(A292="VINCULACIÓN Y DESVINCULACIÓN", 15, IF(A292="NO ES DE NUESTRA COMPETENCIA", 5, IF(A292="OTRO", 15, "")))))) -> 15 | K292: =IF(AND(F292<>"", L292<>""), NETWORKDAYS(TODAY(), L292-1, FESTIVOS!A$1:A$55), "") -> -62 | L292: =IF(AND(F292<>"", J292<>""), WORKDAY(F292, J292, FESTIVOS!A$1:A$55), "") -> 46098 | M292: LAURA GIRALDO | N292: =IF(K292="", "", MAX(0, K292 - (TODAY() - TODAY()))) -> 0 | O292: =IF(OR(K292="", J292=""), "", IF(K292<0, "Vencido", IF(K292>(J292/2), "Supere la mitad", "Bajo la mitad"))) -> Vencido | P292: CE-GC-0297 | Q292: 46079 | R292: =IF(OR(Q292="", L292=""), "", NETWORKDAYS(L292, Q292, FESTIVOS!A291:A345)) -> -14
A293: OTRO | B293: KARLA JOHANA LISCANO CORREA | C293: ALCALDIA | D293: Convocatoria Comité de Conocimiento del Riesgo | E293: 292 | F293: 46077 | G293: FALSE | H293: FALSE | I293: COMERCIAL | J293: =IF(A293="INFORMACIÓN O DOCUMENTOS", 10, IF(A293="CONSULTA", 30, IF(A293="FACTURACIÓN Y COBROS", 15, IF(A293="VINCULACIÓN Y DESVINCULACIÓN", 15, IF(A293="NO ES DE NUESTRA COMPETENCIA", 5, IF(A293="OTRO", 15, "")))))) -> 15 | K293: =IF(AND(F293<>"", L293<>""), NETWORKDAYS(TODAY(), L293-1, FESTIVOS!A$1:A$55), "") -> -62 | L293: =IF(AND(F293<>"", J293<>""), WORKDAY(F293, J293, FESTIVOS!A$1:A$55), "") -> 46098 | M293: LAURA GIRALDO | N293: =IF(K293="", "", MAX(0, K293 - (TODAY() - TODAY()))) -> 0 | O293: =IF(OR(K293="", J293=""), "", IF(K293<0, "Vencido", IF(K293>(J293/2), "Supere la mitad", "Bajo la mitad"))) -> Vencido | P293: CE-GC-0267 | Q293: 46094 | R293: =IF(OR(Q293="", L293=""), "", NETWORKDAYS(L293, Q293, FESTIVOS!A292:A346)) -> -3
A294: OTRO | B294: Euler Alexander Paniagua Zambrano | C294: USUARIO DE SERVINTEGRAL | D294: Solicitud de Apoyo para limpieza en sector Caseta Comunal del barrio El Lenin | E294: 293 | F294: 46077 | G294: FALSE | H294: FALSE | I294: COMERCIAL | J294: =IF(A294="INFORMACIÓN O DOCUMENTOS", 10, IF(A294="CONSULTA", 30, IF(A294="FACTURACIÓN Y COBROS", 15, IF(A294="VINCULACIÓN Y DESVINCULACIÓN", 15, IF(A294="NO ES DE NUESTRA COMPETENCIA", 5, IF(A294="OTRO", 15, "")))))) -> 15 | K294: =IF(AND(F294<>"", L294<>""), NETWORKDAYS(TODAY(), L294-1, FESTIVOS!A$1:A$55), "") -> -62 | L294: =IF(AND(F294<>"", J294<>""), WORKDAY(F294, J294, FESTIVOS!A$1:A$55), "") -> 46098 | M294: LAURA GIRALDO | N294: =IF(K294="", "", MAX(0, K294 - (TODAY() - TODAY()))) -> 0 | O294: =IF(OR(K294="", J294=""), "", IF(K294<0, "Vencido", IF(K294>(J294/2), "Supere la mitad", "Bajo la mitad"))) -> Vencido | P294: CE-GC-0346 | Q294: 46098 | R294: =IF(OR(Q294="", L294=""), "", NETWORKDAYS(L294, Q294, FESTIVOS!A293:A347)) -> 1
A295: OTRO | B295: HEBERTH TOBAR VEGA | C295: USUARIO DE SERVINTEGRAL | D295: Petición para la Instalación de Contenedor de Residuos Sólidos en la carrera 9 NO.8C-87 Barrio La Estrella | E295: 294 | F295: 46077 | G295: FALSE | H295: FALSE | I295: COMERCIAL | J295: =IF(A295="INFORMACIÓN O DOCUMENTOS", 10, IF(A295="CONSULTA", 30, IF(A295="FACTURACIÓN Y COBROS", 15, IF(A295="VINCULACIÓN Y DESVINCULACIÓN", 15, IF(A295="NO ES DE NUESTRA COMPETENCIA", 5, IF(A295="OTRO", 15, "")))))) -> 15 | K295: =IF(AND(F295<>"", L295<>""), NETWORKDAYS(TODAY(), L295-1, FESTIVOS!A$1:A$55), "") -> -62 | L295: =IF(AND(F295<>"", J295<>""), WORKDAY(F295, J295, FESTIVOS!A$1:A$55), "") -> 46098 | M295: LAURA GIRALDO | N295: =IF(K295="", "", MAX(0, K295 - (TODAY() - TODAY()))) -> 0 | O295: =IF(OR(K295="", J295=""), "", IF(K295<0, "Vencido", IF(K295>(J295/2), "Supere la mitad", "Bajo la mitad"))) -> Vencido | P295: CE-GC-0305 | Q295: 46097 | R295: =IF(OR(Q295="", L295=""), "", NETWORKDAYS(L295, Q295, FESTIVOS!A294:A348)) -> -2
A296: OTRO | B296: CARLOS ESCOBAR | C296: USUARIO DE SERVINTEGRAL | D296: DERECHO DE PETICIÓN | E296: 295 | F296: 46078 | G296: FALSE | H296: FALSE | I296: COMERCIAL | J296: =IF(A296="INFORMACIÓN O DOCUMENTOS", 10, IF(A296="CONSULTA", 30, IF(A296="FACTURACIÓN Y COBROS", 15, IF(A296="VINCULACIÓN Y DESVINCULACIÓN", 15, IF(A296="NO ES DE NUESTRA COMPETENCIA", 5, IF(A296="OTRO", 15, "")))))) -> 15 | K296: =IF(AND(F296<>"", L296<>""), NETWORKDAYS(TODAY(), L296-1, FESTIVOS!A$1:A$55), "") -> -61 | L296: =IF(AND(F296<>"", J296<>""), WORKDAY(F296, J296, FESTIVOS!A$1:A$55), "") -> 46099 | M296: LAURA GIRALDO | N296: =IF(K296="", "", MAX(0, K296 - (TODAY() - TODAY()))) -> 0 | O296: =IF(OR(K296="", J296=""), "", IF(K296<0, "Vencido", IF(K296>(J296/2), "Supere la mitad", "Bajo la mitad"))) -> Vencido | P296: CE-GC-0279 | Q296: 46086 | R296: =IF(OR(Q296="", L296=""), "", NETWORKDAYS(L296, Q296, FESTIVOS!A295:A349)) -> -10
A297: OTRO | B297: MARIA FERNANDA JARAMILLO TRUJILLO | C297: SUPER | D297: Remisión memorias mesa de trabajo de fecha 29 de enero de 2026 | E297: 296 | F297: 46078 | G297: FALSE | H297: FALSE | I297: JURÍDICA | J297: =IF(A297="INFORMACIÓN O DOCUMENTOS", 10, IF(A297="CONSULTA", 30, IF(A297="FACTURACIÓN Y COBROS", 15, IF(A297="VINCULACIÓN Y DESVINCULACIÓN", 15, IF(A297="NO ES DE NUESTRA COMPETENCIA", 5, IF(A297="OTRO", 15, "")))))) -> 15 | K297: =IF(AND(F297<>"", L297<>""), NETWORKDAYS(TODAY(), L297-1, FESTIVOS!A$1:A$55), "") -> -61 | L297: =IF(AND(F297<>"", J297<>""), WORKDAY(F297, J297, FESTIVOS!A$1:A$55), "") -> 46099 | M297: LAURA GIRALDO | N297: =IF(K297="", "", MAX(0, K297 - (TODAY() - TODAY()))) -> 0 | O297: =IF(OR(K297="", J297=""), "", IF(K297<0, "Vencido", IF(K297>(J297/2), "Supere la mitad", "Bajo la mitad"))) -> Vencido | P297: CE-GC-0033 | Q297: 46036 | R297: =IF(OR(Q297="", L297=""), "", NETWORKDAYS(L297, Q297, FESTIVOS!A296:A350)) -> -46
A298: OTRO | B298: LINA PATRICIA MEJIA ROJAS | C298: ALCALDIA | D298: Solicitud de apoyo para recolección de residuos verdes-SAN JUDAS | E298: 297 | F298: 46078 | G298: FALSE | H298: FALSE | I298: RESIDUOS | J298: =IF(A298="INFORMACIÓN O DOCUMENTOS", 10, IF(A298="CONSULTA", 30, IF(A298="FACTURACIÓN Y COBROS", 15, IF(A298="VINCULACIÓN Y DESVINCULACIÓN", 15, IF(A298="NO ES DE NUESTRA COMPETENCIA", 5, IF(A298="OTRO", 15, "")))))) -> 15 | K298: =IF(AND(F298<>"", L298<>""), NETWORKDAYS(TODAY(), L298-1, FESTIVOS!A$1:A$55), "") -> -61 | L298: =IF(AND(F298<>"", J298<>""), WORKDAY(F298, J298, FESTIVOS!A$1:A$55), "") -> 46099 | M298: LAURA GIRALDO | N298: =IF(K298="", "", MAX(0, K298 - (TODAY() - TODAY()))) -> 0 | O298: =IF(OR(K298="", J298=""), "", IF(K298<0, "Vencido", IF(K298>(J298/2), "Supere la mitad", "Bajo la mitad"))) -> Vencido | P298: CE-GR-0301 | Q298: 46084 | R298: =IF(OR(Q298="", L298=""), "", NETWORKDAYS(L298, Q298, FESTIVOS!A297:A351)) -> -12
A299: OTRO | B299: BEATRIZ ELENA GUTIERREZ | C299: USUARIO DE SERVINTEGRAL | D299: ACCIÓN DE TUTELA | E299: 298 | F299: 46078 | G299: FALSE | H299: FALSE | I299: COMERCIAL | J299: =IF(A299="INFORMACIÓN O DOCUMENTOS", 10, IF(A299="CONSULTA", 30, IF(A299="FACTURACIÓN Y COBROS", 15, IF(A299="VINCULACIÓN Y DESVINCULACIÓN", 15, IF(A299="NO ES DE NUESTRA COMPETENCIA", 5, IF(A299="OTRO", 15, "")))))) -> 15 | K299: =IF(AND(F299<>"", L299<>""), NETWORKDAYS(TODAY(), L299-1, FESTIVOS!A$1:A$55), "") -> -61 | L299: =IF(AND(F299<>"", J299<>""), WORKDAY(F299, J299, FESTIVOS!A$1:A$55), "") -> 46099 | M299: LAURA GIRALDO | N299: =IF(K299="", "", MAX(0, K299 - (TODAY() - TODAY()))) -> 0 | O299: =IF(OR(K299="", J299=""), "", IF(K299<0, "Vencido", IF(K299>(J299/2), "Supere la mitad", "Bajo la mitad"))) -> Vencido | P299: NO REQUIERE RESPUESTA | Q299: FALSE | R299: FALSE
A300: OTRO | B300: ILIANA ROJAS | C300: USUARIO DE SERVINTEGRAL | D300: SOLICITUD DE APOYO INSTITUCIONAL | E300: 299 | F300: 46078 | G300: FALSE | H300: FALSE | I300: COMERCIAL | J300: =IF(A300="INFORMACIÓN O DOCUMENTOS", 10, IF(A300="CONSULTA", 30, IF(A300="FACTURACIÓN Y COBROS", 15, IF(A300="VINCULACIÓN Y DESVINCULACIÓN", 15, IF(A300="NO ES DE NUESTRA COMPETENCIA", 5, IF(A300="OTRO", 15, "")))))) -> 15 | K300: =IF(AND(F300<>"", L300<>""), NETWORKDAYS(TODAY(), L300-1, FESTIVOS!A$1:A$55), "") -> -61 | L300: =IF(AND(F300<>"", J300<>""), WORKDAY(F300, J300, FESTIVOS!A$1:A$55), "") -> 46099 | M300: LAURA GIRALDO | N300: =IF(K300="", "", MAX(0, K300 - (TODAY() - TODAY()))) -> 0 | O300: =IF(OR(K300="", J300=""), "", IF(K300<0, "Vencido", IF(K300>(J300/2), "Supere la mitad", "Bajo la mitad"))) -> Vencido | P300: CE- GC-0403 | Q300: 46105 | R300: =IF(OR(Q300="", L300=""), "", NETWORKDAYS(L300, Q300, FESTIVOS!A299:A353)) -> 5
A301: OTRO | B301: MAIBRY LIZETH CALDERON | C301: USUARIO DE SERVINTEGRAL | D301: SOLICITUD DE CERTIFICACIÓN | E301: 300 | F301: 46078 | G301: FALSE | H301: FALSE | I301: COMERCIAL | J301: =IF(A301="INFORMACIÓN O DOCUMENTOS", 10, IF(A301="CONSULTA", 30, IF(A301="FACTURACIÓN Y COBROS", 15, IF(A301="VINCULACIÓN Y DESVINCULACIÓN", 15, IF(A301="NO ES DE NUESTRA COMPETENCIA", 5, IF(A301="OTRO", 15, "")))))) -> 15 | K301: =IF(AND(F301<>"", L301<>""), NETWORKDAYS(TODAY(), L301-1, FESTIVOS!A$1:A$55), "") -> -61 | L301: =IF(AND(F301<>"", J301<>""), WORKDAY(F301, J301, FESTIVOS!A$1:A$55), "") -> 46099 | M301: LAURA GIRALDO | N301: =IF(K301="", "", MAX(0, K301 - (TODAY() - TODAY()))) -> 0 | O301: =IF(OR(K301="", J301=""), "", IF(K301<0, "Vencido", IF(K301>(J301/2), "Supere la mitad", "Bajo la mitad"))) -> Vencido | P301: CE-GC-0350 | Q301: 46097 | R301: =IF(OR(Q301="", L301=""), "", NETWORKDAYS(L301, Q301, FESTIVOS!A300:A354)) -> -3
A302: OTRO | B302: ARLEY CAICEDO | C302: USUARIO DE SERVINTEGRAL | D302: SOLICITUD DE APOYO PARA CORTE DE ARBOLES | E302: 301 | F302: 46078 | G302: FALSE | H302: FALSE | I302: RESIDUOS | J302: =IF(A302="INFORMACIÓN O DOCUMENTOS", 10, IF(A302="CONSULTA", 30, IF(A302="FACTURACIÓN Y COBROS", 15, IF(A302="VINCULACIÓN Y DESVINCULACIÓN", 15, IF(A302="NO ES DE NUESTRA COMPETENCIA", 5, IF(A302="OTRO", 15, "")))))) -> 15 | K302: =IF(AND(F302<>"", L302<>""), NETWORKDAYS(TODAY(), L302-1, FESTIVOS!A$1:A$55), "") -> -61 | L302: =IF(AND(F302<>"", J302<>""), WORKDAY(F302, J302, FESTIVOS!A$1:A$55), "") -> 46099 | M302: LAURA GIRALDO | N302: =IF(K302="", "", MAX(0, K302 - (TODAY() - TODAY()))) -> 0 | O302: =IF(OR(K302="", J302=""), "", IF(K302<0, "Vencido", IF(K302>(J302/2), "Supere la mitad", "Bajo la mitad"))) -> Vencido | P302: CE-GR-0302 | Q302: 46084 | R302: =IF(OR(Q302="", L302=""), "", NETWORKDAYS(L302, Q302, FESTIVOS!A301:A355)) -> -12
A303: OTRO | B303: HERMILA CABRERA | C303: USUARIO DE SERVINTEGRAL | D303: SOLICITUD DE CERTIFICADO | E303: 302 | F303: 46079 | G303: FALSE | H303: FALSE | I303: COMERCIAL | J303: =IF(A303="INFORMACIÓN O DOCUMENTOS", 10, IF(A303="CONSULTA", 30, IF(A303="FACTURACIÓN Y COBROS", 15, IF(A303="VINCULACIÓN Y DESVINCULACIÓN", 15, IF(A303="NO ES DE NUESTRA COMPETENCIA", 5, IF(A303="OTRO", 15, "")))))) -> 15 | K303: =IF(AND(F303<>"", L303<>""), NETWORKDAYS(TODAY(), L303-1, FESTIVOS!A$1:A$55), "") -> -60 | L303: =IF(AND(F303<>"", J303<>""), WORKDAY(F303, J303, FESTIVOS!A$1:A$55), "") -> 46100 | M303: LAURA GIRALDO | N303: =IF(K303="", "", MAX(0, K303 - (TODAY() - TODAY()))) -> 0 | O303: =IF(OR(K303="", J303=""), "", IF(K303<0, "Vencido", IF(K303>(J303/2), "Supere la mitad", "Bajo la mitad"))) -> Vencido | P303: CE-GC-0371 | Q303: 46097 | R303: =IF(OR(Q303="", L303=""), "", NETWORKDAYS(L303, Q303, FESTIVOS!A302:A356)) -> -4
A304: OTRO | B304: JORGE CABRERA | C304: USUARIO DE SERVINTEGRAL | D304: DESCUENTO EN LA DEUDA DE ASEO | E304: 303 | F304: 46079 | G304: FALSE | H304: FALSE | I304: COMERCIAL | J304: =IF(A304="INFORMACIÓN O DOCUMENTOS", 10, IF(A304="CONSULTA", 30, IF(A304="FACTURACIÓN Y COBROS", 15, IF(A304="VINCULACIÓN Y DESVINCULACIÓN", 15, IF(A304="NO ES DE NUESTRA COMPETENCIA", 5, IF(A304="OTRO", 15, "")))))) -> 15 | K304: =IF(AND(F304<>"", L304<>""), NETWORKDAYS(TODAY(), L304-1, FESTIVOS!A$1:A$55), "") -> -60 | L304: =IF(AND(F304<>"", J304<>""), WORKDAY(F304, J304, FESTIVOS!A$1:A$55), "") -> 46100 | M304: LAURA GIRALDO | N304: =IF(K304="", "", MAX(0, K304 - (TODAY() - TODAY()))) -> 0 | O304: =IF(OR(K304="", J304=""), "", IF(K304<0, "Vencido", IF(K304>(J304/2), "Supere la mitad", "Bajo la mitad"))) -> Vencido | P304: CE-GC-0317 | Q304: 46094 | R304: =IF(OR(Q304="", L304=""), "", NETWORKDAYS(L304, Q304, FESTIVOS!A303:A357)) -> -5
A305: OTRO | B305: STELLA SANCHEZ GOMEZ | C305: USUARIO DE SERVINTEGRAL | D305: SOLICITUD DE COBRO DE 2 CONTADORES QUE NO SE ESTAN UTILIZANDO DE ENERGIA | E305: 304 | F305: 46079 | G305: FALSE | H305: FALSE | I305: COMERCIAL | J305: =IF(A305="INFORMACIÓN O DOCUMENTOS", 10, IF(A305="CONSULTA", 30, IF(A305="FACTURACIÓN Y COBROS", 15, IF(A305="VINCULACIÓN Y DESVINCULACIÓN", 15, IF(A305="NO ES DE NUESTRA COMPETENCIA", 5, IF(A305="OTRO", 15, "")))))) -> 15 | K305: =IF(AND(F305<>"", L305<>""), NETWORKDAYS(TODAY(), L305-1, FESTIVOS!A$1:A$55), "") -> -60 | L305: =IF(AND(F305<>"", J305<>""), WORKDAY(F305, J305, FESTIVOS!A$1:A$55), "") -> 46100 | M305: LAURA GIRALDO | N305: =IF(K305="", "", MAX(0, K305 - (TODAY() - TODAY()))) -> 0 | O305: =IF(OR(K305="", J305=""), "", IF(K305<0, "Vencido", IF(K305>(J305/2), "Supere la mitad", "Bajo la mitad"))) -> Vencido | P305: CE-GC-0464 | Q305: 46100 | R305: =IF(OR(Q305="", L305=""), "", NETWORKDAYS(L305, Q305, FESTIVOS!A304:A358)) -> 1
A306: OTRO | B306: JUAN CICERY | C306: USUARIO DE SERVINTEGRAL | D306: SOLICITUD DE ENTREGA DE DOCUMENTOS | E306: 305 | F306: 46079 | G306: FALSE | H306: FALSE | I306: TALENTO HUMANO | J306: 10 | K306: =IF(AND(F306<>"", L306<>""), NETWORKDAYS(TODAY(), L306-1, FESTIVOS!A$1:A$55), "") -> -65 | L306: =IF(AND(F306<>"", J306<>""), WORKDAY(F306, J306, FESTIVOS!A$1:A$55), "") -> 46093 | M306: LAURA GIRALDO | N306: =IF(K306="", "", MAX(0, K306 - (TODAY() - TODAY()))) -> 0 | O306: =IF(OR(K306="", J306=""), "", IF(K306<0, "Vencido", IF(K306>(J306/2), "Supere la mitad", "Bajo la mitad"))) -> Vencido | P306: CE-GT-0382 | Q306: 46093 | R306: =IF(OR(Q306="", L306=""), "", NETWORKDAYS(L306, Q306, FESTIVOS!A305:A359)) -> 1
A307: OTRO | B307: BELISARIO MONTOYA | C307: USUARIO DE SERVINTEGRAL | D307: SOLICITUD DE CONTENEDORES | E307: 306 | F307: 46079 | G307: FALSE | H307: FALSE | I307: COMERCIAL | J307: =IF(A307="INFORMACIÓN O DOCUMENTOS", 10, IF(A307="CONSULTA", 30, IF(A307="FACTURACIÓN Y COBROS", 15, IF(A307="VINCULACIÓN Y DESVINCULACIÓN", 15, IF(A307="NO ES DE NUESTRA COMPETENCIA", 5, IF(A307="OTRO", 15, "")))))) -> 15 | K307: =IF(AND(F307<>"", L307<>""), NETWORKDAYS(TODAY(), L307-1, FESTIVOS!A$1:A$55), "") -> -60 | L307: =IF(AND(F307<>"", J307<>""), WORKDAY(F307, J307, FESTIVOS!A$1:A$55), "") -> 46100 | M307: LAURA GIRALDO | N307: =IF(K307="", "", MAX(0, K307 - (TODAY() - TODAY()))) -> 0 | O307: =IF(OR(K307="", J307=""), "", IF(K307<0, "Vencido", IF(K307>(J307/2), "Supere la mitad", "Bajo la mitad"))) -> Vencido | P307: CE-GC-0355 | Q307: 46099 | R307: =IF(OR(Q307="", L307=""), "", NETWORKDAYS(L307, Q307, FESTIVOS!A306:A360)) -> -2
A308: OTRO | B308: ALEXANDER FIERRO | C308: USUARIO DE SERVINTEGRAL | D308: PODA | E308: 307 | F308: 46079 | G308: FALSE | H308: FALSE | I308: RESIDUOS | J308: =IF(A308="INFORMACIÓN O DOCUMENTOS", 10, IF(A308="CONSULTA", 30, IF(A308="FACTURACIÓN Y COBROS", 15, IF(A308="VINCULACIÓN Y DESVINCULACIÓN", 15, IF(A308="NO ES DE NUESTRA COMPETENCIA", 5, IF(A308="OTRO", 15, "")))))) -> 15 | K308: =IF(AND(F308<>"", L308<>""), NETWORKDAYS(TODAY(), L308-1, FESTIVOS!A$1:A$55), "") -> -60 | L308: =IF(AND(F308<>"", J308<>""), WORKDAY(F308, J308, FESTIVOS!A$1:A$55), "") -> 46100 | M308: LAURA GIRALDO | N308: =IF(K308="", "", MAX(0, K308 - (TODAY() - TODAY()))) -> 0 | O308: =IF(OR(K308="", J308=""), "", IF(K308<0, "Vencido", IF(K308>(J308/2), "Supere la mitad", "Bajo la mitad"))) -> Vencido | P308: CE-GR-0310 | Q308: 46084 | R308: =IF(OR(Q308="", L308=""), "", NETWORKDAYS(L308, Q308, FESTIVOS!A307:A361)) -> -13
A309: OTRO | B309: MAYRA ARTUNDUAGA | C309: ESAC | D309: Desafiliación | E309: 308 | F309: 46079 | G309: FALSE | H309: FALSE | I309: COMERCIAL | J309: =IF(A309="INFORMACIÓN O DOCUMENTOS", 10, IF(A309="CONSULTA", 30, IF(A309="FACTURACIÓN Y COBROS", 15, IF(A309="VINCULACIÓN Y DESVINCULACIÓN", 15, IF(A309="NO ES DE NUESTRA COMPETENCIA", 5, IF(A309="OTRO", 15, "")))))) -> 15 | K309: =IF(AND(F309<>"", L309<>""), NETWORKDAYS(TODAY(), L309-1, FESTIVOS!A$1:A$55), "") -> -60 | L309: =IF(AND(F309<>"", J309<>""), WORKDAY(F309, J309, FESTIVOS!A$1:A$55), "") -> 46100 | M309: LAURA GIRALDO | N309: =IF(K309="", "", MAX(0, K309 - (TODAY() - TODAY()))) -> 0 | O309: =IF(OR(K309="", J309=""), "", IF(K309<0, "Vencido", IF(K309>(J309/2), "Supere la mitad", "Bajo la mitad"))) -> Vencido | P309: CE-GC-0373 | Q309: 46094 | R309: =IF(OR(Q309="", L309=""), "", NETWORKDAYS(L309, Q309, FESTIVOS!A308:A362)) -> -5
A310: OTRO | B310: ANDRES FELIPE CABRERA | C310: USUARIO DE SERVINTEGRAL | D310: COMPROBANTE DE PAGO Y SOLICITUD DE CERTIFICADO | E310: 309 | F310: 46079 | G310: FALSE | H310: FALSE | I310: COMERCIAL | J310: =IF(A310="INFORMACIÓN O DOCUMENTOS", 10, IF(A310="CONSULTA", 30, IF(A310="FACTURACIÓN Y COBROS", 15, IF(A310="VINCULACIÓN Y DESVINCULACIÓN", 15, IF(A310="NO ES DE NUESTRA COMPETENCIA", 5, IF(A310="OTRO", 15, "")))))) -> 15 | K310: =IF(AND(F310<>"", L310<>""), NETWORKDAYS(TODAY(), L310-1, FESTIVOS!A$1:A$55), "") -> -60 | L310: =IF(AND(F310<>"", J310<>""), WORKDAY(F310, J310, FESTIVOS!A$1:A$55), "") -> 46100 | M310: LAURA GIRALDO | N310: =IF(K310="", "", MAX(0, K310 - (TODAY() - TODAY()))) -> 0 | O310: =IF(OR(K310="", J310=""), "", IF(K310<0, "Vencido", IF(K310>(J310/2), "Supere la mitad", "Bajo la mitad"))) -> Vencido | P310: CE-GC0368 | Q310: 46097 | R310: =IF(OR(Q310="", L310=""), "", NETWORKDAYS(L310, Q310, FESTIVOS!A309:A363)) -> -4
A311: OTRO | B311: DAGOBERTO POLANIA | C311: USUARIO DE SERVINTEGRAL | D311: SOLICITUD DE PODA | E311: 310 | F311: 46079 | G311: FALSE | H311: FALSE | I311: RESIDUOS | J311: =IF(A311="INFORMACIÓN O DOCUMENTOS", 10, IF(A311="CONSULTA", 30, IF(A311="FACTURACIÓN Y COBROS", 15, IF(A311="VINCULACIÓN Y DESVINCULACIÓN", 15, IF(A311="NO ES DE NUESTRA COMPETENCIA", 5, IF(A311="OTRO", 15, "")))))) -> 15 | K311: =IF(AND(F311<>"", L311<>""), NETWORKDAYS(TODAY(), L311-1, FESTIVOS!A$1:A$55), "") -> -60 | L311: =IF(AND(F311<>"", J311<>""), WORKDAY(F311, J311, FESTIVOS!A$1:A$55), "") -> 46100 | M311: LAURA GIRALDO | N311: =IF(K311="", "", MAX(0, K311 - (TODAY() - TODAY()))) -> 0 | O311: =IF(OR(K311="", J311=""), "", IF(K311<0, "Vencido", IF(K311>(J311/2), "Supere la mitad", "Bajo la mitad"))) -> Vencido | P311: CE-GR-0349 | Q311: 46093 | R311: ENTREGADO FISICO
A312: OTRO | B312: FREDY HERNAN TEJADA | C312: ELECTROCAQUETA | D312: Respuesta a oficio CE-GC-0225 del 13-02-2026 con Rad interno No 2026-1-1-1160 del 16-02-2026 | E312: 311 | F312: 46079 | G312: FALSE | H312: FALSE | I312: COMERCIAL | J312: =IF(A312="INFORMACIÓN O DOCUMENTOS", 10, IF(A312="CONSULTA", 30, IF(A312="FACTURACIÓN Y COBROS", 15, IF(A312="VINCULACIÓN Y DESVINCULACIÓN", 15, IF(A312="NO ES DE NUESTRA COMPETENCIA", 5, IF(A312="OTRO", 15, "")))))) -> 15 | K312: =IF(AND(F312<>"", L312<>""), NETWORKDAYS(TODAY(), L312-1, FESTIVOS!A$1:A$55), "") -> -60 | L312: =IF(AND(F312<>"", J312<>""), WORKDAY(F312, J312, FESTIVOS!A$1:A$55), "") -> 46100 | M312: LAURA GIRALDO | N312: =IF(K312="", "", MAX(0, K312 - (TODAY() - TODAY()))) -> 0 | O312: =IF(OR(K312="", J312=""), "", IF(K312<0, "Vencido", IF(K312>(J312/2), "Supere la mitad", "Bajo la mitad"))) -> Vencido | P312: NO REQUIERE RESPUESTA | Q312: FALSE | R312: =IF(OR(Q312="", L312=""), "", NETWORKDAYS(L312, Q312, FESTIVOS!A311:A365)) -> #VALUE!
A313: OTRO | B313: YESENNIA MONSALVE | C313: SERVAF | D313: Traslado por competencias Radicado E-2026010000382 del 11/02/2026 | E313: 312 | F313: 46079 | G313: FALSE | H313: FALSE | I313: COMERCIAL | J313: =IF(A313="INFORMACIÓN O DOCUMENTOS", 10, IF(A313="CONSULTA", 30, IF(A313="FACTURACIÓN Y COBROS", 15, IF(A313="VINCULACIÓN Y DESVINCULACIÓN", 15, IF(A313="NO ES DE NUESTRA COMPETENCIA", 5, IF(A313="OTRO", 15, "")))))) -> 15 | K313: =IF(AND(F313<>"", L313<>""), NETWORKDAYS(TODAY(), L313-1, FESTIVOS!A$1:A$55), "") -> -60 | L313: =IF(AND(F313<>"", J313<>""), WORKDAY(F313, J313, FESTIVOS!A$1:A$55), "") -> 46100 | M313: LAURA GIRALDO | N313: =IF(K313="", "", MAX(0, K313 - (TODAY() - TODAY()))) -> 0 | O313: =IF(OR(K313="", J313=""), "", IF(K313<0, "Vencido", IF(K313>(J313/2), "Supere la mitad", "Bajo la mitad"))) -> Vencido | P313: CE-GC-0467 | Q313: 46099 | R313: =IF(OR(Q313="", L313=""), "", NETWORKDAYS(L313, Q313, FESTIVOS!A312:A366)) -> -2
A314: OTRO | B314: Norma Suleiza Mavesoy polanco | C314: USUARIO DE SERVINTEGRAL | D314: SOLICITUD DE PODA | E314: 313 | F314: 46080 | G314: FALSE | H314: FALSE | I314: RESIDUOS | J314: =IF(A314="INFORMACIÓN O DOCUMENTOS", 10, IF(A314="CONSULTA", 30, IF(A314="FACTURACIÓN Y COBROS", 15, IF(A314="VINCULACIÓN Y DESVINCULACIÓN", 15, IF(A314="NO ES DE NUESTRA COMPETENCIA", 5, IF(A314="OTRO", 15, "")))))) -> 15 | K314: =IF(AND(F314<>"", L314<>""), NETWORKDAYS(TODAY(), L314-1, FESTIVOS!A$1:A$55), "") -> -59 | L314: =IF(AND(F314<>"", J314<>""), WORKDAY(F314, J314, FESTIVOS!A$1:A$55), "") -> 46101 | M314: LAURA GIRALDO | N314: =IF(K314="", "", MAX(0, K314 - (TODAY() - TODAY()))) -> 0 | O314: =IF(OR(K314="", J314=""), "", IF(K314<0, "Vencido", IF(K314>(J314/2), "Supere la mitad", "Bajo la mitad"))) -> Vencido | P314: CE-GR-0305 | Q314: 46084 | R314: =IF(OR(Q314="", L314=""), "", NETWORKDAYS(L314, Q314, FESTIVOS!A313:A367)) -> -14
A315: OTRO | B315: BELISARIO MONTOYA | C315: USUARIO DE SERVINTEGRAL | D315: Solicitud jornada de trabajo | E315: 314 | F315: 46080 | G315: FALSE | H315: FALSE | I315: RESIDUOS | J315: =IF(A315="INFORMACIÓN O DOCUMENTOS", 10, IF(A315="CONSULTA", 30, IF(A315="FACTURACIÓN Y COBROS", 15, IF(A315="VINCULACIÓN Y DESVINCULACIÓN", 15, IF(A315="NO ES DE NUESTRA COMPETENCIA", 5, IF(A315="OTRO", 15, "")))))) -> 15 | K315: =IF(AND(F315<>"", L315<>""), NETWORKDAYS(TODAY(), L315-1, FESTIVOS!A$1:A$55), "") -> -59 | L315: =IF(AND(F315<>"", J315<>""), WORKDAY(F315, J315, FESTIVOS!A$1:A$55), "") -> 46101 | M315: LAURA GIRALDO | N315: =IF(K315="", "", MAX(0, K315 - (TODAY() - TODAY()))) -> 0 | O315: =IF(OR(K315="", J315=""), "", IF(K315<0, "Vencido", IF(K315>(J315/2), "Supere la mitad", "Bajo la mitad"))) -> Vencido | P315: CE-GR-0306 | Q315: 46084 | R315: =IF(OR(Q315="", L315=""), "", NETWORKDAYS(L315, Q315, FESTIVOS!A314:A368)) -> -14
...

Sheet FESTIVOS
A1: 45658
A2: 45663
A3: 45740
A4: 45764
A5: 45765
A6: 45778
A7: 45810
A8: 45831
A9: 45838
A10: 45858
A11: 45876
A12: 45887
... A55: 46746
