Workbook

Sheet 2026
A1: TIPO DE SOLICITUD | B1: NOMBRE | C1: ENTIDAD | D1: ASUNTO | E1: RADICADO | F1: FECHA DE INGRESO DE LA SOLICITUD | G1: AREA RESPONSABLE | H1: TERMINO | I1: POSIBLES DIAS RESTANTES | J1: FECHA DE VENCIMIENTO | K1: QUEN RECIBIO | L1: ALERTA | M1: ALERTA 2 | N1: CONSECUTIVO | O1: FECHA DE SALIDA | P1: DIAS QUE LE SOBRARON
A2: OTRO | B2: MAYRA ARTUNDUAGA | C2: ESAC | D2: DESAFILIACIONES | E2: 1 | F2: 46024 | G2: COMERCIAL | H2: =IF(A2="INFORMACIÓN O DOCUMENTOS", 10, IF(A2="CONSULTA", 30, IF(A2="FACTURACIÓN Y COBROS", 15, IF(A2="VINCULACIÓN Y DESVINCULACIÓN", 15, IF(A2="NO ES DE NUESTRA COMPETENCIA", 5, IF(A2="OTRO", 15, "")))))) -> 15 | I2: =IF(AND(F2<>"", J2<>""), NETWORKDAYS(TODAY(), J2-1, FESTIVOS!A$1:A$55), "") -> -93 | J2: =IF(AND(F2<>"", H2<>""), WORKDAY(F2, H2, FESTIVOS!A$1:A$55), "") -> 46048 | K2: LAURA GIRALDO | L2: 0 | M2: =IF(OR(I2="", H2=""), "", IF(I2<0, "Vencido", IF(I2>(H2/2), "Supere la mitad", "Bajo la mitad"))) -> Vencido | N2: CE-GC-007 | O2: 46038 | P2: =IF(OR(O2="", J2=""), "", NETWORKDAYS(J2, O2, FESTIVOS!A1:A55)) -> -7
A3: OTRO | B3: MAYRA ARTUNDUAGA | C3: ESAC | D3: DESAFILIACIONES | E3: 2 | F3: 46024 | G3: COMERCIAL | H3: =IF(A3="INFORMACIÓN O DOCUMENTOS", 10, IF(A3="CONSULTA", 30, IF(A3="FACTURACIÓN Y COBROS", 15, IF(A3="VINCULACIÓN Y DESVINCULACIÓN", 15, IF(A3="NO ES DE NUESTRA COMPETENCIA", 5, IF(A3="OTRO", 15, "")))))) -> 15 | I3: =IF(AND(F3<>"", J3<>""), NETWORKDAYS(TODAY(), J3-1, FESTIVOS!A$1:A$55), "") -> -93 | J3: =IF(AND(F3<>"", H3<>""), WORKDAY(F3, H3, FESTIVOS!A$1:A$55), "") -> 46048 | K3: LAURA GIRALDO | L3: =IF(I3="", "", MAX(0, I3 - (TODAY() - TODAY()))) -> 0 | M3: =IF(OR(I3="", H3=""), "", IF(I3<0, "Vencido", IF(I3>(H3/2), "Supere la mitad", "Bajo la mitad"))) -> Vencido | N3: CE-GC-008 | O3: 46041 | P3: =IF(OR(O3="", J3=""), "", NETWORKDAYS(J3, O3, FESTIVOS!A2:A56)) -> -6
A4: OTRO | B4: CARLOS ALMERO VIDEL | C4: USUARIO | D4: COTIZACIÓN | E4: 3 | F4: 46027 | G4: COMERCIAL | H4: =IF(A4="INFORMACIÓN O DOCUMENTOS", 10, IF(A4="CONSULTA", 30, IF(A4="FACTURACIÓN Y COBROS", 15, IF(A4="VINCULACIÓN Y DESVINCULACIÓN", 15, IF(A4="NO ES DE NUESTRA COMPETENCIA", 5, IF(A4="OTRO", 15, "")))))) -> 15 | I4: =IF(AND(F4<>"", J4<>""), NETWORKDAYS(TODAY(), J4-1, FESTIVOS!A$1:A$55), "") -> -93 | J4: =IF(AND(F4<>"", H4<>""), WORKDAY(F4, H4, FESTIVOS!A$1:A$55), "") -> 46049 | K4: LAURA GIRALDO | L4: =IF(I4="", "", MAX(0, I4 - (TODAY() - TODAY()))) -> 0 | M4: =IF(OR(I4="", H4=""), "", IF(I4<0, "Vencido", IF(I4>(H4/2), "Supere la mitad", "Bajo la mitad"))) -> Vencido | N4: CE-GC-0011 | O4: 46029 | P4: =IF(OR(O4="", J4=""), "", NETWORKDAYS(J4, O4, FESTIVOS!A3:A57)) -> -14 | Q4: si salen en engativo sobraron
A5: OTRO | B5: MAYRA ARTUNDUAGA | C5: ESAC | D5: DESAFILIACIONES | E5: 4 | F5: 46027 | G5: COMERCIAL | H5: =IF(A5="INFORMACIÓN O DOCUMENTOS", 10, IF(A5="CONSULTA", 30, IF(A5="FACTURACIÓN Y COBROS", 15, IF(A5="VINCULACIÓN Y DESVINCULACIÓN", 15, IF(A5="NO ES DE NUESTRA COMPETENCIA", 5, IF(A5="OTRO", 15, "")))))) -> 15 | I5: =IF(AND(F5<>"", J5<>""), NETWORKDAYS(TODAY(), J5-1, FESTIVOS!A$1:A$55), "") -> -93 | J5: =IF(AND(F5<>"", H5<>""), WORKDAY(F5, H5, FESTIVOS!A$1:A$55), "") -> 46049 | K5: LAURA GIRALDO | L5: =IF(I5="", "", MAX(0, I5 - (TODAY() - TODAY()))) -> 0 | M5: =IF(OR(I5="", H5=""), "", IF(I5<0, "Vencido", IF(I5>(H5/2), "Supere la mitad", "Bajo la mitad"))) -> Vencido | N5: CE-GC-0010 | O5: 46038 | P5: =IF(OR(O5="", J5=""), "", NETWORKDAYS(J5, O5, FESTIVOS!A4:A58)) -> -8 | Q5: si salen positivos nos pasamos
A6: OTRO | B6: EMITIDO POR LA ALCALDIA | C6: ALCALDIA | D6: TRASLADO POR COMPETENCIA -MARIA MARGARITALOPEZ GOMEZ | E6: 5 | F6: 46028 | G6: COMERCIAL | H6: =IF(A6="INFORMACIÓN O DOCUMENTOS", 10, IF(A6="CONSULTA", 30, IF(A6="FACTURACIÓN Y COBROS", 15, IF(A6="VINCULACIÓN Y DESVINCULACIÓN", 15, IF(A6="NO ES DE NUESTRA COMPETENCIA", 5, IF(A6="OTRO", 15, "")))))) -> 15 | I6: =IF(AND(F6<>"", J6<>""), NETWORKDAYS(TODAY(), J6-1, FESTIVOS!A$1:A$55), "") -> -92 | J6: =IF(AND(F6<>"", H6<>""), WORKDAY(F6, H6, FESTIVOS!A$1:A$55), "") -> 46050 | K6: LAURA GIRALDO | L6: =IF(I6="", "", MAX(0, I6 - (TODAY() - TODAY()))) -> 0 | M6: =IF(OR(I6="", H6=""), "", IF(I6<0, "Vencido", IF(I6>(H6/2), "Supere la mitad", "Bajo la mitad"))) -> Vencido | N6: CE-GC-0055 | O6: 46038 | P6: =IF(OR(O6="", J6=""), "", NETWORKDAYS(J6, O6, FESTIVOS!A5:A59)) -> -9
A7: OTRO | B7: KARLA JOHANA LISCANO CORREA | C7: ALCALDIA | D7: ACTA DEL COMITÉ DE CONOCIMIENTO DE RIESGO | E7: 6 | F7: 46028 | G7: COMERCIAL | H7: =IF(A7="INFORMACIÓN O DOCUMENTOS", 10, IF(A7="CONSULTA", 30, IF(A7="FACTURACIÓN Y COBROS", 15, IF(A7="VINCULACIÓN Y DESVINCULACIÓN", 15, IF(A7="NO ES DE NUESTRA COMPETENCIA", 5, IF(A7="OTRO", 15, "")))))) -> 15 | I7: =IF(AND(F7<>"", J7<>""), NETWORKDAYS(TODAY(), J7-1, FESTIVOS!A$1:A$55), "") -> -92 | J7: =IF(AND(F7<>"", H7<>""), WORKDAY(F7, H7, FESTIVOS!A$1:A$55), "") -> 46050 | K7: LAURA GIRALDO | L7: =IF(I7="", "", MAX(0, I7 - (TODAY() - TODAY()))) -> 0 | M7: =IF(OR(I7="", H7=""), "", IF(I7<0, "Vencido", IF(I7>(H7/2), "Supere la mitad", "Bajo la mitad"))) -> Vencido | N7: NO REQUIERE RESPUESTA | P7: =IF(OR(O7="", J7=""), "", NETWORKDAYS(J7, O7, FESTIVOS!A6:A60))
A8: OTRO | B8: ESTHER JULIA GOMEZ | C8: USUARIO | D8: DERECHO DE PETICIÓN | E8: 7 | F8: 46028 | G8: COMERCIAL | H8: =IF(A8="INFORMACIÓN O DOCUMENTOS", 10, IF(A8="CONSULTA", 30, IF(A8="FACTURACIÓN Y COBROS", 15, IF(A8="VINCULACIÓN Y DESVINCULACIÓN", 15, IF(A8="NO ES DE NUESTRA COMPETENCIA", 5, IF(A8="OTRO", 15, "")))))) -> 15 | I8: =IF(AND(F8<>"", J8<>""), NETWORKDAYS(TODAY(), J8-1, FESTIVOS!A$1:A$55), "") -> -92 | J8: =IF(AND(F8<>"", H8<>""), WORKDAY(F8, H8, FESTIVOS!A$1:A$55), "") -> 46050 | K8: LAURA GIRALDO | L8: =IF(I8="", "", MAX(0, I8 - (TODAY() - TODAY()))) -> 0 | M8: =IF(OR(I8="", H8=""), "", IF(I8<0, "Vencido", IF(I8>(H8/2), "Supere la mitad", "Bajo la mitad"))) -> Vencido | N8: CE-GC-0113 | O8: 46050 | P8: =IF(OR(O8="", J8=""), "", NETWORKDAYS(J8, O8, FESTIVOS!A7:A61)) -> 1
A9: OTRO | B9: OMAR JOSE MAESTRE FELIZZOLA | C9: SUPER | D9: REMISIÓN MESA DE TRABAJO | E9: 8 | F9: 46028 | G9: JURÍDICA | H9: =IF(A9="INFORMACIÓN O DOCUMENTOS", 10, IF(A9="CONSULTA", 30, IF(A9="FACTURACIÓN Y COBROS", 15, IF(A9="VINCULACIÓN Y DESVINCULACIÓN", 15, IF(A9="NO ES DE NUESTRA COMPETENCIA", 5, IF(A9="OTRO", 15, "")))))) -> 15 | I9: =IF(AND(F9<>"", J9<>""), NETWORKDAYS(TODAY(), J9-1, FESTIVOS!A$1:A$55), "") -> -92 | J9: =IF(AND(F9<>"", H9<>""), WORKDAY(F9, H9, FESTIVOS!A$1:A$55), "") -> 46050 | K9: LAURA GIRALDO | L9: =IF(I9="", "", MAX(0, I9 - (TODAY() - TODAY()))) -> 0 | M9: =IF(OR(I9="", H9=""), "", IF(I9<0, "Vencido", IF(I9>(H9/2), "Supere la mitad", "Bajo la mitad"))) -> Vencido | P9: =IF(OR(O9="", J9=""), "", NETWORKDAYS(J9, O9, FESTIVOS!A8:A62))
A10: OTRO | B10: ADRIANA GUZMÁN BUITRAGO | C10: USUARIO DE SERVINTEGRAL | D10: DERECHO DE PETICIÓN | E10: 9 | F10: 46028 | G10: COMERCIAL | H10: =IF(A10="INFORMACIÓN O DOCUMENTOS", 10, IF(A10="CONSULTA", 30, IF(A10="FACTURACIÓN Y COBROS", 15, IF(A10="VINCULACIÓN Y DESVINCULACIÓN", 15, IF(A10="NO ES DE NUESTRA COMPETENCIA", 5, IF(A10="OTRO", 15, "")))))) -> 15 | I10: =IF(AND(F10<>"", J10<>""), NETWORKDAYS(TODAY(), J10-1, FESTIVOS!A$1:A$55), "") -> -92 | J10: =IF(AND(F10<>"", H10<>""), WORKDAY(F10, H10, FESTIVOS!A$1:A$55), "") -> 46050 | K10: LAURA GIRALDO | L10: =IF(I10="", "", MAX(0, I10 - (TODAY() - TODAY()))) -> 0 | M10: =IF(OR(I10="", H10=""), "", IF(I10<0, "Vencido", IF(I10>(H10/2), "Supere la mitad", "Bajo la mitad"))) -> Vencido | N10: CE-GC-0065 | O10: 46041 | P10: =IF(OR(O10="", J10=""), "", NETWORKDAYS(J10, O10, FESTIVOS!A9:A63)) -> -8
A11: OTRO | B11: GINA PAOLA RIVERA CHACON | C11: USUARIO DE SERVINTEGRAL | D11: RESPUESTA DE VINCULACIÓN | E11: 10 | F11: 46029 | G11: COMERCIAL | H11: =IF(A11="INFORMACIÓN O DOCUMENTOS", 10, IF(A11="CONSULTA", 30, IF(A11="FACTURACIÓN Y COBROS", 15, IF(A11="VINCULACIÓN Y DESVINCULACIÓN", 15, IF(A11="NO ES DE NUESTRA COMPETENCIA", 5, IF(A11="OTRO", 15, "")))))) -> 15 | I11: =IF(AND(F11<>"", J11<>""), NETWORKDAYS(TODAY(), J11-1, FESTIVOS!A$1:A$55), "") -> -91 | J11: =IF(AND(F11<>"", H11<>""), WORKDAY(F11, H11, FESTIVOS!A$1:A$55), "") -> 46051 | K11: LAURA GIRALDO | L11: =IF(I11="", "", MAX(0, I11 - (TODAY() - TODAY()))) -> 0 | M11: =IF(OR(I11="", H11=""), "", IF(I11<0, "Vencido", IF(I11>(H11/2), "Supere la mitad", "Bajo la mitad"))) -> Vencido | N11: CE-GC-0012 | O11: 46037 | P11: =IF(OR(O11="", J11=""), "", NETWORKDAYS(J11, O11, FESTIVOS!A10:A64)) -> -11
A12: OTRO | B12: EQUIPO DE VERIFICACIÓN | C12: USUARIO DE SERVINTEGRAL | D12: ACTUALIZACIÓN DE INFORMACIÓN | E12: 11 | F12: 46029 | G12: JURÍDICA | H12: =IF(A12="INFORMACIÓN O DOCUMENTOS", 10, IF(A12="CONSULTA", 30, IF(A12="FACTURACIÓN Y COBROS", 15, IF(A12="VINCULACIÓN Y DESVINCULACIÓN", 15, IF(A12="NO ES DE NUESTRA COMPETENCIA", 5, IF(A12="OTRO", 15, "")))))) -> 15 | I12: =IF(AND(F12<>"", J12<>""), NETWORKDAYS(TODAY(), J12-1, FESTIVOS!A$1:A$55), "") -> -91 | J12: =IF(AND(F12<>"", H12<>""), WORKDAY(F12, H12, FESTIVOS!A$1:A$55), "") -> 46051 | K12: LAURA GIRALDO | L12: =IF(I12="", "", MAX(0, I12 - (TODAY() - TODAY()))) -> 0 | M12: =IF(OR(I12="", H12=""), "", IF(I12<0, "Vencido", IF(I12>(H12/2), "Supere la mitad", "Bajo la mitad"))) -> Vencido | P12: =IF(OR(O12="", J12=""), "", NETWORKDAYS(J12, O12, FESTIVOS!A11:A65))
A13: OTRO | B13: MARIA GLORIA CUELLAR LOZANO | C13: USUARIO DE SERVINTEGRAL | D13: INMUEBLE DESOCUPADO | E13: 12 | F13: 46030 | G13: COMERCIAL | H13: =IF(A13="INFORMACIÓN O DOCUMENTOS", 10, IF(A13="CONSULTA", 30, IF(A13="FACTURACIÓN Y COBROS", 15, IF(A13="VINCULACIÓN Y DESVINCULACIÓN", 15, IF(A13="NO ES DE NUESTRA COMPETENCIA", 5, IF(A13="OTRO", 15, "")))))) -> 15 | I13: =IF(AND(F13<>"", J13<>""), NETWORKDAYS(TODAY(), J13-1, FESTIVOS!A$1:A$55), "") -> -90 | J13: =IF(AND(F13<>"", H13<>""), WORKDAY(F13, H13, FESTIVOS!A$1:A$55), "") -> 46052 | K13: LAURA GIRALDO | L13: =IF(I13="", "", MAX(0, I13 - (TODAY() - TODAY()))) -> 0 | M13: =IF(OR(I13="", H13=""), "", IF(I13<0, "Vencido", IF(I13>(H13/2), "Supere la mitad", "Bajo la mitad"))) -> Vencido | N13: CE-GC-0033 | O13: 46036 | P13: =IF(OR(O13="", J13=""), "", NETWORKDAYS(J13, O13, FESTIVOS!A12:A66)) -> -13
A14: OTRO | B14: DIANA MARCELA PERDOMO BELTRÁN | C14: SUPER | D14: Respuesta al radicado de entrada SSPD No. 20255294845332 de fecha 20 de noviembre de 2025 - Respuesta a solicitud con radicado interno 2529 del 4 de noviembre de 2025. “Radicado CE-GT-2420 (Respuesta a Radicado No. 2437 del 20 de octubre de 2025.Requerimiento Ordinario No. 49 - 3458)” | E14: 13 | F14: 46030 | G14: JURÍDICA | H14: =IF(A14="INFORMACIÓN O DOCUMENTOS", 10, IF(A14="CONSULTA", 30, IF(A14="FACTURACIÓN Y COBROS", 15, IF(A14="VINCULACIÓN Y DESVINCULACIÓN", 15, IF(A14="NO ES DE NUESTRA COMPETENCIA", 5, IF(A14="OTRO", 15, "")))))) -> 15 | I14: =IF(AND(F14<>"", J14<>""), NETWORKDAYS(TODAY(), J14-1, FESTIVOS!A$1:A$55), "") -> -90 | J14: =IF(AND(F14<>"", H14<>""), WORKDAY(F14, H14, FESTIVOS!A$1:A$55), "") -> 46052 | K14: LAURA GIRALDO | L14: =IF(I14="", "", MAX(0, I14 - (TODAY() - TODAY()))) -> 0 | M14: =IF(OR(I14="", H14=""), "", IF(I14<0, "Vencido", IF(I14>(H14/2), "Supere la mitad", "Bajo la mitad"))) -> Vencido | N14: CE-GC-0033 | O14: 46036 | P14: =IF(OR(O14="", J14=""), "", NETWORKDAYS(J14, O14, FESTIVOS!A13:A67)) -> -13
A15: OTRO | B15: ISMAEL SILVA ALVAREZ | C15: GAS CAQUETA | D15: SOLICITUD DE CERTIFICADO | E15: 14 | F15: 46030 | G15: COMERCIAL | H15: =IF(A15="INFORMACIÓN O DOCUMENTOS", 10, IF(A15="CONSULTA", 30, IF(A15="FACTURACIÓN Y COBROS", 15, IF(A15="VINCULACIÓN Y DESVINCULACIÓN", 15, IF(A15="NO ES DE NUESTRA COMPETENCIA", 5, IF(A15="OTRO", 15, "")))))) -> 15 | I15: =IF(AND(F15<>"", J15<>""), NETWORKDAYS(TODAY(), J15-1, FESTIVOS!A$1:A$55), "") -> -90 | J15: =IF(AND(F15<>"", H15<>""), WORKDAY(F15, H15, FESTIVOS!A$1:A$55), "") -> 46052 | K15: LAURA GIRALDO | L15: =IF(I15="", "", MAX(0, I15 - (TODAY() - TODAY()))) -> 0 | M15: =IF(OR(I15="", H15=""), "", IF(I15<0, "Vencido", IF(I15>(H15/2), "Supere la mitad", "Bajo la mitad"))) -> Vencido | N15: CE-GC-0014 | O15: 46035 | P15: =IF(OR(O15="", J15=""), "", NETWORKDAYS(J15, O15, FESTIVOS!A14:A68)) -> -14
A16: OTRO | B16: LORENA CASTAÑO | C16: SAMAMB | D16: CARACTERIZACIÓN | E16: 15 | F16: 46030 | G16: RESIDUOS | H16: =IF(A16="INFORMACIÓN O DOCUMENTOS", 10, IF(A16="CONSULTA", 30, IF(A16="FACTURACIÓN Y COBROS", 15, IF(A16="VINCULACIÓN Y DESVINCULACIÓN", 15, IF(A16="NO ES DE NUESTRA COMPETENCIA", 5, IF(A16="OTRO", 15, "")))))) -> 15 | I16: =IF(AND(F16<>"", J16<>""), NETWORKDAYS(TODAY(), J16-1, FESTIVOS!A$1:A$55), "") -> -90 | J16: =IF(AND(F16<>"", H16<>""), WORKDAY(F16, H16, FESTIVOS!A$1:A$55), "") -> 46052 | K16: LAURA GIRALDO | L16: =IF(I16="", "", MAX(0, I16 - (TODAY() - TODAY()))) -> 0 | M16: =IF(OR(I16="", H16=""), "", IF(I16<0, "Vencido", IF(I16>(H16/2), "Supere la mitad", "Bajo la mitad"))) -> Vencido | N16: NO REQUIERE RESPUESTA | P16: =IF(OR(O16="", J16=""), "", NETWORKDAYS(J16, O16, FESTIVOS!A15:A69))
A17: OTRO | B17: LORENA CASTAÑO | C17: SAMAMB | D17: PROPUESTA | E17: 16 | F17: 46030 | G17: COMERCIAL | H17: =IF(A17="INFORMACIÓN O DOCUMENTOS", 10, IF(A17="CONSULTA", 30, IF(A17="FACTURACIÓN Y COBROS", 15, IF(A17="VINCULACIÓN Y DESVINCULACIÓN", 15, IF(A17="NO ES DE NUESTRA COMPETENCIA", 5, IF(A17="OTRO", 15, "")))))) -> 15 | I17: =IF(AND(F17<>"", J17<>""), NETWORKDAYS(TODAY(), J17-1, FESTIVOS!A$1:A$55), "") -> -90 | J17: =IF(AND(F17<>"", H17<>""), WORKDAY(F17, H17, FESTIVOS!A$1:A$55), "") -> 46052 | K17: LAURA GIRALDO | L17: =IF(I17="", "", MAX(0, I17 - (TODAY() - TODAY()))) -> 0 | M17: =IF(OR(I17="", H17=""), "", IF(I17<0, "Vencido", IF(I17>(H17/2), "Supere la mitad", "Bajo la mitad"))) -> Vencido | N17: NO REQUIERE RESPUESTA | P17: =IF(OR(O17="", J17=""), "", NETWORKDAYS(J17, O17, FESTIVOS!A16:A70))
A18: OTRO | B18: FREDY HERNAN TEJADA | C18: ELECTROCAQUETA | D18: Respuesta a oficio CE-GC-0002 del 05-01-2026 con Rad interno No 2026-1-1-75 del 06-01-2026 | E18: 17 | F18: 46030 | G18: COMERCIAL | H18: =IF(A18="INFORMACIÓN O DOCUMENTOS", 10, IF(A18="CONSULTA", 30, IF(A18="FACTURACIÓN Y COBROS", 15, IF(A18="VINCULACIÓN Y DESVINCULACIÓN", 15, IF(A18="NO ES DE NUESTRA COMPETENCIA", 5, IF(A18="OTRO", 15, "")))))) -> 15 | I18: =IF(AND(F18<>"", J18<>""), NETWORKDAYS(TODAY(), J18-1, FESTIVOS!A$1:A$55), "") -> -90 | J18: =IF(AND(F18<>"", H18<>""), WORKDAY(F18, H18, FESTIVOS!A$1:A$55), "") -> 46052 | K18: LAURA GIRALDO | L18: =IF(I18="", "", MAX(0, I18 - (TODAY() - TODAY()))) -> 0 | M18: =IF(OR(I18="", H18=""), "", IF(I18<0, "Vencido", IF(I18>(H18/2), "Supere la mitad", "Bajo la mitad"))) -> Vencido | N18: NO REQUIERE RESPUESTA | P18: =IF(OR(O18="", J18=""), "", NETWORKDAYS(J18, O18, FESTIVOS!A17:A71))
A19: OTRO | B19: FREDY HERNAN TEJADA | C19: ELECTROCAQUETA | D19: Respuesta a oficio CE-GC-0001 del 05-1-2026 con Rad interno No 2026-1-1-74 del 06-01-2026 | E19: 18 | F19: 46031 | G19: COMERCIAL | H19: =IF(A19="INFORMACIÓN O DOCUMENTOS", 10, IF(A19="CONSULTA", 30, IF(A19="FACTURACIÓN Y COBROS", 15, IF(A19="VINCULACIÓN Y DESVINCULACIÓN", 15, IF(A19="NO ES DE NUESTRA COMPETENCIA", 5, IF(A19="OTRO", 15, "")))))) -> 15 | I19: =IF(AND(F19<>"", J19<>""), NETWORKDAYS(TODAY(), J19-1, FESTIVOS!A$1:A$55), "") -> -88 | J19: =IF(AND(F19<>"", H19<>""), WORKDAY(F19, H19, FESTIVOS!A$1:A$55), "") -> 46055 | K19: LAURA GIRALDO | L19: =IF(I19="", "", MAX(0, I19 - (TODAY() - TODAY()))) -> 0 | M19: =IF(OR(I19="", H19=""), "", IF(I19<0, "Vencido", IF(I19>(H19/2), "Supere la mitad", "Bajo la mitad"))) -> Vencido | N19: NO REQUIERE RESPUESTA | P19: =IF(OR(O19="", J19=""), "", NETWORKDAYS(J19, O19, FESTIVOS!A18:A72))
A20: OTRO | B20: LUZ ELIANA TOBON MUÑOZ | C20: USUARIO DE SERVINTEGRAL | D20: SOLICITD DE ESCOMBROS | E20: 19 | F20: 46031 | G20: COMERCIAL | H20: =IF(A20="INFORMACIÓN O DOCUMENTOS", 10, IF(A20="CONSULTA", 30, IF(A20="FACTURACIÓN Y COBROS", 15, IF(A20="VINCULACIÓN Y DESVINCULACIÓN", 15, IF(A20="NO ES DE NUESTRA COMPETENCIA", 5, IF(A20="OTRO", 15, "")))))) -> 15 | I20: =IF(AND(F20<>"", J20<>""), NETWORKDAYS(TODAY(), J20-1, FESTIVOS!A$1:A$55), "") -> -88 | J20: =IF(AND(F20<>"", H20<>""), WORKDAY(F20, H20, FESTIVOS!A$1:A$55), "") -> 46055 | K20: LAURA GIRALDO | L20: =IF(I20="", "", MAX(0, I20 - (TODAY() - TODAY()))) -> 0 | M20: =IF(OR(I20="", H20=""), "", IF(I20<0, "Vencido", IF(I20>(H20/2), "Supere la mitad", "Bajo la mitad"))) -> Vencido | N20: CE-GC-0073 | O20: 46043 | P20: =IF(OR(O20="", J20=""), "", NETWORKDAYS(J20, O20, FESTIVOS!A19:A73)) -> -9
A21: OTRO | B21: NANCY BOHORQUEZ | C21: USUARIO DE SERVINTEGRAL | D21: SOLICITD DE DESCUENTO EN LA DEUDA DE ASEO | E21: 20 | F21: 46035 | G21: COMERCIAL | H21: =IF(A21="INFORMACIÓN O DOCUMENTOS", 10, IF(A21="CONSULTA", 30, IF(A21="FACTURACIÓN Y COBROS", 15, IF(A21="VINCULACIÓN Y DESVINCULACIÓN", 15, IF(A21="NO ES DE NUESTRA COMPETENCIA", 5, IF(A21="OTRO", 15, "")))))) -> 15 | I21: =IF(AND(F21<>"", J21<>""), NETWORKDAYS(TODAY(), J21-1, FESTIVOS!A$1:A$55), "") -> -88 | J21: =IF(AND(F21<>"", H21<>""), WORKDAY(F21, H21, FESTIVOS!A$1:A$55), "") -> 46056 | K21: LAURA GIRALDO | L21: =IF(I21="", "", MAX(0, I21 - (TODAY() - TODAY()))) -> 0 | N21: CE-GC-0050 | O21: 46037 | P21: =IF(OR(O21="", J21=""), "", NETWORKDAYS(J21, O21, FESTIVOS!A20:A74)) -> -14
A22: OTRO | B22: EMA | C22: USUARIO DE SERVINTEGRAL | D22: REFERENCIAS PERSONALES | E22: 21 | F22: 46035 | G22: TALENTO HUMANO | H22: =IF(A22="INFORMACIÓN O DOCUMENTOS", 10, IF(A22="CONSULTA", 30, IF(A22="FACTURACIÓN Y COBROS", 15, IF(A22="VINCULACIÓN Y DESVINCULACIÓN", 15, IF(A22="NO ES DE NUESTRA COMPETENCIA", 5, IF(A22="OTRO", 15, "")))))) -> 15 | I22: =IF(AND(F22<>"", J22<>""), NETWORKDAYS(TODAY(), J22-1, FESTIVOS!A$1:A$55), "") -> -88 | J22: =IF(AND(F22<>"", H22<>""), WORKDAY(F22, H22, FESTIVOS!A$1:A$55), "") -> 46056 | K22: LAURA GIRALDO | L22: =IF(I22="", "", MAX(0, I22 - (TODAY() - TODAY()))) -> 0 | M22: =IF(OR(I22="", H22=""), "", IF(I22<0, "Vencido", IF(I22>(H22/2), "Supere la mitad", "Bajo la mitad"))) -> Vencido | N22: NO REQUIERE RESPUESTA | P22: =IF(OR(O22="", J22=""), "", NETWORKDAYS(J22, O22, FESTIVOS!A21:A75))
A23: OTRO | B23: LEONOR RODRIGUEZ CELIS | C23: USUARIO DE SERVINTEGRAL | D23: AGRADECIMIENTO | E23: 22 | F23: 46035 | G23: RESIDUOS | H23: =IF(A23="INFORMACIÓN O DOCUMENTOS", 10, IF(A23="CONSULTA", 30, IF(A23="FACTURACIÓN Y COBROS", 15, IF(A23="VINCULACIÓN Y DESVINCULACIÓN", 15, IF(A23="NO ES DE NUESTRA COMPETENCIA", 5, IF(A23="OTRO", 15, "")))))) -> 15 | I23: =IF(AND(F23<>"", J23<>""), NETWORKDAYS(TODAY(), J23-1, FESTIVOS!A$1:A$55), "") -> -88 | J23: =IF(AND(F23<>"", H23<>""), WORKDAY(F23, H23, FESTIVOS!A$1:A$55), "") -> 46056 | K23: LAURA GIRALDO | L23: =IF(I23="", "", MAX(0, I23 - (TODAY() - TODAY()))) -> 0 | M23: =IF(OR(I23="", H23=""), "", IF(I23<0, "Vencido", IF(I23>(H23/2), "Supere la mitad", "Bajo la mitad"))) -> Vencido | N23: CE-GC-0033 | O23: 46036 | P23: =IF(OR(O23="", J23=""), "", NETWORKDAYS(J23, O23, FESTIVOS!A22:A76)) -> -15
A24: OTRO | B24: YULIANA ESCOBAR | C24: ESAC | D24: NOTIFICACIÓN PERSONAL | E24: 23 | F24: 46035 | G24: COMERCIAL | H24: =IF(A24="INFORMACIÓN O DOCUMENTOS", 10, IF(A24="CONSULTA", 30, IF(A24="FACTURACIÓN Y COBROS", 15, IF(A24="VINCULACIÓN Y DESVINCULACIÓN", 15, IF(A24="NO ES DE NUESTRA COMPETENCIA", 5, IF(A24="OTRO", 15, "")))))) -> 15 | I24: =IF(AND(F24<>"", J24<>""), NETWORKDAYS(TODAY(), J24-1, FESTIVOS!A$1:A$55), "") -> -88 | J24: =IF(AND(F24<>"", H24<>""), WORKDAY(F24, H24, FESTIVOS!A$1:A$55), "") -> 46056 | K24: LAURA GIRALDO | L24: =IF(I24="", "", MAX(0, I24 - (TODAY() - TODAY()))) -> 0 | M24: =IF(OR(I24="", H24=""), "", IF(I24<0, "Vencido", IF(I24>(H24/2), "Supere la mitad", "Bajo la mitad"))) -> Vencido | N24: CE-GC-0033 | O24: 46036 | P24: =IF(OR(O24="", J24=""), "", NETWORKDAYS(J24, O24, FESTIVOS!A23:A77)) -> -15
A25: OTRO | B25: YULIANA ESCOBAR | C25: ESAC | D25: NOTIFICACIÓN PERSONAL | E25: 24 | F25: 46035 | G25: COMERCIAL | H25: =IF(A25="INFORMACIÓN O DOCUMENTOS", 10, IF(A25="CONSULTA", 30, IF(A25="FACTURACIÓN Y COBROS", 15, IF(A25="VINCULACIÓN Y DESVINCULACIÓN", 15, IF(A25="NO ES DE NUESTRA COMPETENCIA", 5, IF(A25="OTRO", 15, "")))))) -> 15 | I25: =IF(AND(F25<>"", J25<>""), NETWORKDAYS(TODAY(), J25-1, FESTIVOS!A$1:A$55), "") -> -88 | J25: =IF(AND(F25<>"", H25<>""), WORKDAY(F25, H25, FESTIVOS!A$1:A$55), "") -> 46056 | K25: LAURA GIRALDO | L25: =IF(I25="", "", MAX(0, I25 - (TODAY() - TODAY()))) -> 0 | M25: =IF(OR(I25="", H25=""), "", IF(I25<0, "Vencido", IF(I25>(H25/2), "Supere la mitad", "Bajo la mitad"))) -> Vencido | N25: CE-GC-0033 | O25: 46036 | P25: =IF(OR(O25="", J25=""), "", NETWORKDAYS(J25, O25, FESTIVOS!A24:A78)) -> -15
A26: OTRO | B26: YULIANA ESCOBAR | C26: ESAC | D26: NOTIFICACIÓN PERSONAL | E26: 25 | F26: 46035 | G26: COMERCIAL | H26: =IF(A26="INFORMACIÓN O DOCUMENTOS", 10, IF(A26="CONSULTA", 30, IF(A26="FACTURACIÓN Y COBROS", 15, IF(A26="VINCULACIÓN Y DESVINCULACIÓN", 15, IF(A26="NO ES DE NUESTRA COMPETENCIA", 5, IF(A26="OTRO", 15, "")))))) -> 15 | I26: =IF(AND(F26<>"", J26<>""), NETWORKDAYS(TODAY(), J26-1, FESTIVOS!A$1:A$55), "") -> -88 | J26: =IF(AND(F26<>"", H26<>""), WORKDAY(F26, H26, FESTIVOS!A$1:A$55), "") -> 46056 | K26: LAURA GIRALDO | L26: =IF(I26="", "", MAX(0, I26 - (TODAY() - TODAY()))) -> 0 | M26: =IF(OR(I26="", H26=""), "", IF(I26<0, "Vencido", IF(I26>(H26/2), "Supere la mitad", "Bajo la mitad"))) -> Vencido | N26: CE-GC-0033 | O26: 46036 | P26: =IF(OR(O26="", J26=""), "", NETWORKDAYS(J26, O26, FESTIVOS!A25:A79)) -> -15
A27: OTRO | B27: YULIANA ESCOBAR | C27: ESAC | D27: NOTIFICACIÓN PERSONAL | E27: 26 | F27: 46035 | G27: COMERCIAL | H27: =IF(A27="INFORMACIÓN O DOCUMENTOS", 10, IF(A27="CONSULTA", 30, IF(A27="FACTURACIÓN Y COBROS", 15, IF(A27="VINCULACIÓN Y DESVINCULACIÓN", 15, IF(A27="NO ES DE NUESTRA COMPETENCIA", 5, IF(A27="OTRO", 15, "")))))) -> 15 | I27: =IF(AND(F27<>"", J27<>""), NETWORKDAYS(TODAY(), J27-1, FESTIVOS!A$1:A$55), "") -> -88 | J27: =IF(AND(F27<>"", H27<>""), WORKDAY(F27, H27, FESTIVOS!A$1:A$55), "") -> 46056 | K27: LAURA GIRALDO | L27: =IF(I27="", "", MAX(0, I27 - (TODAY() - TODAY()))) -> 0 | M27: =IF(OR(I27="", H27=""), "", IF(I27<0, "Vencido", IF(I27>(H27/2), "Supere la mitad", "Bajo la mitad"))) -> Vencido | N27: CE-GC-0033 | O27: 46036 | P27: =IF(OR(O27="", J27=""), "", NETWORKDAYS(J27, O27, FESTIVOS!A26:A80)) -> -15
A28: OTRO | B28: YULIANA ESCOBAR | C28: ESAC | D28: NOTIFICACIÓN PERSONAL | E28: 27 | F28: 46035 | G28: COMERCIAL | H28: =IF(A28="INFORMACIÓN O DOCUMENTOS", 10, IF(A28="CONSULTA", 30, IF(A28="FACTURACIÓN Y COBROS", 15, IF(A28="VINCULACIÓN Y DESVINCULACIÓN", 15, IF(A28="NO ES DE NUESTRA COMPETENCIA", 5, IF(A28="OTRO", 15, "")))))) -> 15 | I28: =IF(AND(F28<>"", J28<>""), NETWORKDAYS(TODAY(), J28-1, FESTIVOS!A$1:A$55), "") -> -88 | J28: =IF(AND(F28<>"", H28<>""), WORKDAY(F28, H28, FESTIVOS!A$1:A$55), "") -> 46056 | K28: LAURA GIRALDO | L28: =IF(I28="", "", MAX(0, I28 - (TODAY() - TODAY()))) -> 0 | M28: =IF(OR(I28="", H28=""), "", IF(I28<0, "Vencido", IF(I28>(H28/2), "Supere la mitad", "Bajo la mitad"))) -> Vencido | N28: CE-GC-0033 | O28: 46036 | P28: =IF(OR(O28="", J28=""), "", NETWORKDAYS(J28, O28, FESTIVOS!A27:A81)) -> -15
A29: OTRO | B29: WILLIAM EDMUNDO PIEDRAHITA MAYA | C29: CORPOAMAZONIA | D29: TRASLADO POR COMPETENCIA | E29: 28 | F29: 46035 | G29: COMERCIAL | H29: =IF(A29="INFORMACIÓN O DOCUMENTOS", 10, IF(A29="CONSULTA", 30, IF(A29="FACTURACIÓN Y COBROS", 15, IF(A29="VINCULACIÓN Y DESVINCULACIÓN", 15, IF(A29="NO ES DE NUESTRA COMPETENCIA", 5, IF(A29="OTRO", 15, "")))))) -> 15 | I29: =IF(AND(F29<>"", J29<>""), NETWORKDAYS(TODAY(), J29-1, FESTIVOS!A$1:A$55), "") -> -88 | J29: =IF(AND(F29<>"", H29<>""), WORKDAY(F29, H29, FESTIVOS!A$1:A$55), "") -> 46056 | K29: LAURA GIRALDO | L29: =IF(I29="", "", MAX(0, I29 - (TODAY() - TODAY()))) -> 0 | M29: =IF(OR(I29="", H29=""), "", IF(I29<0, "Vencido", IF(I29>(H29/2), "Supere la mitad", "Bajo la mitad"))) -> Vencido | N29: CE-GC-0033 | O29: 46036 | P29: =IF(OR(O29="", J29=""), "", NETWORKDAYS(J29, O29, FESTIVOS!A28:A82)) -> -15
A30: OTRO | B30: LUIS MANUEL ESPINOSA CALDERON | C30: ALCALDIA | D30: SOLICITUD DE INFORMACIÓN PARA LIQUIDAR EL CONCURSO ECONOMICO | E30: 29 | F30: 46036 | G30: COMERCIAL | H30: =IF(A30="INFORMACIÓN O DOCUMENTOS", 10, IF(A30="CONSULTA", 30, IF(A30="FACTURACIÓN Y COBROS", 15, IF(A30="VINCULACIÓN Y DESVINCULACIÓN", 15, IF(A30="NO ES DE NUESTRA COMPETENCIA", 5, IF(A30="OTRO", 15, "")))))) -> 15 | I30: =IF(AND(F30<>"", J30<>""), NETWORKDAYS(TODAY(), J30-1, FESTIVOS!A$1:A$55), "") -> -87 | J30: =IF(AND(F30<>"", H30<>""), WORKDAY(F30, H30, FESTIVOS!A$1:A$55), "") -> 46057 | K30: LAURA GIRALDO | L30: =IF(I30="", "", MAX(0, I30 - (TODAY() - TODAY()))) -> 0 | M30: =IF(OR(I30="", H30=""), "", IF(I30<0, "Vencido", IF(I30>(H30/2), "Supere la mitad", "Bajo la mitad"))) -> Vencido | N30: CE-GC-0033 | O30: 46036 | P30: =IF(OR(O30="", J30=""), "", NETWORKDAYS(J30, O30, FESTIVOS!A29:A83)) -> -16
A31: OTRO | B31: Javier Hernán Puyo Plazas | C31: MINESTERIO DE TRABAJO | D31: Derecho de Petición fechado el día 23/12/2025 | E31: 30 | F31: 46036 | G31: TALENTO HUMANO | H31: =IF(A31="INFORMACIÓN O DOCUMENTOS", 10, IF(A31="CONSULTA", 30, IF(A31="FACTURACIÓN Y COBROS", 15, IF(A31="VINCULACIÓN Y DESVINCULACIÓN", 15, IF(A31="NO ES DE NUESTRA COMPETENCIA", 5, IF(A31="OTRO", 15, "")))))) -> 15 | I31: =IF(AND(F31<>"", J31<>""), NETWORKDAYS(TODAY(), J31-1, FESTIVOS!A$1:A$55), "") -> -87 | J31: =IF(AND(F31<>"", H31<>""), WORKDAY(F31, H31, FESTIVOS!A$1:A$55), "") -> 46057 | K31: LAURA GIRALDO | L31: =IF(I31="", "", MAX(0, I31 - (TODAY() - TODAY()))) -> 0 | M31: =IF(OR(I31="", H31=""), "", IF(I31<0, "Vencido", IF(I31>(H31/2), "Supere la mitad", "Bajo la mitad"))) -> Vencido | N31: CE-GC-0033 | O31: 46036 | P31: =IF(OR(O31="", J31=""), "", NETWORKDAYS(J31, O31, FESTIVOS!A30:A84)) -> -16
A32: OTRO | B32: LUIS ZAPATA OROZCO | C32: USUARIO DE SERVINTEGRAL | D32: SOLICITUD DE 1 LETRERO | E32: 31 | F32: 46036 | G32: COMERCIAL | H32: =IF(A32="INFORMACIÓN O DOCUMENTOS", 10, IF(A32="CONSULTA", 30, IF(A32="FACTURACIÓN Y COBROS", 15, IF(A32="VINCULACIÓN Y DESVINCULACIÓN", 15, IF(A32="NO ES DE NUESTRA COMPETENCIA", 5, IF(A32="OTRO", 15, "")))))) -> 15 | I32: =IF(AND(F32<>"", J32<>""), NETWORKDAYS(TODAY(), J32-1, FESTIVOS!A$1:A$55), "") -> -87 | J32: =IF(AND(F32<>"", H32<>""), WORKDAY(F32, H32, FESTIVOS!A$1:A$55), "") -> 46057 | K32: LAURA GIRALDO | L32: =IF(I32="", "", MAX(0, I32 - (TODAY() - TODAY()))) -> 0 | M32: =IF(OR(I32="", H32=""), "", IF(I32<0, "Vencido", IF(I32>(H32/2), "Supere la mitad", "Bajo la mitad"))) -> Vencido | N32: CE-GC-0033 | O32: 46036 | P32: =IF(OR(O32="", J32=""), "", NETWORKDAYS(J32, O32, FESTIVOS!A31:A85)) -> -16
A33: OTRO | B33: CLAUDIA TOVAR | C33: USUARIO DE SERVINTEGRAL | D33: VINCULACIÓN DIRECTA | E33: 32 | F33: 46036 | G33: COMERCIAL | H33: =IF(A33="INFORMACIÓN O DOCUMENTOS", 10, IF(A33="CONSULTA", 30, IF(A33="FACTURACIÓN Y COBROS", 15, IF(A33="VINCULACIÓN Y DESVINCULACIÓN", 15, IF(A33="NO ES DE NUESTRA COMPETENCIA", 5, IF(A33="OTRO", 15, "")))))) -> 15 | I33: =IF(AND(F33<>"", J33<>""), NETWORKDAYS(TODAY(), J33-1, FESTIVOS!A$1:A$55), "") -> -87 | J33: =IF(AND(F33<>"", H33<>""), WORKDAY(F33, H33, FESTIVOS!A$1:A$55), "") -> 46057 | K33: LAURA GIRALDO | L33: =IF(I33="", "", MAX(0, I33 - (TODAY() - TODAY()))) -> 0 | M33: =IF(OR(I33="", H33=""), "", IF(I33<0, "Vencido", IF(I33>(H33/2), "Supere la mitad", "Bajo la mitad"))) -> Vencido | N33: CE-GC-0033 | O33: 46036 | P33: =IF(OR(O33="", J33=""), "", NETWORKDAYS(J33, O33, FESTIVOS!A32:A86)) -> -16
A34: OTRO | B34: MARIA IRAIDES HERRERA GAITAN | C34: USUARIO DE SERVINTEGRAL | D34: VINCULACIÓN DIRECTA | E34: 33 | F34: 46036 | G34: COMERCIAL | H34: =IF(A34="INFORMACIÓN O DOCUMENTOS", 10, IF(A34="CONSULTA", 30, IF(A34="FACTURACIÓN Y COBROS", 15, IF(A34="VINCULACIÓN Y DESVINCULACIÓN", 15, IF(A34="NO ES DE NUESTRA COMPETENCIA", 5, IF(A34="OTRO", 15, "")))))) -> 15 | I34: =IF(AND(F34<>"", J34<>""), NETWORKDAYS(TODAY(), J34-1, FESTIVOS!A$1:A$55), "") -> -87 | J34: =IF(AND(F34<>"", H34<>""), WORKDAY(F34, H34, FESTIVOS!A$1:A$55), "") -> 46057 | K34: LAURA GIRALDO | L34: =IF(I34="", "", MAX(0, I34 - (TODAY() - TODAY()))) -> 0 | M34: =IF(OR(I34="", H34=""), "", IF(I34<0, "Vencido", IF(I34>(H34/2), "Supere la mitad", "Bajo la mitad"))) -> Vencido | N34: CE-GC-0033 | O34: 46036 | P34: =IF(OR(O34="", J34=""), "", NETWORKDAYS(J34, O34, FESTIVOS!A33:A87)) -> -16
... A186: OTRO | B186: CHRISTYAM CAMILO SALAZAR ROJAS | C186: ALCALDIA | D186: APOYO INSTITUCIONAL | E186: 185 | F186: 46062 | G186: COMERCIAL | H186: =IF(A186="INFORMACIÓN O DOCUMENTOS", 10, IF(A186="CONSULTA", 30, IF(A186="FACTURACIÓN Y COBROS", 15, IF(A186="VINCULACIÓN Y DESVINCULACIÓN", 15, IF(A186="NO ES DE NUESTRA COMPETENCIA", 5, IF(A186="OTRO", 15, "")))))) -> 15 | I186: =IF(AND(F186<>"", J186<>""), NETWORKDAYS(TODAY(), J186-1, FESTIVOS!A$1:A$55), "") -> -68 | J186: =IF(AND(F186<>"", H186<>""), WORKDAY(F186, H186, FESTIVOS!A$1:A$55), "") -> 46083 | K186: LAURA GIRALDO | L186: =IF(I186="", "", MAX(0, I186 - (TODAY() - TODAY()))) -> 0 | M186: =IF(OR(I186="", H186=""), "", IF(I186<0, "Vencido", IF(I186>(H186/2), "Supere la mitad", "Bajo la mitad"))) -> Vencido | N186: CE-GC-0228 | O186: 46069 | P186: =IF(OR(O186="", J186=""), "", NETWORKDAYS(J186, O186, FESTIVOS!A185:A239)) -> -11
A187: OTRO | B187: OSCAR JAVIER RAMOS | C187: USUARIO DE SERVINTEGRAL | D187: Solicitud de apoyo para jornada de aseo y embellecimiento I.E. ANDES SEDE ALPES | E187: 186 | F187: 46062 | H187: =IF(A187="INFORMACIÓN O DOCUMENTOS", 10, IF(A187="CONSULTA", 30, IF(A187="FACTURACIÓN Y COBROS", 15, IF(A187="VINCULACIÓN Y DESVINCULACIÓN", 15, IF(A187="NO ES DE NUESTRA COMPETENCIA", 5, IF(A187="OTRO", 15, "")))))) -> 15 | I187: =IF(AND(F187<>"", J187<>""), NETWORKDAYS(TODAY(), J187-1, FESTIVOS!A$1:A$55), "") -> -68 | J187: =IF(AND(F187<>"", H187<>""), WORKDAY(F187, H187, FESTIVOS!A$1:A$55), "") -> 46083 | K187: LAURA GIRALDO | L187: =IF(I187="", "", MAX(0, I187 - (TODAY() - TODAY()))) -> 0 | M187: =IF(OR(I187="", H187=""), "", IF(I187<0, "Vencido", IF(I187>(H187/2), "Supere la mitad", "Bajo la mitad"))) -> Vencido | N187: CE-GC-0033 | O187: 46036 | P187: =IF(OR(O187="", J187=""), "", NETWORKDAYS(J187, O187, FESTIVOS!A186:A240)) -> -34
A188: OTRO | B188: ARISTIDES TOVAR | C188: USUARIO DE SERVINTEGRAL | D188: ENCUENTRO NACIONAL | E188: 187 | F188: 46062 | H188: =IF(A188="INFORMACIÓN O DOCUMENTOS", 10, IF(A188="CONSULTA", 30, IF(A188="FACTURACIÓN Y COBROS", 15, IF(A188="VINCULACIÓN Y DESVINCULACIÓN", 15, IF(A188="NO ES DE NUESTRA COMPETENCIA", 5, IF(A188="OTRO", 15, "")))))) -> 15 | I188: =IF(AND(F188<>"", J188<>""), NETWORKDAYS(TODAY(), J188-1, FESTIVOS!A$1:A$55), "") -> -68 | J188: =IF(AND(F188<>"", H188<>""), WORKDAY(F188, H188, FESTIVOS!A$1:A$55), "") -> 46083 | K188: LAURA GIRALDO | L188: =IF(I188="", "", MAX(0, I188 - (TODAY() - TODAY()))) -> 0 | M188: =IF(OR(I188="", H188=""), "", IF(I188<0, "Vencido", IF(I188>(H188/2), "Supere la mitad", "Bajo la mitad"))) -> Vencido | N188: CE-GC-0033 | O188: 46036 | P188: =IF(OR(O188="", J188=""), "", NETWORKDAYS(J188, O188, FESTIVOS!A187:A241)) -> -34
A189: OTRO | B189: QUEJA DEL SERVICIO | C189: USUARIO DE SERVINTEGRAL | D189: EVIDALIA LADINO | E189: 188 | F189: 46062 | H189: =IF(A189="INFORMACIÓN O DOCUMENTOS", 10, IF(A189="CONSULTA", 30, IF(A189="FACTURACIÓN Y COBROS", 15, IF(A189="VINCULACIÓN Y DESVINCULACIÓN", 15, IF(A189="NO ES DE NUESTRA COMPETENCIA", 5, IF(A189="OTRO", 15, "")))))) -> 15 | I189: =IF(AND(F189<>"", J189<>""), NETWORKDAYS(TODAY(), J189-1, FESTIVOS!A$1:A$55), "") -> -68 | J189: =IF(AND(F189<>"", H189<>""), WORKDAY(F189, H189, FESTIVOS!A$1:A$55), "") -> 46083 | K189: LAURA GIRALDO | L189: =IF(I189="", "", MAX(0, I189 - (TODAY() - TODAY()))) -> 0 | M189: =IF(OR(I189="", H189=""), "", IF(I189<0, "Vencido", IF(I189>(H189/2), "Supere la mitad", "Bajo la mitad"))) -> Vencido | N189: CE-GC-0033 | O189: 46036 | P189: =IF(OR(O189="", J189=""), "", NETWORKDAYS(J189, O189, FESTIVOS!A188:A242)) -> -34
A190: OTRO | B190: SIXTO ALFONSO PARAMO | C190: USUARIO DE SERVINTEGRAL | D190: COMUNICACIÓN DE ACTA MEDIANTE LA CUAL SE RESUELVE IMPUGNACIÓN FRENTE AL CASO MARIANO OSWALDO ROJAS ARANGO- C.C 94043507 Y SE REITERA EL DEBER DE ALLEGAR EL SOPORTE DE PAGO DE HONORARIOS A FAVOR DE LA JUNTA NACIONAL PARA EL TRÁMITE CORRESPONDIENTE | E190: 189 | F190: 46062 | H190: =IF(A190="INFORMACIÓN O DOCUMENTOS", 10, IF(A190="CONSULTA", 30, IF(A190="FACTURACIÓN Y COBROS", 15, IF(A190="VINCULACIÓN Y DESVINCULACIÓN", 15, IF(A190="NO ES DE NUESTRA COMPETENCIA", 5, IF(A190="OTRO", 15, "")))))) -> 15 | I190: =IF(AND(F190<>"", J190<>""), NETWORKDAYS(TODAY(), J190-1, FESTIVOS!A$1:A$55), "") -> -68 | J190: =IF(AND(F190<>"", H190<>""), WORKDAY(F190, H190, FESTIVOS!A$1:A$55), "") -> 46083 | K190: LAURA GIRALDO | L190: =IF(I190="", "", MAX(0, I190 - (TODAY() - TODAY()))) -> 0 | M190: =IF(OR(I190="", H190=""), "", IF(I190<0, "Vencido", IF(I190>(H190/2), "Supere la mitad", "Bajo la mitad"))) -> Vencido | N190: CE-GC-0033 | O190: 46036 | P190: =IF(OR(O190="", J190=""), "", NETWORKDAYS(J190, O190, FESTIVOS!A189:A243)) -> -34
A191: OTRO | B191: CAMILO ENRIQUE DIAZ CARDENAS | C191: USUARIO DE SERVINTEGRAL | D191: ACEPTACIÓN DE LA PROPUESTA | E191: 190 | F191: 46062 | H191: =IF(A191="INFORMACIÓN O DOCUMENTOS", 10, IF(A191="CONSULTA", 30, IF(A191="FACTURACIÓN Y COBROS", 15, IF(A191="VINCULACIÓN Y DESVINCULACIÓN", 15, IF(A191="NO ES DE NUESTRA COMPETENCIA", 5, IF(A191="OTRO", 15, "")))))) -> 15 | I191: =IF(AND(F191<>"", J191<>""), NETWORKDAYS(TODAY(), J191-1, FESTIVOS!A$1:A$55), "") -> -68 | J191: =IF(AND(F191<>"", H191<>""), WORKDAY(F191, H191, FESTIVOS!A$1:A$55), "") -> 46083 | K191: LAURA GIRALDO | L191: =IF(I191="", "", MAX(0, I191 - (TODAY() - TODAY()))) -> 0 | M191: =IF(OR(I191="", H191=""), "", IF(I191<0, "Vencido", IF(I191>(H191/2), "Supere la mitad", "Bajo la mitad"))) -> Vencido | N191: CE-GC-0033 | O191: 46036 | P191: =IF(OR(O191="", J191=""), "", NETWORKDAYS(J191, O191, FESTIVOS!A190:A244)) -> -34
A192: OTRO | B192: YOLANDA NARVAEZ | C192: USUARIO DE SERVINTEGRAL | D192: SOLIICTUD DE CERTIFICADO | E192: 191 | F192: 46062 | H192: =IF(A192="INFORMACIÓN O DOCUMENTOS", 10, IF(A192="CONSULTA", 30, IF(A192="FACTURACIÓN Y COBROS", 15, IF(A192="VINCULACIÓN Y DESVINCULACIÓN", 15, IF(A192="NO ES DE NUESTRA COMPETENCIA", 5, IF(A192="OTRO", 15, "")))))) -> 15 | I192: =IF(AND(F192<>"", J192<>""), NETWORKDAYS(TODAY(), J192-1, FESTIVOS!A$1:A$55), "") -> -68 | J192: =IF(AND(F192<>"", H192<>""), WORKDAY(F192, H192, FESTIVOS!A$1:A$55), "") -> 46083 | K192: LAURA GIRALDO | L192: =IF(I192="", "", MAX(0, I192 - (TODAY() - TODAY()))) -> 0 | M192: =IF(OR(I192="", H192=""), "", IF(I192<0, "Vencido", IF(I192>(H192/2), "Supere la mitad", "Bajo la mitad"))) -> Vencido | N192: CE-GC-0033 | O192: 46036 | P192: =IF(OR(O192="", J192=""), "", NETWORKDAYS(J192, O192, FESTIVOS!A191:A245)) -> -34
A193: OTRO | B193: YANETH MOLINA | C193: USUARIO DE SERVINTEGRAL | D193: COTIZACIÓN | E193: 192 | F193: 46062 | H193: =IF(A193="INFORMACIÓN O DOCUMENTOS", 10, IF(A193="CONSULTA", 30, IF(A193="FACTURACIÓN Y COBROS", 15, IF(A193="VINCULACIÓN Y DESVINCULACIÓN", 15, IF(A193="NO ES DE NUESTRA COMPETENCIA", 5, IF(A193="OTRO", 15, "")))))) -> 15 | I193: =IF(AND(F193<>"", J193<>""), NETWORKDAYS(TODAY(), J193-1, FESTIVOS!A$1:A$55), "") -> -68 | J193: =IF(AND(F193<>"", H193<>""), WORKDAY(F193, H193, FESTIVOS!A$1:A$55), "") -> 46083 | K193: LAURA GIRALDO | L193: =IF(I193="", "", MAX(0, I193 - (TODAY() - TODAY()))) -> 0 | M193: =IF(OR(I193="", H193=""), "", IF(I193<0, "Vencido", IF(I193>(H193/2), "Supere la mitad", "Bajo la mitad"))) -> Vencido | N193: CE-GC-0033 | O193: 46036 | P193: =IF(OR(O193="", J193=""), "", NETWORKDAYS(J193, O193, FESTIVOS!A192:A246)) -> -34
A194: OTRO | B194: ELBA OBANDO | C194: USUARIO DE SERVINTEGRAL | D194: SOLICITUD DE PAZ Y SALVO | E194: 193 | F194: 46062 | H194: =IF(A194="INFORMACIÓN O DOCUMENTOS", 10, IF(A194="CONSULTA", 30, IF(A194="FACTURACIÓN Y COBROS", 15, IF(A194="VINCULACIÓN Y DESVINCULACIÓN", 15, IF(A194="NO ES DE NUESTRA COMPETENCIA", 5, IF(A194="OTRO", 15, "")))))) -> 15 | I194: =IF(AND(F194<>"", J194<>""), NETWORKDAYS(TODAY(), J194-1, FESTIVOS!A$1:A$55), "") -> -68 | J194: =IF(AND(F194<>"", H194<>""), WORKDAY(F194, H194, FESTIVOS!A$1:A$55), "") -> 46083 | K194: LAURA GIRALDO | L194: =IF(I194="", "", MAX(0, I194 - (TODAY() - TODAY()))) -> 0 | M194: =IF(OR(I194="", H194=""), "", IF(I194<0, "Vencido", IF(I194>(H194/2), "Supere la mitad", "Bajo la mitad"))) -> Vencido | N194: CE-GC-0033 | O194: 46036 | P194: =IF(OR(O194="", J194=""), "", NETWORKDAYS(J194, O194, FESTIVOS!A193:A247)) -> -34
A195: OTRO | B195: LUZ DARY MURILLO GOMEZ | C195: USUARIO DE SERVINTEGRAL | D195: APOYO INSTITUCIONAL | E195: 194 | F195: 46062 | H195: =IF(A195="INFORMACIÓN O DOCUMENTOS", 10, IF(A195="CONSULTA", 30, IF(A195="FACTURACIÓN Y COBROS", 15, IF(A195="VINCULACIÓN Y DESVINCULACIÓN", 15, IF(A195="NO ES DE NUESTRA COMPETENCIA", 5, IF(A195="OTRO", 15, "")))))) -> 15 | I195: =IF(AND(F195<>"", J195<>""), NETWORKDAYS(TODAY(), J195-1, FESTIVOS!A$1:A$55), "") -> -68 | J195: =IF(AND(F195<>"", H195<>""), WORKDAY(F195, H195, FESTIVOS!A$1:A$55), "") -> 46083 | K195: LAURA GIRALDO | L195: =IF(I195="", "", MAX(0, I195 - (TODAY() - TODAY()))) -> 0 | M195: =IF(OR(I195="", H195=""), "", IF(I195<0, "Vencido", IF(I195>(H195/2), "Supere la mitad", "Bajo la mitad"))) -> Vencido | N195: CE-GC-0033 | O195: 46036 | P195: =IF(OR(O195="", J195=""), "", NETWORKDAYS(J195, O195, FESTIVOS!A194:A248)) -> -34
A196: OTRO | B196: JESÚS ALBERTO ESCOBAR HURTADO | C196: ALCALDIA | D196: REMISIÓN DE CIRCULAR 003 | E196: 195 | F196: 46062 | H196: =IF(A196="INFORMACIÓN O DOCUMENTOS", 10, IF(A196="CONSULTA", 30, IF(A196="FACTURACIÓN Y COBROS", 15, IF(A196="VINCULACIÓN Y DESVINCULACIÓN", 15, IF(A196="NO ES DE NUESTRA COMPETENCIA", 5, IF(A196="OTRO", 15, "")))))) -> 15 | I196: =IF(AND(F196<>"", J196<>""), NETWORKDAYS(TODAY(), J196-1, FESTIVOS!A$1:A$55), "") -> -68 | J196: =IF(AND(F196<>"", H196<>""), WORKDAY(F196, H196, FESTIVOS!A$1:A$55), "") -> 46083 | K196: LAURA GIRALDO | L196: =IF(I196="", "", MAX(0, I196 - (TODAY() - TODAY()))) -> 0 | M196: =IF(OR(I196="", H196=""), "", IF(I196<0, "Vencido", IF(I196>(H196/2), "Supere la mitad", "Bajo la mitad"))) -> Vencido | N196: CE-GC-0033 | O196: 46036 | P196: =IF(OR(O196="", J196=""), "", NETWORKDAYS(J196, O196, FESTIVOS!A195:A249)) -> -34
A197: OTRO | B197: MARIBEL CAMACHO | C197: USUARIO DE SERVINTEGRAL | D197: capacitaciones a Empresas 100% Subsidiado | E197: 196 | F197: 46062 | H197: =IF(A197="INFORMACIÓN O DOCUMENTOS", 10, IF(A197="CONSULTA", 30, IF(A197="FACTURACIÓN Y COBROS", 15, IF(A197="VINCULACIÓN Y DESVINCULACIÓN", 15, IF(A197="NO ES DE NUESTRA COMPETENCIA", 5, IF(A197="OTRO", 15, "")))))) -> 15 | I197: =IF(AND(F197<>"", J197<>""), NETWORKDAYS(TODAY(), J197-1, FESTIVOS!A$1:A$55), "") -> -68 | J197: =IF(AND(F197<>"", H197<>""), WORKDAY(F197, H197, FESTIVOS!A$1:A$55), "") -> 46083 | K197: LAURA GIRALDO | L197: =IF(I197="", "", MAX(0, I197 - (TODAY() - TODAY()))) -> 0 | M197: =IF(OR(I197="", H197=""), "", IF(I197<0, "Vencido", IF(I197>(H197/2), "Supere la mitad", "Bajo la mitad"))) -> Vencido | N197: CE-GC-0033 | O197: 46036 | P197: =IF(OR(O197="", J197=""), "", NETWORKDAYS(J197, O197, FESTIVOS!A196:A250)) -> -34
A198: OTRO | B198: HERMES DARÍO CRUZ GÓMEZ | C198: USUARIO DE SERVINTEGRAL | D198: Solicitud de información – Factor de productividad | E198: 197 | F198: 46063 | H198: =IF(A198="INFORMACIÓN O DOCUMENTOS", 10, IF(A198="CONSULTA", 30, IF(A198="FACTURACIÓN Y COBROS", 15, IF(A198="VINCULACIÓN Y DESVINCULACIÓN", 15, IF(A198="NO ES DE NUESTRA COMPETENCIA", 5, IF(A198="OTRO", 15, "")))))) -> 15 | I198: =IF(AND(F198<>"", J198<>""), NETWORKDAYS(TODAY(), J198-1, FESTIVOS!A$1:A$55), "") -> -68 | J198: =IF(AND(F198<>"", H198<>""), WORKDAY(F198, H198, FESTIVOS!A$1:A$55), "") -> 46084 | K198: LAURA GIRALDO | L198: =IF(I198="", "", MAX(0, I198 - (TODAY() - TODAY()))) -> 0 | M198: =IF(OR(I198="", H198=""), "", IF(I198<0, "Vencido", IF(I198>(H198/2), "Supere la mitad", "Bajo la mitad"))) -> Vencido | N198: CE-GC-0033 | O198: 46036 | P198: =IF(OR(O198="", J198=""), "", NETWORKDAYS(J198, O198, FESTIVOS!A197:A251)) -> -35
... A263: OTRO | B263: JESSIKA PERDOMO | C263: ALCALDIA | D263: SOLICITUD DE CERTIFICACIÓN | E263: 262 | F263: 46072 | H263: =IF(A263="INFORMACIÓN O DOCUMENTOS", 10, IF(A263="CONSULTA", 30, IF(A263="FACTURACIÓN Y COBROS", 15, IF(A263="VINCULACIÓN Y DESVINCULACIÓN", 15, IF(A263="NO ES DE NUESTRA COMPETENCIA", 5, IF(A263="OTRO", 15, "")))))) -> 15 | I263: =IF(AND(F263<>"", J263<>""), NETWORKDAYS(TODAY(), J263-1, FESTIVOS!A$1:A$55), "") -> -61 | J263: =IF(AND(F263<>"", H263<>""), WORKDAY(F263, H263, FESTIVOS!A$1:A$55), "") -> 46093 | K263: LAURA GIRALDO | L263: =IF(I263="", "", MAX(0, I263 - (TODAY() - TODAY()))) -> 0 | M263: =IF(OR(I263="", H263=""), "", IF(I263<0, "Vencido", IF(I263>(H263/2), "Supere la mitad", "Bajo la mitad"))) -> Vencido | N263: CE-GC-0283 | O263: 46085 | P263: =IF(OR(O263="", J263=""), "", NETWORKDAYS(J263, O263, FESTIVOS!A262:A316)) -> -7
A264: OTRO | B264: DOMINGA DE JESÚS RAMOS SUÁREZ | C264: JUZGADO | D264: LEVANTAMIENTO DE MEDIDAS CAUTELARES - PROCESO EJECUTIVO DE ALIMENTOS RAD. 2025-00118-00-00 | E264: 263 | F264: 46072 | H264: =IF(A264="INFORMACIÓN O DOCUMENTOS", 10, IF(A264="CONSULTA", 30, IF(A264="FACTURACIÓN Y COBROS", 15, IF(A264="VINCULACIÓN Y DESVINCULACIÓN", 15, IF(A264="NO ES DE NUESTRA COMPETENCIA", 5, IF(A264="OTRO", 15, "")))))) -> 15 | I264: =IF(AND(F264<>"", J264<>""), NETWORKDAYS(TODAY(), J264-1, FESTIVOS!A$1:A$55), "") -> -61 | J264: =IF(AND(F264<>"", H264<>""), WORKDAY(F264, H264, FESTIVOS!A$1:A$55), "") -> 46093 | K264: LAURA GIRALDO | L264: =IF(I264="", "", MAX(0, I264 - (TODAY() - TODAY()))) -> 0 | M264: =IF(OR(I264="", H264=""), "", IF(I264<0, "Vencido", IF(I264>(H264/2), "Supere la mitad", "Bajo la mitad"))) -> Vencido | N264: NO REQUIERE RESPUESTA | P264: =IF(OR(O264="", J264=""), "", NETWORKDAYS(J264, O264, FESTIVOS!A263:A317))
A265: OTRO | B265: Leidi Milena Santamaria Perez | C265: ALCALDIA | D265: Solicitud de Certificación de pago de subsidios año 2025 | E265: 264 | F265: 46072 | H265: =IF(A265="INFORMACIÓN O DOCUMENTOS", 10, IF(A265="CONSULTA", 30, IF(A265="FACTURACIÓN Y COBROS", 15, IF(A265="VINCULACIÓN Y DESVINCULACIÓN", 15, IF(A265="NO ES DE NUESTRA COMPETENCIA", 5, IF(A265="OTRO", 15, "")))))) -> 15 | I265: =IF(AND(F265<>"", J265<>""), NETWORKDAYS(TODAY(), J265-1, FESTIVOS!A$1:A$55), "") -> -61 | J265: =IF(AND(F265<>"", H265<>""), WORKDAY(F265, H265, FESTIVOS!A$1:A$55), "") -> 46093 | K265: LAURA GIRALDO | L265: =IF(I265="", "", MAX(0, I265 - (TODAY() - TODAY()))) -> 0 | M265: =IF(OR(I265="", H265=""), "", IF(I265<0, "Vencido", IF(I265>(H265/2), "Supere la mitad", "Bajo la mitad"))) -> Vencido | N265: CE-GC-0274 | O265: 46076 | P265: =IF(OR(O265="", J265=""), "", NETWORKDAYS(J265, O265, FESTIVOS!A264:A318)) -> -14
A266: OTRO | B266: ANDRES CAMILO CADAVID | C266: USUARIO DE SERVINTEGRAL | D266: CERTIFICADO DEUDA JASMÍN BELTRÁN MORALES | E266: 265 | F266: 46072 | H266: =IF(A266="INFORMACIÓN O DOCUMENTOS", 10, IF(A266="CONSULTA", 30, IF(A266="FACTURACIÓN Y COBROS", 15, IF(A266="VINCULACIÓN Y DESVINCULACIÓN", 15, IF(A266="NO ES DE NUESTRA COMPETENCIA", 5, IF(A266="OTRO", 15, "")))))) -> 15 | I266: =IF(AND(F266<>"", J266<>""), NETWORKDAYS(TODAY(), J266-1, FESTIVOS!A$1:A$55), "") -> -61 | J266: =IF(AND(F266<>"", H266<>""), WORKDAY(F266, H266, FESTIVOS!A$1:A$55), "") -> 46093 | K266: LAURA GIRALDO | L266: =IF(I266="", "", MAX(0, I266 - (TODAY() - TODAY()))) -> 0 | M266: =IF(OR(I266="", H266=""), "", IF(I266<0, "Vencido", IF(I266>(H266/2), "Supere la mitad", "Bajo la mitad"))) -> Vencido | N266: CE-GT-0280 | O266: 46090 | P266: =IF(OR(O266="", J266=""), "", NETWORKDAYS(J266, O266, FESTIVOS!A265:A319)) -> -4
A267: OTRO | B267: YENY CAROLINA VILLAMIL | C267: ELECTROCAQUETA | D267: Traslado por competencia del oficio con rad No 2026-1-1-222 del 18-02-2026 | E267: 266 | F267: 46072 | H267: =IF(A267="INFORMACIÓN O DOCUMENTOS", 10, IF(A267="CONSULTA", 30, IF(A267="FACTURACIÓN Y COBROS", 15, IF(A267="VINCULACIÓN Y DESVINCULACIÓN", 15, IF(A267="NO ES DE NUESTRA COMPETENCIA", 5, IF(A267="OTRO", 15, "")))))) -> 15 | I267: =IF(AND(F267<>"", J267<>""), NETWORKDAYS(TODAY(), J267-1, FESTIVOS!A$1:A$55), "") -> -61 | J267: =IF(AND(F267<>"", H267<>""), WORKDAY(F267, H267, FESTIVOS!A$1:A$55), "") -> 46093 | K267: LAURA GIRALDO | L267: =IF(I267="", "", MAX(0, I267 - (TODAY() - TODAY()))) -> 0 | M267: =IF(OR(I267="", H267=""), "", IF(I267<0, "Vencido", IF(I267>(H267/2), "Supere la mitad", "Bajo la mitad"))) -> Vencido | N267: CE-GC-0363 | O267: 46093 | P267: =IF(OR(O267="", J267=""), "", NETWORKDAYS(J267, O267, FESTIVOS!A266:A320)) -> 1
A268: OTRO | B268: JAIRO ANTONIO MOLINA | C268: USUARIO DE SERVINTEGRAL | D268: SOLICITUD DE CERTIFICADO | E268: 267 | F268: 46072 | H268: =IF(A268="INFORMACIÓN O DOCUMENTOS", 10, IF(A268="CONSULTA", 30, IF(A268="FACTURACIÓN Y COBROS", 15, IF(A268="VINCULACIÓN Y DESVINCULACIÓN", 15, IF(A268="NO ES DE NUESTRA COMPETENCIA", 5, IF(A268="OTRO", 15, "")))))) -> 15 | I268: =IF(AND(F268<>"", J268<>""), NETWORKDAYS(TODAY(), J268-1, FESTIVOS!A$1:A$55), "") -> -61 | J268: =IF(AND(F268<>"", H268<>""), WORKDAY(F268, H268, FESTIVOS!A$1:A$55), "") -> 46093 | K268: LAURA GIRALDO | L268: =IF(I268="", "", MAX(0, I268 - (TODAY() - TODAY()))) -> 0 | M268: =IF(OR(I268="", H268=""), "", IF(I268<0, "Vencido", IF(I268>(H268/2), "Supere la mitad", "Bajo la mitad"))) -> Vencido | N268: CE-GC-0294 | O268: 46107 | P268: =IF(OR(O268="", J268=""), "", NETWORKDAYS(J268, O268, FESTIVOS!A267:A321)) -> 11
A269: OTRO | B269: RIQUELIO OVIEDO | C269: USUARIO DE SERVINTEGRAL | D269: SOLICITUD DE PODA | E269: 268 | F269: 46073 | H269: =IF(A269="INFORMACIÓN O DOCUMENTOS", 10, IF(A269="CONSULTA", 30, IF(A269="FACTURACIÓN Y COBROS", 15, IF(A269="VINCULACIÓN Y DESVINCULACIÓN", 15, IF(A269="NO ES DE NUESTRA COMPETENCIA", 5, IF(A269="OTRO", 15, "")))))) -> 15 | I269: =IF(AND(F269<>"", J269<>""), NETWORKDAYS(TODAY(), J269-1, FESTIVOS!A$1:A$55), "") -> -60 | J269: =IF(AND(F269<>"", H269<>""), WORKDAY(F269, H269, FESTIVOS!A$1:A$55), "") -> 46094 | K269: LAURA GIRALDO | L269: =IF(I269="", "", MAX(0, I269 - (TODAY() - TODAY()))) -> 0 | M269: =IF(OR(I269="", H269=""), "", IF(I269<0, "Vencido", IF(I269>(H269/2), "Supere la mitad", "Bajo la mitad"))) -> Vencido | N269: CE-GR-0278 | O269: 46085 | P269: =IF(OR(O269="", J269=""), "", NETWORKDAYS(J269, O269, FESTIVOS!A268:A322)) -> -8
A270: OTRO | B270: CHRISTYAM CAMILO SALAZAR ROJAS | C270: ALCALDIA | D270: SOLICITUD DE COTIZACIÓN | E270: 269 | F270: 46073 | H270: =IF(A270="INFORMACIÓN O DOCUMENTOS", 10, IF(A270="CONSULTA", 30, IF(A270="FACTURACIÓN Y COBROS", 15, IF(A270="VINCULACIÓN Y DESVINCULACIÓN", 15, IF(A270="NO ES DE NUESTRA COMPETENCIA", 5, IF(A270="OTRO", 15, "")))))) -> 15 | I270: =IF(AND(F270<>"", J270<>""), NETWORKDAYS(TODAY(), J270-1, FESTIVOS!A$1:A$55), "") -> -60 | J270: =IF(AND(F270<>"", H270<>""), WORKDAY(F270, H270, FESTIVOS!A$1:A$55), "") -> 46094 | K270: LAURA GIRALDO | L270: =IF(I270="", "", MAX(0, I270 - (TODAY() - TODAY()))) -> 0 | M270: =IF(OR(I270="", H270=""), "", IF(I270<0, "Vencido", IF(I270>(H270/2), "Supere la mitad", "Bajo la mitad"))) -> Vencido | N270: CE-GC-0308 | O270: 46085 | P270: =IF(OR(O270="", J270=""), "", NETWORKDAYS(J270, O270, FESTIVOS!A269:A323)) -> -8
A271: OTRO | B271: INGESCOR S.A.S. | C271: USUARIO DE SERVINTEGRAL | D271: SOLICITUD INFORMACIÓN DE CAPACITACIÓN EN GESTIÓN DE RESIDUOS Y SOSTENIBILIDAD | E271: 270 | F271: 46073 | H271: =IF(A271="INFORMACIÓN O DOCUMENTOS", 10, IF(A271="CONSULTA", 30, IF(A271="FACTURACIÓN Y COBROS", 15, IF(A271="VINCULACIÓN Y DESVINCULACIÓN", 15, IF(A271="NO ES DE NUESTRA COMPETENCIA", 5, IF(A271="OTRO", 15, "")))))) -> 15 | I271: =IF(AND(F271<>"", J271<>""), NETWORKDAYS(TODAY(), J271-1, FESTIVOS!A$1:A$55), "") -> -60 | J271: =IF(AND(F271<>"", H271<>""), WORKDAY(F271, H271, FESTIVOS!A$1:A$55), "") -> 46094 | K271: LAURA GIRALDO | L271: =IF(I271="", "", MAX(0, I271 - (TODAY() - TODAY()))) -> 0 | M271: =IF(OR(I271="", H271=""), "", IF(I271<0, "Vencido", IF(I271>(H271/2), "Supere la mitad", "Bajo la mitad"))) -> Vencido | N271: CE-GR-0293 | O271: 46079 | P271: =IF(OR(O271="", J271=""), "", NETWORKDAYS(J271, O271, FESTIVOS!A270:A324)) -> -12
A272: OTRO | B272: MAYRA ARTUNDUAGA | C272: ESAC | D272: DESAFILIACIÓN | E272: 271 | F272: 46073 | G272: COMERCIAL | H272: =IF(A272="INFORMACIÓN O DOCUMENTOS", 10, IF(A272="CONSULTA", 30, IF(A272="FACTURACIÓN Y COBROS", 15, IF(A272="VINCULACIÓN Y DESVINCULACIÓN", 15, IF(A272="NO ES DE NUESTRA COMPETENCIA", 5, IF(A272="OTRO", 15, "")))))) -> 15 | I272: =IF(AND(F272<>"", J272<>""), NETWORKDAYS(TODAY(), J272-1, FESTIVOS!A$1:A$55), "") -> -60 | J272: =IF(AND(F272<>"", H272<>""), WORKDAY(F272, H272, FESTIVOS!A$1:A$55), "") -> 46094 | K272: LAURA GIRALDO | L272: =IF(I272="", "", MAX(0, I272 - (TODAY() - TODAY()))) -> 0 | M272: =IF(OR(I272="", H272=""), "", IF(I272<0, "Vencido", IF(I272>(H272/2), "Supere la mitad", "Bajo la mitad"))) -> Vencido | N272: CE-GC-0326 | O272: 46091
A273: OTRO | B273: MAYRA ARTUNDUAGA | C273: ESAC | D273: DESAFILIACIÓN | E273: 272 | F273: 46073 | G273: COMERCIAL | H273: =IF(A273="INFORMACIÓN O DOCUMENTOS", 10, IF(A273="CONSULTA", 30, IF(A273="FACTURACIÓN Y COBROS", 15, IF(A273="VINCULACIÓN Y DESVINCULACIÓN", 15, IF(A273="NO ES DE NUESTRA COMPETENCIA", 5, IF(A273="OTRO", 15, "")))))) -> 15 | I273: =IF(AND(F273<>"", J273<>""), NETWORKDAYS(TODAY(), J273-1, FESTIVOS!A$1:A$55), "") -> -60 | J273: =IF(AND(F273<>"", H273<>""), WORKDAY(F273, H273, FESTIVOS!A$1:A$55), "") -> 46094 | K273: LAURA GIRALDO | L273: =IF(I273="", "", MAX(0, I273 - (TODAY() - TODAY()))) -> 0 | M273: =IF(OR(I273="", H273=""), "", IF(I273<0, "Vencido", IF(I273>(H273/2), "Supere la mitad", "Bajo la mitad"))) -> Vencido | N273: CE-GC-0327 | O273: NO FIRMADO
A274: OTRO | B274: MAYRA ARTUNDUAGA | C274: ESAC | D274: DESAFILIACIÓN | E274: 273 | F274: 46073 | G274: COMERCIAL | H274: =IF(A274="INFORMACIÓN O DOCUMENTOS", 10, IF(A274="CONSULTA", 30, IF(A274="FACTURACIÓN Y COBROS", 15, IF(A274="VINCULACIÓN Y DESVINCULACIÓN", 15, IF(A274="NO ES DE NUESTRA COMPETENCIA", 5, IF(A274="OTRO", 15, "")))))) -> 15 | I274: =IF(AND(F274<>"", J274<>""), NETWORKDAYS(TODAY(), J274-1, FESTIVOS!A$1:A$55), "") -> -60 | J274: =IF(AND(F274<>"", H274<>""), WORKDAY(F274, H274, FESTIVOS!A$1:A$55), "") -> 46094 | K274: LAURA GIRALDO | L274: =IF(I274="", "", MAX(0, I274 - (TODAY() - TODAY()))) -> 0 | M274: =IF(OR(I274="", H274=""), "", IF(I274<0, "Vencido", IF(I274>(H274/2), "Supere la mitad", "Bajo la mitad"))) -> Vencido | N274: CE-GC-0328 | O274: NO FIRMADO
A275: OTRO | B275: MAYRA ARTUNDUAGA | C275: ESAC | D275: DESAFILIACIÓN | E275: 274 | F275: 46073 | G275: COMERCIAL | H275: =IF(A275="INFORMACIÓN O DOCUMENTOS", 10, IF(A275="CONSULTA", 30, IF(A275="FACTURACIÓN Y COBROS", 15, IF(A275="VINCULACIÓN Y DESVINCULACIÓN", 15, IF(A275="NO ES DE NUESTRA COMPETENCIA", 5, IF(A275="OTRO", 15, "")))))) -> 15 | I275: =IF(AND(F275<>"", J275<>""), NETWORKDAYS(TODAY(), J275-1, FESTIVOS!A$1:A$55), "") -> -60 | J275: =IF(AND(F275<>"", H275<>""), WORKDAY(F275, H275, FESTIVOS!A$1:A$55), "") -> 46094 | K275: LAURA GIRALDO | L275: =IF(I275="", "", MAX(0, I275 - (TODAY() - TODAY()))) -> 0 | M275: =IF(OR(I275="", H275=""), "", IF(I275<0, "Vencido", IF(I275>(H275/2), "Supere la mitad", "Bajo la mitad"))) -> Vencido | N275: CE-GC-0329 | O275: NO FIRMADO
A276: OTRO | B276: MAYRA ARTUNDUAGA | C276: ESAC | D276: DESAFILIACIÓN | E276: 275 | F276: 46073 | G276: COMERCIAL | H276: =IF(A276="INFORMACIÓN O DOCUMENTOS", 10, IF(A276="CONSULTA", 30, IF(A276="FACTURACIÓN Y COBROS", 15, IF(A276="VINCULACIÓN Y DESVINCULACIÓN", 15, IF(A276="NO ES DE NUESTRA COMPETENCIA", 5, IF(A276="OTRO", 15, "")))))) -> 15 | I276: =IF(AND(F276<>"", J276<>""), NETWORKDAYS(TODAY(), J276-1, FESTIVOS!A$1:A$55), "") -> -60 | J276: =IF(AND(F276<>"", H276<>""), WORKDAY(F276, H276, FESTIVOS!A$1:A$55), "") -> 46094 | K276: LAURA GIRALDO | L276: =IF(I276="", "", MAX(0, I276 - (TODAY() - TODAY()))) -> 0 | M276: =IF(OR(I276="", H276=""), "", IF(I276<0, "Vencido", IF(I276>(H276/2), "Supere la mitad", "Bajo la mitad"))) -> Vencido | N276: CE-GC-0330 | O276: 46095
A277: OTRO | B277: MAYRA ARTUNDUAGA | C277: ESAC | D277: DESAFILIACIÓN | E277: 276 | F277: 46073 | G277: COMERCIAL | H277: =IF(A277="INFORMACIÓN O DOCUMENTOS", 10, IF(A277="CONSULTA", 30, IF(A277="FACTURACIÓN Y COBROS", 15, IF(A277="VINCULACIÓN Y DESVINCULACIÓN", 15, IF(A277="NO ES DE NUESTRA COMPETENCIA", 5, IF(A277="OTRO", 15, "")))))) -> 15 | I277: =IF(AND(F277<>"", J277<>""), NETWORKDAYS(TODAY(), J277-1, FESTIVOS!A$1:A$55), "") -> -60 | J277: =IF(AND(F277<>"", H277<>""), WORKDAY(F277, H277, FESTIVOS!A$1:A$55), "") -> 46094 | K277: LAURA GIRALDO | L277: =IF(I277="", "", MAX(0, I277 - (TODAY() - TODAY()))) -> 0 | M277: =IF(OR(I277="", H277=""), "", IF(I277<0, "Vencido", IF(I277>(H277/2), "Supere la mitad", "Bajo la mitad"))) -> Vencido | N277: CE-GC-0331 | O277: 46085
A278: OTRO | B278: MAYRA ARTUNDUAGA | C278: ESAC | D278: DESAFILIACIÓN | E278: 277 | F278: 46073 | G278: COMERCIAL | H278: =IF(A278="INFORMACIÓN O DOCUMENTOS", 10, IF(A278="CONSULTA", 30, IF(A278="FACTURACIÓN Y COBROS", 15, IF(A278="VINCULACIÓN Y DESVINCULACIÓN", 15, IF(A278="NO ES DE NUESTRA COMPETENCIA", 5, IF(A278="OTRO", 15, "")))))) -> 15 | I278: =IF(AND(F278<>"", J278<>""), NETWORKDAYS(TODAY(), J278-1, FESTIVOS!A$1:A$55), "") -> -60 | J278: =IF(AND(F278<>"", H278<>""), WORKDAY(F278, H278, FESTIVOS!A$1:A$55), "") -> 46094 | K278: LAURA GIRALDO | L278: =IF(I278="", "", MAX(0, I278 - (TODAY() - TODAY()))) -> 0 | M278: =IF(OR(I278="", H278=""), "", IF(I278<0, "Vencido", IF(I278>(H278/2), "Supere la mitad", "Bajo la mitad"))) -> Vencido | N278: CE-GC-0332 | O278: NO FIRMADO
A279: OTRO | B279: Luis Eduardo Guevara Joven | C279: USUARIO DE SERVINTEGRAL | D279: DERECHO DE PETICIÓN | E279: 278 | F279: 46073 | G279: COMERCIAL | H279: =IF(A279="INFORMACIÓN O DOCUMENTOS", 10, IF(A279="CONSULTA", 30, IF(A279="FACTURACIÓN Y COBROS", 15, IF(A279="VINCULACIÓN Y DESVINCULACIÓN", 15, IF(A279="NO ES DE NUESTRA COMPETENCIA", 5, IF(A279="OTRO", 15, "")))))) -> 15 | I279: =IF(AND(F279<>"", J279<>""), NETWORKDAYS(TODAY(), J279-1, FESTIVOS!A$1:A$55), "") -> -60 | J279: =IF(AND(F279<>"", H279<>""), WORKDAY(F279, H279, FESTIVOS!A$1:A$55), "") -> 46094 | K279: LAURA GIRALDO | L279: =IF(I279="", "", MAX(0, I279 - (TODAY() - TODAY()))) -> 0 | M279: =IF(OR(I279="", H279=""), "", IF(I279<0, "Vencido", IF(I279>(H279/2), "Supere la mitad", "Bajo la mitad"))) -> Vencido | N279: CE-GC-0323 | O279: 46090
A280: OTRO | B280: MAYRA ARTUNDUAGA | C280: ESAC | D280: DESAFILIACIÓN | E280: 279 | F280: 46073 | G280: COMERCIAL | H280: =IF(A280="INFORMACIÓN O DOCUMENTOS", 10, IF(A280="CONSULTA", 30, IF(A280="FACTURACIÓN Y COBROS", 15, IF(A280="VINCULACIÓN Y DESVINCULACIÓN", 15, IF(A280="NO ES DE NUESTRA COMPETENCIA", 5, IF(A280="OTRO", 15, "")))))) -> 15 | I280: =IF(AND(F280<>"", J280<>""), NETWORKDAYS(TODAY(), J280-1, FESTIVOS!A$1:A$55), "") -> -60 | J280: =IF(AND(F280<>"", H280<>""), WORKDAY(F280, H280, FESTIVOS!A$1:A$55), "") -> 46094 | K280: LAURA GIRALDO | L280: =IF(I280="", "", MAX(0, I280 - (TODAY() - TODAY()))) -> 0 | M280: =IF(OR(I280="", H280=""), "", IF(I280<0, "Vencido", IF(I280>(H280/2), "Supere la mitad", "Bajo la mitad"))) -> Vencido | N280: CE-GC-0333 | O280: 46090
A281: OTRO | B281: ZAMORA ARISTIZABAL JHOHN | C281: USUARIO DE SERVINTEGRAL | D281: SOLIICTUD DE APOYO | E281: 280 | F281: 46073 | G281: COMERCIAL | H281: =IF(A281="INFORMACIÓN O DOCUMENTOS", 10, IF(A281="CONSULTA", 30, IF(A281="FACTURACIÓN Y COBROS", 15, IF(A281="VINCULACIÓN Y DESVINCULACIÓN", 15, IF(A281="NO ES DE NUESTRA COMPETENCIA", 5, IF(A281="OTRO", 15, "")))))) -> 15 | I281: =IF(AND(F281<>"", J281<>""), NETWORKDAYS(TODAY(), J281-1, FESTIVOS!A$1:A$55), "") -> -60 | J281: =IF(AND(F281<>"", H281<>""), WORKDAY(F281, H281, FESTIVOS!A$1:A$55), "") -> 46094 | K281: LAURA GIRALDO | L281: =IF(I281="", "", MAX(0, I281 - (TODAY() - TODAY()))) -> 0 | M281: =IF(OR(I281="", H281=""), "", IF(I281<0, "Vencido", IF(I281>(H281/2), "Supere la mitad", "Bajo la mitad"))) -> Vencido | N281: CE-GC-0400 | O281: 46094
A282: OTRO | B282: BELISARIO MONTOYA | C282: USUARIO DE SERVINTEGRAL | D282: SOLICITUD DE VISITA | E282: 281 | F282: 46076 | G282: RESIDUOS | H282: =IF(A282="INFORMACIÓN O DOCUMENTOS", 10, IF(A282="CONSULTA", 30, IF(A282="FACTURACIÓN Y COBROS", 15, IF(A282="VINCULACIÓN Y DESVINCULACIÓN", 15, IF(A282="NO ES DE NUESTRA COMPETENCIA", 5, IF(A282="OTRO", 15, "")))))) -> 15 | I282: =IF(AND(F282<>"", J282<>""), NETWORKDAYS(TODAY(), J282-1, FESTIVOS!A$1:A$55), "") -> -58 | J282: =IF(AND(F282<>"", H282<>""), WORKDAY(F282, H282, FESTIVOS!A$1:A$55), "") -> 46097 | K282: LAURA GIRALDO | L282: =IF(I282="", "", MAX(0, I282 - (TODAY() - TODAY()))) -> 0 | M282: =IF(OR(I282="", H282=""), "", IF(I282<0, "Vencido", IF(I282>(H282/2), "Supere la mitad", "Bajo la mitad"))) -> Vencido | N282: CE-GR-0290 | O282: 46080
A283: OTRO | B283: CARLOS ESCOBAR | C283: USUARIO DE SERVINTEGRAL | D283: DERECHO DE PETICIÓN | E283: 282 | F283: 46076 | G283: COMERCIAL | H283: =IF(A283="INFORMACIÓN O DOCUMENTOS", 10, IF(A283="CONSULTA", 30, IF(A283="FACTURACIÓN Y COBROS", 15, IF(A283="VINCULACIÓN Y DESVINCULACIÓN", 15, IF(A283="NO ES DE NUESTRA COMPETENCIA", 5, IF(A283="OTRO", 15, "")))))) -> 15 | I283: =IF(AND(F283<>"", J283<>""), NETWORKDAYS(TODAY(), J283-1, FESTIVOS!A$1:A$55), "") -> -58 | J283: =IF(AND(F283<>"", H283<>""), WORKDAY(F283, H283, FESTIVOS!A$1:A$55), "") -> 46097 | K283: LAURA GIRALDO | L283: =IF(I283="", "", MAX(0, I283 - (TODAY() - TODAY()))) -> 0 | M283: =IF(OR(I283="", H283=""), "", IF(I283<0, "Vencido", IF(I283>(H283/2), "Supere la mitad", "Bajo la mitad"))) -> Vencido | N283: CE-GC-0279 | O283: 46086
A284: OTRO | B284: ANDRES FELIPE CABRERA | C284: USUARIO DE SERVINTEGRAL | D284: COTIZACIÓN | E284: 283 | F284: 46076 | G284: COMERCIAL | H284: =IF(A284="INFORMACIÓN O DOCUMENTOS", 10, IF(A284="CONSULTA", 30, IF(A284="FACTURACIÓN Y COBROS", 15, IF(A284="VINCULACIÓN Y DESVINCULACIÓN", 15, IF(A284="NO ES DE NUESTRA COMPETENCIA", 5, IF(A284="OTRO", 15, "")))))) -> 15 | I284: =IF(AND(F284<>"", J284<>""), NETWORKDAYS(TODAY(), J284-1, FESTIVOS!A$1:A$55), "") -> -58 | J284: =IF(AND(F284<>"", H284<>""), WORKDAY(F284, H284, FESTIVOS!A$1:A$55), "") -> 46097 | K284: LAURA GIRALDO | L284: =IF(I284="", "", MAX(0, I284 - (TODAY() - TODAY()))) -> 0 | M284: =IF(OR(I284="", H284=""), "", IF(I284<0, "Vencido", IF(I284>(H284/2), "Supere la mitad", "Bajo la mitad"))) -> Vencido | N284: CE-GC-0291 | O284: 46079 | P284: =IF(OR(O284="", J284=""), "", NETWORKDAYS(J284, O284, FESTIVOS!A283:A337)) -> -13
A285: OTRO | B285: CINDY VANESSA CONTRERAS ZAMBRANO | C285: USUARIO DE SERVINTEGRAL | D285: Invitación a capacitación gratuita “Reglamento Interno de Trabajo” | E285: 284 | F285: 46076 | G285: TALENTO HUMANO | H285: =IF(A285="INFORMACIÓN O DOCUMENTOS", 10, IF(A285="CONSULTA", 30, IF(A285="FACTURACIÓN Y COBROS", 15, IF(A285="VINCULACIÓN Y DESVINCULACIÓN", 15, IF(A285="NO ES DE NUESTRA COMPETENCIA", 5, IF(A285="OTRO", 15, "")))))) -> 15 | I285: =IF(AND(F285<>"", J285<>""), NETWORKDAYS(TODAY(), J285-1, FESTIVOS!A$1:A$55), "") -> -58 | J285: =IF(AND(F285<>"", H285<>""), WORKDAY(F285, H285, FESTIVOS!A$1:A$55), "") -> 46097 | K285: LAURA GIRALDO | L285: =IF(I285="", "", MAX(0, I285 - (TODAY() - TODAY()))) -> 0 | M285: =IF(OR(I285="", H285=""), "", IF(I285<0, "Vencido", IF(I285>(H285/2), "Supere la mitad", "Bajo la mitad"))) -> Vencido | N285: NO REQUIERE RESPUESTA | P285: =IF(OR(O285="", J285=""), "", NETWORKDAYS(J285, O285, FESTIVOS!A284:A338))
A286: OTRO | B286: WILSON BECERRA | C286: USUARIO DE SERVINTEGRAL | D286: SOLICITUD PUERTA A PUERTA | E286: 285 | F286: 46076 | G286: RESIDUOS | H286: =IF(A286="INFORMACIÓN O DOCUMENTOS", 10, IF(A286="CONSULTA", 30, IF(A286="FACTURACIÓN Y COBROS", 15, IF(A286="VINCULACIÓN Y DESVINCULACIÓN", 15, IF(A286="NO ES DE NUESTRA COMPETENCIA", 5, IF(A286="OTRO", 15, "")))))) -> 15 | I286: =IF(AND(F286<>"", J286<>""), NETWORKDAYS(TODAY(), J286-1, FESTIVOS!A$1:A$55), "") -> -58 | J286: =IF(AND(F286<>"", H286<>""), WORKDAY(F286, H286, FESTIVOS!A$1:A$55), "") -> 46097 | K286: LAURA GIRALDO | L286: =IF(I286="", "", MAX(0, I286 - (TODAY() - TODAY()))) -> 0 | M286: =IF(OR(I286="", H286=""), "", IF(I286<0, "Vencido", IF(I286>(H286/2), "Supere la mitad", "Bajo la mitad"))) -> Vencido | N286: CE-GR-0352 | O286: 46094 | P286: =IF(OR(O286="", J286=""), "", NETWORKDAYS(J286, O286, FESTIVOS!A285:A339)) -> -2
A287: OTRO | B287: Vilma Socorro Luengas | C287: USUARIO DE SERVINTEGRAL | D287: Petición respetuosa | E287: 286 | F287: 46076 | H287: =IF(A287="INFORMACIÓN O DOCUMENTOS", 10, IF(A287="CONSULTA", 30, IF(A287="FACTURACIÓN Y COBROS", 15, IF(A287="VINCULACIÓN Y DESVINCULACIÓN", 15, IF(A287="NO ES DE NUESTRA COMPETENCIA", 5, IF(A287="OTRO", 15, "")))))) -> 15 | I287: =IF(AND(F287<>"", J287<>""), NETWORKDAYS(TODAY(), J287-1, FESTIVOS!A$1:A$55), "") -> -58 | J287: =IF(AND(F287<>"", H287<>""), WORKDAY(F287, H287, FESTIVOS!A$1:A$55), "") -> 46097 | K287: LAURA GIRALDO | L287: =IF(I287="", "", MAX(0, I287 - (TODAY() - TODAY()))) -> 0 | M287: =IF(OR(I287="", H287=""), "", IF(I287<0, "Vencido", IF(I287>(H287/2), "Supere la mitad", "Bajo la mitad"))) -> Vencido | N287: CE-GR-0295 | O287: 46079 | P287: =IF(OR(O287="", J287=""), "", NETWORKDAYS(J287, O287, FESTIVOS!A286:A340)) -> -13
A288: OTRO | B288: Iván Alexander Ribon Castillo | C288: USUARIO DE SERVINTEGRAL | D288: CITACION A VALORACION # 1 Y TESTIGO 94043507 MARIANO OSWALDO ROJAS ARANGO | E288: 287 | F288: 46076 | G288: TALENTO HUMANO | H288: =IF(A288="INFORMACIÓN O DOCUMENTOS", 10, IF(A288="CONSULTA", 30, IF(A288="FACTURACIÓN Y COBROS", 15, IF(A288="VINCULACIÓN Y DESVINCULACIÓN", 15, IF(A288="NO ES DE NUESTRA COMPETENCIA", 5, IF(A288="OTRO", 15, "")))))) -> 15 | I288: =IF(AND(F288<>"", J288<>""), NETWORKDAYS(TODAY(), J288-1, FESTIVOS!A$1:A$55), "") -> -58 | J288: =IF(AND(F288<>"", H288<>""), WORKDAY(F288, H288, FESTIVOS!A$1:A$55), "") -> 46097 | K288: LAURA GIRALDO | L288: =IF(I288="", "", MAX(0, I288 - (TODAY() - TODAY()))) -> 0 | N288: NO REQUIERE RESPUESTA | P288: =IF(OR(O288="", J288=""), "", NETWORKDAYS(J288, O288, FESTIVOS!A287:A341))
A289: OTRO | B289: LUZ DARY MURILLO GOMEZ | C289: ALCALDIA | D289: Solicitud de apoyo institucional - Estrategia grandes voluntarios | E289: 288 | F289: 46076 | G289: COMERCIAL | H289: =IF(A289="INFORMACIÓN O DOCUMENTOS", 10, IF(A289="CONSULTA", 30, IF(A289="FACTURACIÓN Y COBROS", 15, IF(A289="VINCULACIÓN Y DESVINCULACIÓN", 15, IF(A289="NO ES DE NUESTRA COMPETENCIA", 5, IF(A289="OTRO", 15, "")))))) -> 15 | I289: =IF(AND(F289<>"", J289<>""), NETWORKDAYS(TODAY(), J289-1, FESTIVOS!A$1:A$55), "") -> -58 | J289: =IF(AND(F289<>"", H289<>""), WORKDAY(F289, H289, FESTIVOS!A$1:A$55), "") -> 46097 | K289: LAURA GIRALDO | L289: =IF(I289="", "", MAX(0, I289 - (TODAY() - TODAY()))) -> 0 | M289: =IF(OR(I289="", H289=""), "", IF(I289<0, "Vencido", IF(I289>(H289/2), "Supere la mitad", "Bajo la mitad"))) -> Vencido | N289: CE-GC-0296 | O289: 46084 | P289: =IF(OR(O289="", J289=""), "", NETWORKDAYS(J289, O289, FESTIVOS!A288:A342)) -> -10
A290: OTRO | B290: CHRISTYAM CAMILO SALAZAR ROJAS | C290: ALCALDIA | D290: 200.09.116-106 Solicitud de apoyo institucional para la segunda jornada de limpieza, reforestación y cátedra ambiental en el Humedal El San Luis SERVINTEGRAL | E290: 289 | F290: 46076 | G290: COMERCIAL | H290: =IF(A290="INFORMACIÓN O DOCUMENTOS", 10, IF(A290="CONSULTA", 30, IF(A290="FACTURACIÓN Y COBROS", 15, IF(A290="VINCULACIÓN Y DESVINCULACIÓN", 15, IF(A290="NO ES DE NUESTRA COMPETENCIA", 5, IF(A290="OTRO", 15, "")))))) -> 15 | I290: =IF(AND(F290<>"", J290<>""), NETWORKDAYS(TODAY(), J290-1, FESTIVOS!A$1:A$55), "") -> -58 | J290: =IF(AND(F290<>"", H290<>""), WORKDAY(F290, H290, FESTIVOS!A$1:A$55), "") -> 46097 | K290: LAURA GIRALDO | L290: =IF(I290="", "", MAX(0, I290 - (TODAY() - TODAY()))) -> 0 | M290: =IF(OR(I290="", H290=""), "", IF(I290<0, "Vencido", IF(I290>(H290/2), "Supere la mitad", "Bajo la mitad"))) -> Vencido | N290: CE-GC-0362 | O290: 46097 | P290: =IF(OR(O290="", J290=""), "", NETWORKDAYS(J290, O290, FESTIVOS!A289:A343)) -> 1
A291: OTRO | B291: SERGIO POLANIA | C291: USUARIO DE SERVINTEGRAL | D291: SOLICITUD DE CERTIFICADO | E291: 290 | F291: 46076 | G291: COMERCIAL | H291: =IF(A291="INFORMACIÓN O DOCUMENTOS", 10, IF(A291="CONSULTA", 30, IF(A291="FACTURACIÓN Y COBROS", 15, IF(A291="VINCULACIÓN Y DESVINCULACIÓN", 15, IF(A291="NO ES DE NUESTRA COMPETENCIA", 5, IF(A291="OTRO", 15, "")))))) -> 15 | I291: =IF(AND(F291<>"", J291<>""), NETWORKDAYS(TODAY(), J291-1, FESTIVOS!A$1:A$55), "") -> -58 | J291: =IF(AND(F291<>"", H291<>""), WORKDAY(F291, H291, FESTIVOS!A$1:A$55), "") -> 46097 | K291: LAURA GIRALDO | L291: =IF(I291="", "", MAX(0, I291 - (TODAY() - TODAY()))) -> 0 | M291: =IF(OR(I291="", H291=""), "", IF(I291<0, "Vencido", IF(I291>(H291/2), "Supere la mitad", "Bajo la mitad"))) -> Vencido | N291: CE-GC-0316 | O291: 46085 | P291: =IF(OR(O291="", J291=""), "", NETWORKDAYS(J291, O291, FESTIVOS!A290:A344)) -> -9
A292: OTRO | B292: DISTRICARNES EL GRAN NOVILLO | C292: USUARIO DE SERVINTEGRAL | D292: SOLICITUD CERTIFICADO PRESTACION DEL SERVICIO DE ASEO | E292: 291 | F292: 46077 | G292: COMERCIAL | H292: =IF(A292="INFORMACIÓN O DOCUMENTOS", 10, IF(A292="CONSULTA", 30, IF(A292="FACTURACIÓN Y COBROS", 15, IF(A292="VINCULACIÓN Y DESVINCULACIÓN", 15, IF(A292="NO ES DE NUESTRA COMPETENCIA", 5, IF(A292="OTRO", 15, "")))))) -> 15 | I292: =IF(AND(F292<>"", J292<>""), NETWORKDAYS(TODAY(), J292-1, FESTIVOS!A$1:A$55), "") -> -58 | J292: =IF(AND(F292<>"", H292<>""), WORKDAY(F292, H292, FESTIVOS!A$1:A$55), "") -> 46098 | K292: LAURA GIRALDO | L292: =IF(I292="", "", MAX(0, I292 - (TODAY() - TODAY()))) -> 0 | M292: =IF(OR(I292="", H292=""), "", IF(I292<0, "Vencido", IF(I292>(H292/2), "Supere la mitad", "Bajo la mitad"))) -> Vencido | N292: CE-GC-0297 | O292: 46079 | P292: =IF(OR(O292="", J292=""), "", NETWORKDAYS(J292, O292, FESTIVOS!A291:A345)) -> -14
A293: OTRO | B293: KARLA JOHANA LISCANO CORREA | C293: ALCALDIA | D293: Convocatoria Comité de Conocimiento del Riesgo | E293: 292 | F293: 46077 | G293: COMERCIAL | H293: =IF(A293="INFORMACIÓN O DOCUMENTOS", 10, IF(A293="CONSULTA", 30, IF(A293="FACTURACIÓN Y COBROS", 15, IF(A293="VINCULACIÓN Y DESVINCULACIÓN", 15, IF(A293="NO ES DE NUESTRA COMPETENCIA", 5, IF(A293="OTRO", 15, "")))))) -> 15 | I293: =IF(AND(F293<>"", J293<>""), NETWORKDAYS(TODAY(), J293-1, FESTIVOS!A$1:A$55), "") -> -58 | J293: =IF(AND(F293<>"", H293<>""), WORKDAY(F293, H293, FESTIVOS!A$1:A$55), "") -> 46098 | K293: LAURA GIRALDO | L293: =IF(I293="", "", MAX(0, I293 - (TODAY() - TODAY()))) -> 0 | M293: =IF(OR(I293="", H293=""), "", IF(I293<0, "Vencido", IF(I293>(H293/2), "Supere la mitad", "Bajo la mitad"))) -> Vencido | N293: CE-GC-0267 | O293: 46094 | P293: =IF(OR(O293="", J293=""), "", NETWORKDAYS(J293, O293, FESTIVOS!A292:A346)) -> -3
A294: OTRO | B294: Euler Alexander Paniagua Zambrano | C294: USUARIO DE SERVINTEGRAL | D294: Solicitud de Apoyo para limpieza en sector Caseta Comunal del barrio El Lenin | E294: 293 | F294: 46077 | G294: COMERCIAL | H294: =IF(A294="INFORMACIÓN O DOCUMENTOS", 10, IF(A294="CONSULTA", 30, IF(A294="FACTURACIÓN Y COBROS", 15, IF(A294="VINCULACIÓN Y DESVINCULACIÓN", 15, IF(A294="NO ES DE NUESTRA COMPETENCIA", 5, IF(A294="OTRO", 15, "")))))) -> 15 | I294: =IF(AND(F294<>"", J294<>""), NETWORKDAYS(TODAY(), J294-1, FESTIVOS!A$1:A$55), "") -> -58 | J294: =IF(AND(F294<>"", H294<>""), WORKDAY(F294, H294, FESTIVOS!A$1:A$55), "") -> 46098 | K294: LAURA GIRALDO | L294: =IF(I294="", "", MAX(0, I294 - (TODAY() - TODAY()))) -> 0 | M294: =IF(OR(I294="", H294=""), "", IF(I294<0, "Vencido", IF(I294>(H294/2), "Supere la mitad", "Bajo la mitad"))) -> Vencido | N294: CE-GC-0346 | O294: 46098 | P294: =IF(OR(O294="", J294=""), "", NETWORKDAYS(J294, O294, FESTIVOS!A293:A347)) -> 1
A295: OTRO | B295: HEBERTH TOBAR VEGA | C295: USUARIO DE SERVINTEGRAL | D295: Petición para la Instalación de Contenedor de Residuos Sólidos en la carrera 9 NO.8C-87 Barrio La Estrella | E295: 294 | F295: 46077 | G295: COMERCIAL | H295: =IF(A295="INFORMACIÓN O DOCUMENTOS", 10, IF(A295="CONSULTA", 30, IF(A295="FACTURACIÓN Y COBROS", 15, IF(A295="VINCULACIÓN Y DESVINCULACIÓN", 15, IF(A295="NO ES DE NUESTRA COMPETENCIA", 5, IF(A295="OTRO", 15, "")))))) -> 15 | I295: =IF(AND(F295<>"", J295<>""), NETWORKDAYS(TODAY(), J295-1, FESTIVOS!A$1:A$55), "") -> -58 | J295: =IF(AND(F295<>"", H295<>""), WORKDAY(F295, H295, FESTIVOS!A$1:A$55), "") -> 46098 | K295: LAURA GIRALDO | L295: =IF(I295="", "", MAX(0, I295 - (TODAY() - TODAY()))) -> 0 | M295: =IF(OR(I295="", H295=""), "", IF(I295<0, "Vencido", IF(I295>(H295/2), "Supere la mitad", "Bajo la mitad"))) -> Vencido | N295: CE-GC-0305 | O295: 46097 | P295: =IF(OR(O295="", J295=""), "", NETWORKDAYS(J295, O295, FESTIVOS!A294:A348)) -> -2
A296: OTRO | B296: CARLOS ESCOBAR | C296: USUARIO DE SERVINTEGRAL | D296: DERECHO DE PETICIÓN | E296: 295 | F296: 46078 | G296: COMERCIAL | H296: =IF(A296="INFORMACIÓN O DOCUMENTOS", 10, IF(A296="CONSULTA", 30, IF(A296="FACTURACIÓN Y COBROS", 15, IF(A296="VINCULACIÓN Y DESVINCULACIÓN", 15, IF(A296="NO ES DE NUESTRA COMPETENCIA", 5, IF(A296="OTRO", 15, "")))))) -> 15 | I296: =IF(AND(F296<>"", J296<>""), NETWORKDAYS(TODAY(), J296-1, FESTIVOS!A$1:A$55), "") -> -57 | J296: =IF(AND(F296<>"", H296<>""), WORKDAY(F296, H296, FESTIVOS!A$1:A$55), "") -> 46099 | K296: LAURA GIRALDO | L296: =IF(I296="", "", MAX(0, I296 - (TODAY() - TODAY()))) -> 0 | M296: =IF(OR(I296="", H296=""), "", IF(I296<0, "Vencido", IF(I296>(H296/2), "Supere la mitad", "Bajo la mitad"))) -> Vencido | N296: CE-GC-0279 | O296: 46086 | P296: =IF(OR(O296="", J296=""), "", NETWORKDAYS(J296, O296, FESTIVOS!A295:A349)) -> -10
A297: OTRO | B297: MARIA FERNANDA JARAMILLO TRUJILLO | C297: SUPER | D297: Remisión memorias mesa de trabajo de fecha 29 de enero de 2026 | E297: 296 | F297: 46078 | G297: JURÍDICA | H297: =IF(A297="INFORMACIÓN O DOCUMENTOS", 10, IF(A297="CONSULTA", 30, IF(A297="FACTURACIÓN Y COBROS", 15, IF(A297="VINCULACIÓN Y DESVINCULACIÓN", 15, IF(A297="NO ES DE NUESTRA COMPETENCIA", 5, IF(A297="OTRO", 15, "")))))) -> 15 | I297: =IF(AND(F297<>"", J297<>""), NETWORKDAYS(TODAY(), J297-1, FESTIVOS!A$1:A$55), "") -> -57 | J297: =IF(AND(F297<>"", H297<>""), WORKDAY(F297, H297, FESTIVOS!A$1:A$55), "") -> 46099 | K297: LAURA GIRALDO | L297: =IF(I297="", "", MAX(0, I297 - (TODAY() - TODAY()))) -> 0 | M297: =IF(OR(I297="", H297=""), "", IF(I297<0, "Vencido", IF(I297>(H297/2), "Supere la mitad", "Bajo la mitad"))) -> Vencido | N297: CE-GC-0033 | O297: 46036 | P297: =IF(OR(O297="", J297=""), "", NETWORKDAYS(J297, O297, FESTIVOS!A296:A350)) -> -46
A298: OTRO | B298: LINA PATRICIA MEJIA ROJAS | C298: ALCALDIA | D298: Solicitud de apoyo para recolección de residuos verdes-SAN JUDAS | E298: 297 | F298: 46078 | G298: RESIDUOS | H298: =IF(A298="INFORMACIÓN O DOCUMENTOS", 10, IF(A298="CONSULTA", 30, IF(A298="FACTURACIÓN Y COBROS", 15, IF(A298="VINCULACIÓN Y DESVINCULACIÓN", 15, IF(A298="NO ES DE NUESTRA COMPETENCIA", 5, IF(A298="OTRO", 15, "")))))) -> 15 | I298: =IF(AND(F298<>"", J298<>""), NETWORKDAYS(TODAY(), J298-1, FESTIVOS!A$1:A$55), "") -> -57 | J298: =IF(AND(F298<>"", H298<>""), WORKDAY(F298, H298, FESTIVOS!A$1:A$55), "") -> 46099 | K298: LAURA GIRALDO | L298: =IF(I298="", "", MAX(0, I298 - (TODAY() - TODAY()))) -> 0 | M298: =IF(OR(I298="", H298=""), "", IF(I298<0, "Vencido", IF(I298>(H298/2), "Supere la mitad", "Bajo la mitad"))) -> Vencido | N298: CE-GR-0301 | O298: 46084 | P298: =IF(OR(O298="", J298=""), "", NETWORKDAYS(J298, O298, FESTIVOS!A297:A351)) -> -12
A299: OTRO | B299: BEATRIZ ELENA GUTIERREZ | C299: USUARIO DE SERVINTEGRAL | D299: ACCIÓN DE TUTELA | E299: 298 | F299: 46078 | G299: COMERCIAL | H299: =IF(A299="INFORMACIÓN O DOCUMENTOS", 10, IF(A299="CONSULTA", 30, IF(A299="FACTURACIÓN Y COBROS", 15, IF(A299="VINCULACIÓN Y DESVINCULACIÓN", 15, IF(A299="NO ES DE NUESTRA COMPETENCIA", 5, IF(A299="OTRO", 15, "")))))) -> 15 | I299: =IF(AND(F299<>"", J299<>""), NETWORKDAYS(TODAY(), J299-1, FESTIVOS!A$1:A$55), "") -> -57 | J299: =IF(AND(F299<>"", H299<>""), WORKDAY(F299, H299, FESTIVOS!A$1:A$55), "") -> 46099 | K299: LAURA GIRALDO | L299: =IF(I299="", "", MAX(0, I299 - (TODAY() - TODAY()))) -> 0 | M299: =IF(OR(I299="", H299=""), "", IF(I299<0, "Vencido", IF(I299>(H299/2), "Supere la mitad", "Bajo la mitad"))) -> Vencido | N299: NO REQUIERE RESPUESTA
A300: OTRO | B300: ILIANA ROJAS | C300: USUARIO DE SERVINTEGRAL | D300: SOLICITUD DE APOYO INSTITUCIONAL | E300: 299 | F300: 46078 | G300: COMERCIAL | H300: =IF(A300="INFORMACIÓN O DOCUMENTOS", 10, IF(A300="CONSULTA", 30, IF(A300="FACTURACIÓN Y COBROS", 15, IF(A300="VINCULACIÓN Y DESVINCULACIÓN", 15, IF(A300="NO ES DE NUESTRA COMPETENCIA", 5, IF(A300="OTRO", 15, "")))))) -> 15 | I300: =IF(AND(F300<>"", J300<>""), NETWORKDAYS(TODAY(), J300-1, FESTIVOS!A$1:A$55), "") -> -57 | J300: =IF(AND(F300<>"", H300<>""), WORKDAY(F300, H300, FESTIVOS!A$1:A$55), "") -> 46099 | K300: LAURA GIRALDO | L300: =IF(I300="", "", MAX(0, I300 - (TODAY() - TODAY()))) -> 0 | M300: =IF(OR(I300="", H300=""), "", IF(I300<0, "Vencido", IF(I300>(H300/2), "Supere la mitad", "Bajo la mitad"))) -> Vencido | N300: CE- GC-0403 | O300: 46105 | P300: =IF(OR(O300="", J300=""), "", NETWORKDAYS(J300, O300, FESTIVOS!A299:A353)) -> 5
A301: OTRO | B301: MAIBRY LIZETH CALDERON | C301: USUARIO DE SERVINTEGRAL | D301: SOLICITUD DE CERTIFICACIÓN | E301: 300 | F301: 46078 | G301: COMERCIAL | H301: =IF(A301="INFORMACIÓN O DOCUMENTOS", 10, IF(A301="CONSULTA", 30, IF(A301="FACTURACIÓN Y COBROS", 15, IF(A301="VINCULACIÓN Y DESVINCULACIÓN", 15, IF(A301="NO ES DE NUESTRA COMPETENCIA", 5, IF(A301="OTRO", 15, "")))))) -> 15 | I301: =IF(AND(F301<>"", J301<>""), NETWORKDAYS(TODAY(), J301-1, FESTIVOS!A$1:A$55), "") -> -57 | J301: =IF(AND(F301<>"", H301<>""), WORKDAY(F301, H301, FESTIVOS!A$1:A$55), "") -> 46099 | K301: LAURA GIRALDO | L301: =IF(I301="", "", MAX(0, I301 - (TODAY() - TODAY()))) -> 0 | M301: =IF(OR(I301="", H301=""), "", IF(I301<0, "Vencido", IF(I301>(H301/2), "Supere la mitad", "Bajo la mitad"))) -> Vencido | N301: CE-GC-0350 | O301: 46097 | P301: =IF(OR(O301="", J301=""), "", NETWORKDAYS(J301, O301, FESTIVOS!A300:A354)) -> -3
A302: OTRO | B302: ARLEY CAICEDO | C302: USUARIO DE SERVINTEGRAL | D302: SOLICITUD DE APOYO PARA CORTE DE ARBOLES | E302: 301 | F302: 46078 | G302: RESIDUOS | H302: =IF(A302="INFORMACIÓN O DOCUMENTOS", 10, IF(A302="CONSULTA", 30, IF(A302="FACTURACIÓN Y COBROS", 15, IF(A302="VINCULACIÓN Y DESVINCULACIÓN", 15, IF(A302="NO ES DE NUESTRA COMPETENCIA", 5, IF(A302="OTRO", 15, "")))))) -> 15 | I302: =IF(AND(F302<>"", J302<>""), NETWORKDAYS(TODAY(), J302-1, FESTIVOS!A$1:A$55), "") -> -57 | J302: =IF(AND(F302<>"", H302<>""), WORKDAY(F302, H302, FESTIVOS!A$1:A$55), "") -> 46099 | K302: LAURA GIRALDO | L302: =IF(I302="", "", MAX(0, I302 - (TODAY() - TODAY()))) -> 0 | M302: =IF(OR(I302="", H302=""), "", IF(I302<0, "Vencido", IF(I302>(H302/2), "Supere la mitad", "Bajo la mitad"))) -> Vencido | N302: CE-GR-0302 | O302: 46084 | P302: =IF(OR(O302="", J302=""), "", NETWORKDAYS(J302, O302, FESTIVOS!A301:A355)) -> -12
A303: OTRO | B303: HERMILA CABRERA | C303: USUARIO DE SERVINTEGRAL | D303: SOLICITUD DE CERTIFICADO | E303: 302 | F303: 46079 | G303: COMERCIAL | H303: =IF(A303="INFORMACIÓN O DOCUMENTOS", 10, IF(A303="CONSULTA", 30, IF(A303="FACTURACIÓN Y COBROS", 15, IF(A303="VINCULACIÓN Y DESVINCULACIÓN", 15, IF(A303="NO ES DE NUESTRA COMPETENCIA", 5, IF(A303="OTRO", 15, "")))))) -> 15 | I303: =IF(AND(F303<>"", J303<>""), NETWORKDAYS(TODAY(), J303-1, FESTIVOS!A$1:A$55), "") -> -56 | J303: =IF(AND(F303<>"", H303<>""), WORKDAY(F303, H303, FESTIVOS!A$1:A$55), "") -> 46100 | K303: LAURA GIRALDO | L303: =IF(I303="", "", MAX(0, I303 - (TODAY() - TODAY()))) -> 0 | M303: =IF(OR(I303="", H303=""), "", IF(I303<0, "Vencido", IF(I303>(H303/2), "Supere la mitad", "Bajo la mitad"))) -> Vencido | N303: CE-GC-0371 | O303: 46097 | P303: =IF(OR(O303="", J303=""), "", NETWORKDAYS(J303, O303, FESTIVOS!A302:A356)) -> -4
A304: OTRO | B304: JORGE CABRERA | C304: USUARIO DE SERVINTEGRAL | D304: DESCUENTO EN LA DEUDA DE ASEO | E304: 303 | F304: 46079 | G304: COMERCIAL | H304: =IF(A304="INFORMACIÓN O DOCUMENTOS", 10, IF(A304="CONSULTA", 30, IF(A304="FACTURACIÓN Y COBROS", 15, IF(A304="VINCULACIÓN Y DESVINCULACIÓN", 15, IF(A304="NO ES DE NUESTRA COMPETENCIA", 5, IF(A304="OTRO", 15, "")))))) -> 15 | I304: =IF(AND(F304<>"", J304<>""), NETWORKDAYS(TODAY(), J304-1, FESTIVOS!A$1:A$55), "") -> -56 | J304: =IF(AND(F304<>"", H304<>""), WORKDAY(F304, H304, FESTIVOS!A$1:A$55), "") -> 46100 | K304: LAURA GIRALDO | L304: =IF(I304="", "", MAX(0, I304 - (TODAY() - TODAY()))) -> 0 | M304: =IF(OR(I304="", H304=""), "", IF(I304<0, "Vencido", IF(I304>(H304/2), "Supere la mitad", "Bajo la mitad"))) -> Vencido | N304: CE-GC-0317 | O304: 46094 | P304: =IF(OR(O304="", J304=""), "", NETWORKDAYS(J304, O304, FESTIVOS!A303:A357)) -> -5
A305: OTRO | B305: STELLA SANCHEZ GOMEZ | C305: USUARIO DE SERVINTEGRAL | D305: SOLICITUD DE COBRO DE 2 CONTADORES QUE NO SE ESTAN UTILIZANDO DE ENERGIA | E305: 304 | F305: 46079 | G305: COMERCIAL | H305: =IF(A305="INFORMACIÓN O DOCUMENTOS", 10, IF(A305="CONSULTA", 30, IF(A305="FACTURACIÓN Y COBROS", 15, IF(A305="VINCULACIÓN Y DESVINCULACIÓN", 15, IF(A305="NO ES DE NUESTRA COMPETENCIA", 5, IF(A305="OTRO", 15, "")))))) -> 15 | I305: =IF(AND(F305<>"", J305<>""), NETWORKDAYS(TODAY(), J305-1, FESTIVOS!A$1:A$55), "") -> -56 | J305: =IF(AND(F305<>"", H305<>""), WORKDAY(F305, H305, FESTIVOS!A$1:A$55), "") -> 46100 | K305: LAURA GIRALDO | L305: =IF(I305="", "", MAX(0, I305 - (TODAY() - TODAY()))) -> 0 | M305: =IF(OR(I305="", H305=""), "", IF(I305<0, "Vencido", IF(I305>(H305/2), "Supere la mitad", "Bajo la mitad"))) -> Vencido | N305: CE-GC-0464 | O305: 46100 | P305: =IF(OR(O305="", J305=""), "", NETWORKDAYS(J305, O305, FESTIVOS!A304:A358)) -> 1
A306: OTRO | B306: JUAN CICERY | C306: USUARIO DE SERVINTEGRAL | D306: SOLICITUD DE ENTREGA DE DOCUMENTOS | E306: 305 | F306: 46079 | G306: TALENTO HUMANO | H306: 10 | I306: =IF(AND(F306<>"", J306<>""), NETWORKDAYS(TODAY(), J306-1, FESTIVOS!A$1:A$55), "") -> -61 | J306: =IF(AND(F306<>"", H306<>""), WORKDAY(F306, H306, FESTIVOS!A$1:A$55), "") -> 46093 | K306: LAURA GIRALDO | L306: =IF(I306="", "", MAX(0, I306 - (TODAY() - TODAY()))) -> 0 | M306: =IF(OR(I306="", H306=""), "", IF(I306<0, "Vencido", IF(I306>(H306/2), "Supere la mitad", "Bajo la mitad"))) -> Vencido | N306: CE-GT-0382 | O306: 46093 | P306: =IF(OR(O306="", J306=""), "", NETWORKDAYS(J306, O306, FESTIVOS!A305:A359)) -> 1
A307: OTRO | B307: BELISARIO MONTOYA | C307: USUARIO DE SERVINTEGRAL | D307: SOLICITUD DE CONTENEDORES | E307: 306 | F307: 46079 | G307: COMERCIAL | H307: =IF(A307="INFORMACIÓN O DOCUMENTOS", 10, IF(A307="CONSULTA", 30, IF(A307="FACTURACIÓN Y COBROS", 15, IF(A307="VINCULACIÓN Y DESVINCULACIÓN", 15, IF(A307="NO ES DE NUESTRA COMPETENCIA", 5, IF(A307="OTRO", 15, "")))))) -> 15 | I307: =IF(AND(F307<>"", J307<>""), NETWORKDAYS(TODAY(), J307-1, FESTIVOS!A$1:A$55), "") -> -56 | J307: =IF(AND(F307<>"", H307<>""), WORKDAY(F307, H307, FESTIVOS!A$1:A$55), "") -> 46100 | K307: LAURA GIRALDO | L307: =IF(I307="", "", MAX(0, I307 - (TODAY() - TODAY()))) -> 0 | M307: =IF(OR(I307="", H307=""), "", IF(I307<0, "Vencido", IF(I307>(H307/2), "Supere la mitad", "Bajo la mitad"))) -> Vencido | N307: CE-GC-0355 | O307: 46099 | P307: =IF(OR(O307="", J307=""), "", NETWORKDAYS(J307, O307, FESTIVOS!A306:A360)) -> -2
A308: OTRO | B308: ALEXANDER FIERRO | C308: USUARIO DE SERVINTEGRAL | D308: PODA | E308: 307 | F308: 46079 | G308: RESIDUOS | H308: =IF(A308="INFORMACIÓN O DOCUMENTOS", 10, IF(A308="CONSULTA", 30, IF(A308="FACTURACIÓN Y COBROS", 15, IF(A308="VINCULACIÓN Y DESVINCULACIÓN", 15, IF(A308="NO ES DE NUESTRA COMPETENCIA", 5, IF(A308="OTRO", 15, "")))))) -> 15 | I308: =IF(AND(F308<>"", J308<>""), NETWORKDAYS(TODAY(), J308-1, FESTIVOS!A$1:A$55), "") -> -56 | J308: =IF(AND(F308<>"", H308<>""), WORKDAY(F308, H308, FESTIVOS!A$1:A$55), "") -> 46100 | K308: LAURA GIRALDO | L308: =IF(I308="", "", MAX(0, I308 - (TODAY() - TODAY()))) -> 0 | M308: =IF(OR(I308="", H308=""), "", IF(I308<0, "Vencido", IF(I308>(H308/2), "Supere la mitad", "Bajo la mitad"))) -> Vencido | N308: CE-GR-0310 | O308: 46084 | P308: =IF(OR(O308="", J308=""), "", NETWORKDAYS(J308, O308, FESTIVOS!A307:A361)) -> -13
A309: OTRO | B309: MAYRA ARTUNDUAGA | C309: ESAC | D309: Desafiliación | E309: 308 | F309: 46079 | G309: COMERCIAL | H309: =IF(A309="INFORMACIÓN O DOCUMENTOS", 10, IF(A309="CONSULTA", 30, IF(A309="FACTURACIÓN Y COBROS", 15, IF(A309="VINCULACIÓN Y DESVINCULACIÓN", 15, IF(A309="NO ES DE NUESTRA COMPETENCIA", 5, IF(A309="OTRO", 15, "")))))) -> 15 | I309: =IF(AND(F309<>"", J309<>""), NETWORKDAYS(TODAY(), J309-1, FESTIVOS!A$1:A$55), "") -> -56 | J309: =IF(AND(F309<>"", H309<>""), WORKDAY(F309, H309, FESTIVOS!A$1:A$55), "") -> 46100 | K309: LAURA GIRALDO | L309: =IF(I309="", "", MAX(0, I309 - (TODAY() - TODAY()))) -> 0 | M309: =IF(OR(I309="", H309=""), "", IF(I309<0, "Vencido", IF(I309>(H309/2), "Supere la mitad", "Bajo la mitad"))) -> Vencido | N309: CE-GC-0373 | O309: 46094 | P309: =IF(OR(O309="", J309=""), "", NETWORKDAYS(J309, O309, FESTIVOS!A308:A362)) -> -5
A310: OTRO | B310: ANDRES FELIPE CABRERA | C310: USUARIO DE SERVINTEGRAL | D310: COMPROBANTE DE PAGO Y SOLICITUD DE CERTIFICADO | E310: 309 | F310: 46079 | G310: COMERCIAL | H310: =IF(A310="INFORMACIÓN O DOCUMENTOS", 10, IF(A310="CONSULTA", 30, IF(A310="FACTURACIÓN Y COBROS", 15, IF(A310="VINCULACIÓN Y DESVINCULACIÓN", 15, IF(A310="NO ES DE NUESTRA COMPETENCIA", 5, IF(A310="OTRO", 15, "")))))) -> 15 | I310: =IF(AND(F310<>"", J310<>""), NETWORKDAYS(TODAY(), J310-1, FESTIVOS!A$1:A$55), "") -> -56 | J310: =IF(AND(F310<>"", H310<>""), WORKDAY(F310, H310, FESTIVOS!A$1:A$55), "") -> 46100 | K310: LAURA GIRALDO | L310: =IF(I310="", "", MAX(0, I310 - (TODAY() - TODAY()))) -> 0 | M310: =IF(OR(I310="", H310=""), "", IF(I310<0, "Vencido", IF(I310>(H310/2), "Supere la mitad", "Bajo la mitad"))) -> Vencido | N310: CE-GC0368 | O310: 46097 | P310: =IF(OR(O310="", J310=""), "", NETWORKDAYS(J310, O310, FESTIVOS!A309:A363)) -> -4
A311: OTRO | B311: DAGOBERTO POLANIA | C311: USUARIO DE SERVINTEGRAL | D311: SOLICITUD DE PODA | E311: 310 | F311: 46079 | G311: RESIDUOS | H311: =IF(A311="INFORMACIÓN O DOCUMENTOS", 10, IF(A311="CONSULTA", 30, IF(A311="FACTURACIÓN Y COBROS", 15, IF(A311="VINCULACIÓN Y DESVINCULACIÓN", 15, IF(A311="NO ES DE NUESTRA COMPETENCIA", 5, IF(A311="OTRO", 15, "")))))) -> 15 | I311: =IF(AND(F311<>"", J311<>""), NETWORKDAYS(TODAY(), J311-1, FESTIVOS!A$1:A$55), "") -> -56 | J311: =IF(AND(F311<>"", H311<>""), WORKDAY(F311, H311, FESTIVOS!A$1:A$55), "") -> 46100 | K311: LAURA GIRALDO | L311: =IF(I311="", "", MAX(0, I311 - (TODAY() - TODAY()))) -> 0 | M311: =IF(OR(I311="", H311=""), "", IF(I311<0, "Vencido", IF(I311>(H311/2), "Supere la mitad", "Bajo la mitad"))) -> Vencido | N311: CE-GR-0349 | O311: 46093 | P311: ENTREGADO FISICO
A312: OTRO | B312: FREDY HERNAN TEJADA | C312: ELECTROCAQUETA | D312: Respuesta a oficio CE-GC-0225 del 13-02-2026 con Rad interno No 2026-1-1-1160 del 16-02-2026 | E312: 311 | F312: 46079 | G312: COMERCIAL | H312: =IF(A312="INFORMACIÓN O DOCUMENTOS", 10, IF(A312="CONSULTA", 30, IF(A312="FACTURACIÓN Y COBROS", 15, IF(A312="VINCULACIÓN Y DESVINCULACIÓN", 15, IF(A312="NO ES DE NUESTRA COMPETENCIA", 5, IF(A312="OTRO", 15, "")))))) -> 15 | I312: =IF(AND(F312<>"", J312<>""), NETWORKDAYS(TODAY(), J312-1, FESTIVOS!A$1:A$55), "") -> -56 | J312: =IF(AND(F312<>"", H312<>""), WORKDAY(F312, H312, FESTIVOS!A$1:A$55), "") -> 46100 | K312: LAURA GIRALDO | L312: =IF(I312="", "", MAX(0, I312 - (TODAY() - TODAY()))) -> 0 | M312: =IF(OR(I312="", H312=""), "", IF(I312<0, "Vencido", IF(I312>(H312/2), "Supere la mitad", "Bajo la mitad"))) -> Vencido | N312: NO REQUIERE RESPUESTA | P312: =IF(OR(O312="", J312=""), "", NETWORKDAYS(J312, O312, FESTIVOS!A311:A365))
A313: OTRO | B313: YESENNIA MONSALVE | C313: SERVAF | D313: Traslado por competencias Radicado E-2026010000382 del 11/02/2026 | E313: 312 | F313: 46079 | G313: COMERCIAL | H313: =IF(A313="INFORMACIÓN O DOCUMENTOS", 10, IF(A313="CONSULTA", 30, IF(A313="FACTURACIÓN Y COBROS", 15, IF(A313="VINCULACIÓN Y DESVINCULACIÓN", 15, IF(A313="NO ES DE NUESTRA COMPETENCIA", 5, IF(A313="OTRO", 15, "")))))) -> 15 | I313: =IF(AND(F313<>"", J313<>""), NETWORKDAYS(TODAY(), J313-1, FESTIVOS!A$1:A$55), "") -> -56 | J313: =IF(AND(F313<>"", H313<>""), WORKDAY(F313, H313, FESTIVOS!A$1:A$55), "") -> 46100 | K313: LAURA GIRALDO | L313: =IF(I313="", "", MAX(0, I313 - (TODAY() - TODAY()))) -> 0 | M313: =IF(OR(I313="", H313=""), "", IF(I313<0, "Vencido", IF(I313>(H313/2), "Supere la mitad", "Bajo la mitad"))) -> Vencido | N313: CE-GC-0467 | O313: 46099 | P313: =IF(OR(O313="", J313=""), "", NETWORKDAYS(J313, O313, FESTIVOS!A312:A366)) -> -2
A314: OTRO | B314: Norma Suleiza Mavesoy polanco | C314: USUARIO DE SERVINTEGRAL | D314: SOLICITUD DE PODA | E314: 313 | F314: 46080 | G314: RESIDUOS | H314: =IF(A314="INFORMACIÓN O DOCUMENTOS", 10, IF(A314="CONSULTA", 30, IF(A314="FACTURACIÓN Y COBROS", 15, IF(A314="VINCULACIÓN Y DESVINCULACIÓN", 15, IF(A314="NO ES DE NUESTRA COMPETENCIA", 5, IF(A314="OTRO", 15, "")))))) -> 15 | I314: =IF(AND(F314<>"", J314<>""), NETWORKDAYS(TODAY(), J314-1, FESTIVOS!A$1:A$55), "") -> -55 | J314: =IF(AND(F314<>"", H314<>""), WORKDAY(F314, H314, FESTIVOS!A$1:A$55), "") -> 46101 | K314: LAURA GIRALDO | L314: =IF(I314="", "", MAX(0, I314 - (TODAY() - TODAY()))) -> 0 | M314: =IF(OR(I314="", H314=""), "", IF(I314<0, "Vencido", IF(I314>(H314/2), "Supere la mitad", "Bajo la mitad"))) -> Vencido | N314: CE-GR-0305 | O314: 46084 | P314: =IF(OR(O314="", J314=""), "", NETWORKDAYS(J314, O314, FESTIVOS!A313:A367)) -> -14
A315: OTRO | B315: BELISARIO MONTOYA | C315: USUARIO DE SERVINTEGRAL | D315: Solicitud jornada de trabajo | E315: 314 | F315: 46080 | G315: RESIDUOS | H315: =IF(A315="INFORMACIÓN O DOCUMENTOS", 10, IF(A315="CONSULTA", 30, IF(A315="FACTURACIÓN Y COBROS", 15, IF(A315="VINCULACIÓN Y DESVINCULACIÓN", 15, IF(A315="NO ES DE NUESTRA COMPETENCIA", 5, IF(A315="OTRO", 15, "")))))) -> 15 | I315: =IF(AND(F315<>"", J315<>""), NETWORKDAYS(TODAY(), J315-1, FESTIVOS!A$1:A$55), "") -> -55 | J315: =IF(AND(F315<>"", H315<>""), WORKDAY(F315, H315, FESTIVOS!A$1:A$55), "") -> 46101 | K315: LAURA GIRALDO | L315: =IF(I315="", "", MAX(0, I315 - (TODAY() - TODAY()))) -> 0 | M315: =IF(OR(I315="", H315=""), "", IF(I315<0, "Vencido", IF(I315>(H315/2), "Supere la mitad", "Bajo la mitad"))) -> Vencido | N315: CE-GR-0306 | O315: 46084 | P315: =IF(OR(O315="", J315=""), "", NETWORKDAYS(J315, O315, FESTIVOS!A314:A368)) -> -14
...

Sheet FESTIVOS
A1: 45658
A2: 45663
A3: 45740
A4: 45764
A5: 45765
A6: 45778
A7: 45810
A8: 45831
A9: 45838
A10: 45858
A11: 45876
A12: 45887
... A55: 46746
